Workbook

Sheet 说明
A1: 还债表 · 赛博老爸开源版 v1（2026 年 10 月）
A3: 这张表帮你做三件事：把所有债摊开看清楚；算出每个月至少要赚多少；算出用「雪球法」和「雪崩法」各自哪天能还清。
A5: 怎么用（4 步）
A6: 1. 打开「债务清单」，把每一笔债填进去（最多 10 笔）。里面的 4 行是示例，换成你自己的。
A7: 2. 打开「每月预算」，填收入和必要开支，再填每个月打算多还多少（加速钱），选一种还法。
A8: 3. 看「两种还法对比」：哪种更省利息，哪种能更快清掉第一笔。
A9: 4. 每个月照着「每月还款表」还。每周更新一次「债务清单」里的「还剩多少」。
A11: 颜色说明
A12: 黄底蓝字 = 你要填的格子。黑字 = 自动计算的，不要改。
A13: 「债务清单」里年化超过 24% 的会标红：银行、消费金融、正规网贷的个人贷款，监管要求利息加各种费用的年化不超过 24%，超过的可以打 12378 投诉。
A15: 不知道自己的真实年化？
A16: 用「利率换算」页：日息、月息、分期手续费、只知道每期还多少，都能换算成年化。
... A26: 免责：这张表只做计算，不构成法律意见或投资建议。具体以合同、银行和平台的官方答复为准。

Sheet 债务清单
A1: 债务清单
A2: 黄底蓝字是你要填的。下面 4 行是示例，换成你自己的债（最多 10 笔）。利率填成 18% 这样的格式。
A4: # | B4: 欠谁的 | C4: 类型 | D4: 还剩多少（元） | E4: 真实年化 | F4: 每月最低还款（元） | G4: 每月几号还 | H4: 有没有逾期 | I4: 备注 | J4: 雪球法顺序 | K4: 雪崩法顺序 | L4: 雪球法：第几个月还清 | M4: 雪崩法：第几个月还清 | N4: 有效（辅助） | O4: 年化（辅助）
A5: 1 | B5: 信用卡A | C5: 信用卡 | D5: 38000 | E5: 0.18 | F5: 1900 | G5: 5 | H5: 否 | I5: 示例，换成你自己的 | J5: =IF(N5=1,COUNTIFS($N$5:$N$14,1,$D$5:$D$14,"<"&D5)+COUNTIFS($N$5:$N$14,1,$D$5:$D$14,D5,$A$5:$A$14,"<"&A5)+1,"") -> 4 | K5: =IF(N5=1,COUNTIFS($N$5:$N$14,1,$O$5:$O$14,">"&O5)+COUNTIFS($N$5:$N$14,1,$O$5:$O$14,O5,$A$5:$A$14,"<"&A5)+1,"") -> 2 | L5: =IF(N5=1,INDEX(计算_雪球!$G$5:$G$14,J5),"") -> 19 | M5: =IF(N5=1,INDEX(计算_雪崩!$G$5:$G$14,K5),"") -> 17 | N5: =IF(AND(B5<>"",N(D5)>0),1,0) -> 1 | O5: =IF(N(E5)>1,N(E5)/100,N(E5)) -> 0.18
A6: 2 | B6: 信用卡B（分期） | C6: 信用卡 | D6: 12000 | E6: 0.13 | F6: 1072 | G6: 10 | H6: 否 | I6: 分期手续费换算后约 13% | J6: =IF(N6=1,COUNTIFS($N$5:$N$14,1,$D$5:$D$14,"<"&D6)+COUNTIFS($N$5:$N$14,1,$D$5:$D$14,D6,$A$5:$A$14,"<"&A6)+1,"") -> 1 | K6: =IF(N6=1,COUNTIFS($N$5:$N$14,1,$O$5:$O$14,">"&O6)+COUNTIFS($N$5:$N$14,1,$O$5:$O$14,O6,$A$5:$A$14,"<"&A6)+1,"") -> 3 | L6: =IF(N6=1,INDEX(计算_雪球!$G$5:$G$14,J6),"") -> 7 | M6: =IF(N6=1,INDEX(计算_雪崩!$G$5:$G$14,K6),"") -> 12 | N6: =IF(AND(B6<>"",N(D6)>0),1,0) -> 1 | O6: =IF(N(E6)>1,N(E6)/100,N(E6)) -> 0.13
A7: 3 | B7: 网贷X | C7: 网贷 | D7: 25000 | E7: 0.24 | F7: 1350 | G7: 15 | H7: 否 | J7: =IF(N7=1,COUNTIFS($N$5:$N$14,1,$D$5:$D$14,"<"&D7)+COUNTIFS($N$5:$N$14,1,$D$5:$D$14,D7,$A$5:$A$14,"<"&A7)+1,"") -> 3 | K7: =IF(N7=1,COUNTIFS($N$5:$N$14,1,$O$5:$O$14,">"&O7)+COUNTIFS($N$5:$N$14,1,$O$5:$O$14,O7,$A$5:$A$14,"<"&A7)+1,"") -> 1 | L7: =IF(N7=1,INDEX(计算_雪球!$G$5:$G$14,J7),"") -> 17 | M7: =IF(N7=1,INDEX(计算_雪崩!$G$5:$G$14,K7),"") -> 13 | N7: =IF(AND(B7<>"",N(D7)>0),1,0) -> 1 | O7: =IF(N(E7)>1,N(E7)/100,N(E7)) -> 0.24
A8: 4 | B8: 亲友借款（老王） | C8: 亲友借款 | D8: 20000 | E8: 0 | F8: 500 | G8: 1 | H8: 否 | I8: 说好每月还 500 | J8: =IF(N8=1,COUNTIFS($N$5:$N$14,1,$D$5:$D$14,"<"&D8)+COUNTIFS($N$5:$N$14,1,$D$5:$D$14,D8,$A$5:$A$14,"<"&A8)+1,"") -> 2 | K8: =IF(N8=1,COUNTIFS($N$5:$N$14,1,$O$5:$O$14,">"&O8)+COUNTIFS($N$5:$N$14,1,$O$5:$O$14,O8,$A$5:$A$14,"<"&A8)+1,"") -> 4 | L8: =IF(N8=1,INDEX(计算_雪球!$G$5:$G$14,J8),"") -> 13 | M8: =IF(N8=1,INDEX(计算_雪崩!$G$5:$G$14,K8),"") -> 19 | N8: =IF(AND(B8<>"",N(D8)>0),1,0) -> 1 | O8: =IF(N(E8)>1,N(E8)/100,N(E8)) -> 0
A9: 5 | J9: =IF(N9=1,COUNTIFS($N$5:$N$14,1,$D$5:$D$14,"<"&D9)+COUNTIFS($N$5:$N$14,1,$D$5:$D$14,D9,$A$5:$A$14,"<"&A9)+1,"") | K9: =IF(N9=1,COUNTIFS($N$5:$N$14,1,$O$5:$O$14,">"&O9)+COUNTIFS($N$5:$N$14,1,$O$5:$O$14,O9,$A$5:$A$14,"<"&A9)+1,"") | L9: =IF(N9=1,INDEX(计算_雪球!$G$5:$G$14,J9),"") | M9: =IF(N9=1,INDEX(计算_雪崩!$G$5:$G$14,K9),"") | N9: =IF(AND(B9<>"",N(D9)>0),1,0) -> 0 | O9: =IF(N(E9)>1,N(E9)/100,N(E9)) -> 0
A10: 6 | J10: =IF(N10=1,COUNTIFS($N$5:$N$14,1,$D$5:$D$14,"<"&D10)+COUNTIFS($N$5:$N$14,1,$D$5:$D$14,D10,$A$5:$A$14,"<"&A10)+1,"") | K10: =IF(N10=1,COUNTIFS($N$5:$N$14,1,$O$5:$O$14,">"&O10)+COUNTIFS($N$5:$N$14,1,$O$5:$O$14,O10,$A$5:$A$14,"<"&A10)+1,"") | L10: =IF(N10=1,INDEX(计算_雪球!$G$5:$G$14,J10),"") | M10: =IF(N10=1,INDEX(计算_雪崩!$G$5:$G$14,K10),"") | N10: =IF(AND(B10<>"",N(D10)>0),1,0) -> 0 | O10: =IF(N(E10)>1,N(E10)/100,N(E10)) -> 0
A11: 7 | J11: =IF(N11=1,COUNTIFS($N$5:$N$14,1,$D$5:$D$14,"<"&D11)+COUNTIFS($N$5:$N$14,1,$D$5:$D$14,D11,$A$5:$A$14,"<"&A11)+1,"") | K11: =IF(N11=1,COUNTIFS($N$5:$N$14,1,$O$5:$O$14,">"&O11)+COUNTIFS($N$5:$N$14,1,$O$5:$O$14,O11,$A$5:$A$14,"<"&A11)+1,"") | L11: =IF(N11=1,INDEX(计算_雪球!$G$5:$G$14,J11),"") | M11: =IF(N11=1,INDEX(计算_雪崩!$G$5:$G$14,K11),"") | N11: =IF(AND(B11<>"",N(D11)>0),1,0) -> 0 | O11: =IF(N(E11)>1,N(E11)/100,N(E11)) -> 0
A12: 8 | J12: =IF(N12=1,COUNTIFS($N$5:$N$14,1,$D$5:$D$14,"<"&D12)+COUNTIFS($N$5:$N$14,1,$D$5:$D$14,D12,$A$5:$A$14,"<"&A12)+1,"") | K12: =IF(N12=1,COUNTIFS($N$5:$N$14,1,$O$5:$O$14,">"&O12)+COUNTIFS($N$5:$N$14,1,$O$5:$O$14,O12,$A$5:$A$14,"<"&A12)+1,"") | L12: =IF(N12=1,INDEX(计算_雪球!$G$5:$G$14,J12),"") | M12: =IF(N12=1,INDEX(计算_雪崩!$G$5:$G$14,K12),"") | N12: =IF(AND(B12<>"",N(D12)>0),1,0) -> 0 | O12: =IF(N(E12)>1,N(E12)/100,N(E12)) -> 0
A13: 9 | J13: =IF(N13=1,COUNTIFS($N$5:$N$14,1,$D$5:$D$14,"<"&D13)+COUNTIFS($N$5:$N$14,1,$D$5:$D$14,D13,$A$5:$A$14,"<"&A13)+1,"") | K13: =IF(N13=1,COUNTIFS($N$5:$N$14,1,$O$5:$O$14,">"&O13)+COUNTIFS($N$5:$N$14,1,$O$5:$O$14,O13,$A$5:$A$14,"<"&A13)+1,"") | L13: =IF(N13=1,INDEX(计算_雪球!$G$5:$G$14,J13),"") | M13: =IF(N13=1,INDEX(计算_雪崩!$G$5:$G$14,K13),"") | N13: =IF(AND(B13<>"",N(D13)>0),1,0) -> 0 | O13: =IF(N(E13)>1,N(E13)/100,N(E13)) -> 0
A14: 10 | J14: =IF(N14=1,COUNTIFS($N$5:$N$14,1,$D$5:$D$14,"<"&D14)+COUNTIFS($N$5:$N$14,1,$D$5:$D$14,D14,$A$5:$A$14,"<"&A14)+1,"") | K14: =IF(N14=1,COUNTIFS($N$5:$N$14,1,$O$5:$O$14,">"&O14)+COUNTIFS($N$5:$N$14,1,$O$5:$O$14,O14,$A$5:$A$14,"<"&A14)+1,"") | L14: =IF(N14=1,INDEX(计算_雪球!$G$5:$G$14,J14),"") | M14: =IF(N14=1,INDEX(计算_雪崩!$G$5:$G$14,K14),"") | N14: =IF(AND(B14<>"",N(D14)>0),1,0) -> 0 | O14: =IF(N(E14)>1,N(E14)/100,N(E14)) -> 0
B15: 合计 | D15: =SUMIF($N$5:$N$14,1,D5:D14) -> 95000 | F15: =SUMIF($N$5:$N$14,1,F5:F14) -> 4822
A17: 年化超过 24% 的会标红：持牌机构的个人贷款，监管要求综合年化不超过 24%，可以打 12378 投诉。不知道年化？用「利率换算」页。

Sheet 每月预算
A1: 每月预算
A2: 黄底蓝字是你要填的，按一个月来算。
A4: 每月收入
A5: 工资 / 主业 | B5: 9500
A6: 副业 | B6: 2000
A7: 其他收入 | B7: 0
A8: 收入合计 | B8: =SUM(B5:B7) -> 11500
A10: 每月必要开支
A11: 房租 / 房贷 | B11: 2000
A12: 吃饭 | B12: 1500
A13: 交通 | B13: 300
A14: 水电、话费、网费 | B14: 300
A15: 孩子、赡养老人 | B15: 800
A16: 保险、看病 | B16: 200
A17: 其他必要开支 | B17: 200
A18: 零花钱（建议留一点，不然坚持不下去） | B18: 300
A19: 开支合计 | B19: =SUM(B11:B18) -> 5600
A21: 还债
A22: 所有债的最低还款合计 | B22: =债务清单!F15 -> 4822 | C22: 自动从「债务清单」拿过来
A23: 每个月至少要赚多少 | B23: =B19+B22 -> 10422 | C23: 也就是：必要开支 + 所有最低还款。低于这个数，就会越欠越多
A24: 每月结余（收入 − 开支 − 最低还款） | B24: =B8-B19-B22 -> 1078 | C24: =IF(B24<0,"【注意】收入不够还最低还款。先看 SOP 第三步，去协商降低月供","收入够覆盖最低还款") -> 收入够覆盖最低还款
A26: 每月打算多还的「加速钱」 | B26: 1000 | C26: =IF(N(B26)>MAX(0,B24),"【注意】加速钱比结余还多，月底会不够用","最多可以拿出 "&TEXT(MAX(0,B24),"#,##0")&" 元") -> 最多可以拿出 1,078 元
A27: 每月还款总预算（最低还款 + 加速钱） | B27: =B22+N(B26) -> 5822
A29: 还款办法 | B29: 雪球法 | C29: 雪球法 = 先还金额最小的；雪崩法 = 先还利息最高的
A30: 从哪个月开始 | B30: 46327
A32: 结果
A33: 还清需要几个月 | B33: =IF($B$29="雪崩法",计算_雪崩!C18,计算_雪球!C18) -> 19
A34: 预计哪个月还清 | B34: =IF(ISNUMBER(B33),IF(B33>0,EDATE(B30,B33-1),""),B33) -> 46874
A35: 总共要付的利息 | B35: =IF($B$29="雪崩法",计算_雪崩!C19,计算_雪球!C19) -> 12947.34
A36: 第一笔债第几个月还清 | B36: =IF($B$29="雪崩法",计算_雪崩!C20,计算_雪球!C20) -> 7

Sheet 两种还法对比
A1: 两种还法对比
A2: 两种办法用的是同一笔「每月还款总预算」，只是加速钱砸向的顺序不同。
B4: 雪球法（先还金额最小的） | C4: 雪崩法（先还利息最高的）
A5: 还清需要几个月 | B5: =计算_雪球!C18 -> 19 | C5: =计算_雪崩!C18 -> 19
A6: 预计哪个月还清 | B6: =IF(ISNUMBER(B5),IF(B5>0,EDATE(每月预算!$B$30,B5-1),""),B5) -> 46874 | C6: =IF(ISNUMBER(C5),IF(C5>0,EDATE(每月预算!$B$30,C5-1),""),C5) -> 46874
A7: 总共要付的利息 | B7: =计算_雪球!C19 -> 12947.34 | C7: =计算_雪崩!C19 -> 10505.63
A8: 第一笔债第几个月还清 | B8: =计算_雪球!C20 -> 7 | C8: =计算_雪崩!C20 -> 12
A10: 怎么选
A11: =IF(AND(ISNUMBER(B7),ISNUMBER(C7)),IF(B7-C7>=1,"雪崩法能少付 "&TEXT(B7-C7,"#,##0")&" 元利息；雪球法清掉第一笔会早一些（第 "&B8&" 个月 vs 第 "&C8&" 个月）。想省钱选雪崩法，怕坚持不住选雪球法。","两种办法差别不大，选让你更有动力的那个就行。"),"") -> 雪崩法能少付 2,442 元利息；雪球法清掉第一笔会早一些（第 7 个月 vs 第 12 个月）。想省钱选雪崩法，怕坚持不住选雪球法。
A14: 还款顺序 | B14: 雪球法：先还哪笔 | C14: 第几个月还清 | D14: 雪崩法：先还哪笔 | E14: 第几个月还清
A15: 1 | B15: =计算_雪球!C5 -> 信用卡B（分期） | C15: =计算_雪球!G5 -> 7 | D15: =计算_雪崩!C5 -> 网贷X | E15: =计算_雪崩!G5 -> 13
A16: 2 | B16: =计算_雪球!C6 -> 亲友借款（老王） | C16: =计算_雪球!G6 -> 13 | D16: =计算_雪崩!C6 -> 信用卡A | E16: =计算_雪崩!G6 -> 17
A17: 3 | B17: =计算_雪球!C7 -> 网贷X | C17: =计算_雪球!G7 -> 17 | D17: =计算_雪崩!C7 -> 信用卡B（分期） | E17: =计算_雪崩!G7 -> 12
A18: 4 | B18: =计算_雪球!C8 -> 信用卡A | C18: =计算_雪球!G8 -> 19 | D18: =计算_雪崩!C8 -> 亲友借款（老王） | E18: =计算_雪崩!G8 -> 19
A19: 5 | B19: =计算_雪球!C9 | C19: =计算_雪球!G9 | D19: =计算_雪崩!C9 | E19: =计算_雪崩!G9
A20: 6 | B20: =计算_雪球!C10 | C20: =计算_雪球!G10 | D20: =计算_雪崩!C10 | E20: =计算_雪崩!G10
A21: 7 | B21: =计算_雪球!C11 | C21: =计算_雪球!G11 | D21: =计算_雪崩!C11 | E21: =计算_雪崩!G11
A22: 8 | B22: =计算_雪球!C12 | C22: =计算_雪球!G12 | D22: =计算_雪崩!C12 | E22: =计算_雪崩!G12
A23: 9 | B23: =计算_雪球!C13 | C23: =计算_雪球!G13 | D23: =计算_雪崩!C13 | E23: =计算_雪崩!G13
A24: 10 | B24: =计算_雪球!C14 | C24: =计算_雪球!G14 | D24: =计算_雪崩!C14 | E24: =计算_雪崩!G14

Sheet 每月还款表
A1: ="每月还款表（"&每月预算!B29&"）" -> 每月还款表（雪球法）
A2: 每个月照着这张表还。「加速钱给了」那一列，就是这个月要多还的那一笔。想换办法，去「每月预算」改。 | Q2: 显示月数（辅助） | R2: =IF(ISNUMBER(每月预算!B33),每月预算!B33,240) -> 19
A4: 月份 | B4: 日期 | C4: =IF(每月预算!$B$29="雪崩法",计算_雪崩!$C$5,计算_雪球!$C$5) -> 信用卡B（分期） | D4: =IF(每月预算!$B$29="雪崩法",计算_雪崩!$C$6,计算_雪球!$C$6) -> 亲友借款（老王） | E4: =IF(每月预算!$B$29="雪崩法",计算_雪崩!$C$7,计算_雪球!$C$7) -> 网贷X | F4: =IF(每月预算!$B$29="雪崩法",计算_雪崩!$C$8,计算_雪球!$C$8) -> 信用卡A | G4: =IF(每月预算!$B$29="雪崩法",计算_雪崩!$C$9,计算_雪球!$C$9) | H4: =IF(每月预算!$B$29="雪崩法",计算_雪崩!$C$10,计算_雪球!$C$10) | I4: =IF(每月预算!$B$29="雪崩法",计算_雪崩!$C$11,计算_雪球!$C$11) | J4: =IF(每月预算!$B$29="雪崩法",计算_雪崩!$C$12,计算_雪球!$C$12) | K4: =IF(每月预算!$B$29="雪崩法",计算_雪崩!$C$13,计算_雪球!$C$13) | L4: =IF(每月预算!$B$29="雪崩法",计算_雪崩!$C$14,计算_雪球!$C$14) | M4: 本月一共还 | N4: 加速钱给了 | O4: 还完还剩
A5: =IF(1<=$R$2,1,"") -> 1 | B5: =IF($A5="","",计算_雪球!B24) -> 46327 | C5: =IF(OR($A5="",C$4=""),"",IF(每月预算!$B$29="雪崩法",计算_雪崩!I24,计算_雪球!I24)) -> 2072 | D5: =IF(OR($A5="",D$4=""),"",IF(每月预算!$B$29="雪崩法",计算_雪崩!N24,计算_雪球!N24)) -> 500 | E5: =IF(OR($A5="",E$4=""),"",IF(每月预算!$B$29="雪崩法",计算_雪崩!S24,计算_雪球!S24)) -> 1350 | F5: =IF(OR($A5="",F$4=""),"",IF(每月预算!$B$29="雪崩法",计算_雪崩!X24,计算_雪球!X24)) -> 1900 | G5: =IF(OR($A5="",G$4=""),"",IF(每月预算!$B$29="雪崩法",计算_雪崩!AC24,计算_雪球!AC24)) | H5: =IF(OR($A5="",H$4=""),"",IF(每月预算!$B$29="雪崩法",计算_雪崩!AH24,计算_雪球!AH24)) | I5: =IF(OR($A5="",I$4=""),"",IF(每月预算!$B$29="雪崩法",计算_雪崩!AM24,计算_雪球!AM24)) | J5: =IF(OR($A5="",J$4=""),"",IF(每月预算!$B$29="雪崩法",计算_雪崩!AR24,计算_雪球!AR24)) | K5: =IF(OR($A5="",K$4=""),"",IF(每月预算!$B$29="雪崩法",计算_雪崩!AW24,计算_雪球!AW24)) | L5: =IF(OR($A5="",L$4=""),"",IF(每月预算!$B$29="雪崩法",计算_雪崩!BB24,计算_雪球!BB24)) | M5: =IF($A5="","",IF(每月预算!$B$29="雪崩法",计算_雪崩!BC24,计算_雪球!BC24)) -> 5822 | N5: =IF($A5="","",IF(每月预算!$B$29="雪崩法",计算_雪崩!BE24,计算_雪球!BE24)) -> 信用卡B（分期） | O5: =IF($A5="","",IF(每月预算!$B$29="雪崩法",计算_雪崩!BD24,计算_雪球!BD24)) -> 90378
A6: =IF(2<=$R$2,2,"") -> 2 | B6: =IF($A6="","",计算_雪球!B25) -> 46357 | C6: =IF(OR($A6="",C$4=""),"",IF(每月预算!$B$29="雪崩法",计算_雪崩!I25,计算_雪球!I25)) -> 2072 | D6: =IF(OR($A6="",D$4=""),"",IF(每月预算!$B$29="雪崩法",计算_雪崩!N25,计算_雪球!N25)) -> 500 | E6: =IF(OR($A6="",E$4=""),"",IF(每月预算!$B$29="雪崩法",计算_雪崩!S25,计算_雪球!S25)) -> 1350 | F6: =IF(OR($A6="",F$4=""),"",IF(每月预算!$B$29="雪崩法",计算_雪崩!X25,计算_雪球!X25)) -> 1900 | G6: =IF(OR($A6="",G$4=""),"",IF(每月预算!$B$29="雪崩法",计算_雪崩!AC25,计算_雪球!AC25)) | H6: =IF(OR($A6="",H$4=""),"",IF(每月预算!$B$29="雪崩法",计算_雪崩!AH25,计算_雪球!AH25)) | I6: =IF(OR($A6="",I$4=""),"",IF(每月预算!$B$29="雪崩法",计算_雪崩!AM25,计算_雪球!AM25)) | J6: =IF(OR($A6="",J$4=""),"",IF(每月预算!$B$29="雪崩法",计算_雪崩!AR25,计算_雪球!AR25)) | K6: =IF(OR($A6="",K$4=""),"",IF(每月预算!$B$29="雪崩法",计算_雪崩!AW25,计算_雪球!AW25)) | L6: =IF(OR($A6="",L$4=""),"",IF(每月预算!$B$29="雪崩法",计算_雪崩!BB25,计算_雪球!BB25)) | M6: =IF($A6="","",IF(每月预算!$B$29="雪崩法",计算_雪崩!BC25,计算_雪球!BC25)) -> 5822 | N6: =IF($A6="","",IF(每月预算!$B$29="雪崩法",计算_雪崩!BE25,计算_雪球!BE25)) -> 信用卡B（分期） | O6: =IF($A6="","",IF(每月预算!$B$29="雪崩法",计算_雪崩!BD25,计算_雪球!BD25)) -> 85698.01
A7: =IF(3<=$R$2,3,"") -> 3 | B7: =IF($A7="","",计算_雪球!B26) -> 46388 | C7: =IF(OR($A7="",C$4=""),"",IF(每月预算!$B$29="雪崩法",计算_雪崩!I26,计算_雪球!I26)) -> 2072 | D7: =IF(OR($A7="",D$4=""),"",IF(每月预算!$B$29="雪崩法",计算_雪崩!N26,计算_雪球!N26)) -> 500 | E7: =IF(OR($A7="",E$4=""),"",IF(每月预算!$B$29="雪崩法",计算_雪崩!S26,计算_雪球!S26)) -> 1350 | F7: =IF(OR($A7="",F$4=""),"",IF(每月预算!$B$29="雪崩法",计算_雪崩!X26,计算_雪球!X26)) -> 1900 | G7: =IF(OR($A7="",G$4=""),"",IF(每月预算!$B$29="雪崩法",计算_雪崩!AC26,计算_雪球!AC26)) | H7: =IF(OR($A7="",H$4=""),"",IF(每月预算!$B$29="雪崩法",计算_雪崩!AH26,计算_雪球!AH26)) | I7: =IF(OR($A7="",I$4=""),"",IF(每月预算!$B$29="雪崩法",计算_雪崩!AM26,计算_雪球!AM26)) | J7: =IF(OR($A7="",J$4=""),"",IF(每月预算!$B$29="雪崩法",计算_雪崩!AR26,计算_雪球!AR26)) | K7: =IF(OR($A7="",K$4=""),"",IF(每月预算!$B$29="雪崩法",计算_雪崩!AW26,计算_雪球!AW26)) | L7: =IF(OR($A7="",L$4=""),"",IF(每月预算!$B$29="雪崩法",计算_雪崩!BB26,计算_雪球!BB26)) | M7: =IF($A7="","",IF(每月预算!$B$29="雪崩法",计算_雪崩!BC26,计算_雪球!BC26)) -> 5822 | N7: =IF($A7="","",IF(每月预算!$B$29="雪崩法",计算_雪崩!BE26,计算_雪球!BE26)) -> 信用卡B（分期） | O7: =IF($A7="","",IF(每月预算!$B$29="雪崩法",计算_雪崩!BD26,计算_雪球!BD26)) -> 80959.17
A8: =IF(4<=$R$2,4,"") -> 4 | B8: =IF($A8="","",计算_雪球!B27) -> 46419 | C8: =IF(OR($A8="",C$4=""),"",IF(每月预算!$B$29="雪崩法",计算_雪崩!I27,计算_雪球!I27)) -> 2072 | D8: =IF(OR($A8="",D$4=""),"",IF(每月预算!$B$29="雪崩法",计算_雪崩!N27,计算_雪球!N27)) -> 500 | E8: =IF(OR($A8="",E$4=""),"",IF(每月预算!$B$29="雪崩法",计算_雪崩!S27,计算_雪球!S27)) -> 1350 | F8: =IF(OR($A8="",F$4=""),"",IF(每月预算!$B$29="雪崩法",计算_雪崩!X27,计算_雪球!X27)) -> 1900 | G8: =IF(OR($A8="",G$4=""),"",IF(每月预算!$B$29="雪崩法",计算_雪崩!AC27,计算_雪球!AC27)) | H8: =IF(OR($A8="",H$4=""),"",IF(每月预算!$B$29="雪崩法",计算_雪崩!AH27,计算_雪球!AH27)) | I8: =IF(OR($A8="",I$4=""),"",IF(每月预算!$B$29="雪崩法",计算_雪崩!AM27,计算_雪球!AM27)) | J8: =IF(OR($A8="",J$4=""),"",IF(每月预算!$B$29="雪崩法",计算_雪崩!AR27,计算_雪球!AR27)) | K8: =IF(OR($A8="",K$4=""),"",IF(每月预算!$B$29="雪崩法",计算_雪崩!AW27,计算_雪球!AW27)) | L8: =IF(OR($A8="",L$4=""),"",IF(每月预算!$B$29="雪崩法",计算_雪崩!BB27,计算_雪球!BB27)) | M8: =IF($A8="","",IF(每月预算!$B$29="雪崩法",计算_雪崩!BC27,计算_雪球!BC27)) -> 5822 | N8: =IF($A8="","",IF(每月预算!$B$29="雪崩法",计算_雪崩!BE27,计算_雪球!BE27)) -> 信用卡B（分期） | O8: =IF($A8="","",IF(每月预算!$B$29="雪崩法",计算_雪崩!BD27,计算_雪球!BD27)) -> 76160.59
A9: =IF(5<=$R$2,5,"") -> 5 | B9: =IF($A9="","",计算_雪球!B28) -> 46447 | C9: =IF(OR($A9="",C$4=""),"",IF(每月预算!$B$29="雪崩法",计算_雪崩!I28,计算_雪球!I28)) -> 2072 | D9: =IF(OR($A9="",D$4=""),"",IF(每月预算!$B$29="雪崩法",计算_雪崩!N28,计算_雪球!N28)) -> 500 | E9: =IF(OR($A9="",E$4=""),"",IF(每月预算!$B$29="雪崩法",计算_雪崩!S28,计算_雪球!S28)) -> 1350 | F9: =IF(OR($A9="",F$4=""),"",IF(每月预算!$B$29="雪崩法",计算_雪崩!X28,计算_雪球!X28)) -> 1900 | G9: =IF(OR($A9="",G$4=""),"",IF(每月预算!$B$29="雪崩法",计算_雪崩!AC28,计算_雪球!AC28)) | H9: =IF(OR($A9="",H$4=""),"",IF(每月预算!$B$29="雪崩法",计算_雪崩!AH28,计算_雪球!AH28)) | I9: =IF(OR($A9="",I$4=""),"",IF(每月预算!$B$29="雪崩法",计算_雪崩!AM28,计算_雪球!AM28)) | J9: =IF(OR($A9="",J$4=""),"",IF(每月预算!$B$29="雪崩法",计算_雪崩!AR28,计算_雪球!AR28)) | K9: =IF(OR($A9="",K$4=""),"",IF(每月预算!$B$29="雪崩法",计算_雪崩!AW28,计算_雪球!AW28)) | L9: =IF(OR($A9="",L$4=""),"",IF(每月预算!$B$29="雪崩法",计算_雪崩!BB28,计算_雪球!BB28)) | M9: =IF($A9="","",IF(每月预算!$B$29="雪崩法",计算_雪崩!BC28,计算_雪球!BC28)) -> 5822 | N9: =IF($A9="","",IF(每月预算!$B$29="雪崩法",计算_雪崩!BE28,计算_雪球!BE28)) -> 信用卡B（分期） | O9: =IF($A9="","",IF(每月预算!$B$29="雪崩法",计算_雪崩!BD28,计算_雪球!BD28)) -> 71301.38
A10: =IF(6<=$R$2,6,"") -> 6 | B10: =IF($A10="","",计算_雪球!B29) -> 46478 | C10: =IF(OR($A10="",C$4=""),"",IF(每月预算!$B$29="雪崩法",计算_雪崩!I29,计算_雪球!I29)) -> 2072 | D10: =IF(OR($A10="",D$4=""),"",IF(每月预算!$B$29="雪崩法",计算_雪崩!N29,计算_雪球!N29)) -> 500 | E10: =IF(OR($A10="",E$4=""),"",IF(每月预算!$B$29="雪崩法",计算_雪崩!S29,计算_雪球!S29)) -> 1350 | F10: =IF(OR($A10="",F$4=""),"",IF(每月预算!$B$29="雪崩法",计算_雪崩!X29,计算_雪球!X29)) -> 1900 | G10: =IF(OR($A10="",G$4=""),"",IF(每月预算!$B$29="雪崩法",计算_雪崩!AC29,计算_雪球!AC29)) | H10: =IF(OR($A10="",H$4=""),"",IF(每月预算!$B$29="雪崩法",计算_雪崩!AH29,计算_雪球!AH29)) | I10: =IF(OR($A10="",I$4=""),"",IF(每月预算!$B$29="雪崩法",计算_雪崩!AM29,计算_雪球!AM29)) | J10: =IF(OR($A10="",J$4=""),"",IF(每月预算!$B$29="雪崩法",计算_雪崩!AR29,计算_雪球!AR29)) | K10: =IF(OR($A10="",K$4=""),"",IF(每月预算!$B$29="雪崩法",计算_雪崩!AW29,计算_雪球!AW29)) | L10: =IF(OR($A10="",L$4=""),"",IF(每月预算!$B$29="雪崩法",计算_雪崩!BB29,计算_雪球!BB29)) | M10: =IF($A10="","",IF(每月预算!$B$29="雪崩法",计算_雪崩!BC29,计算_雪球!BC29)) -> 5822 | N10: =IF($A10="","",IF(每月预算!$B$29="雪崩法",计算_雪崩!BE29,计算_雪球!BE29)) -> 信用卡B（分期） | O10: =IF($A10="","",IF(每月预算!$B$29="雪崩法",计算_雪崩!BD29,计算_雪球!BD29)) -> 66380.62
A11: =IF(7<=$R$2,7,"") -> 7 | B11: =IF($A11="","",计算_雪球!B30) -> 46508 | C11: =IF(OR($A11="",C$4=""),"",IF(每月预算!$B$29="雪崩法",计算_雪崩!I30,计算_雪球!I30)) -> 28.13 | D11: =IF(OR($A11="",D$4=""),"",IF(每月预算!$B$29="雪崩法",计算_雪崩!N30,计算_雪球!N30)) -> 2543.87 | E11: =IF(OR($A11="",E$4=""),"",IF(每月预算!$B$29="雪崩法",计算_雪崩!S30,计算_雪球!S30)) -> 1350 | F11: =IF(OR($A11="",F$4=""),"",IF(每月预算!$B$29="雪崩法",计算_雪崩!X30,计算_雪球!X30)) -> 1900 | G11: =IF(OR($A11="",G$4=""),"",IF(每月预算!$B$29="雪崩法",计算_雪崩!AC30,计算_雪球!AC30)) | H11: =IF(OR($A11="",H$4=""),"",IF(每月预算!$B$29="雪崩法",计算_雪崩!AH30,计算_雪球!AH30)) | I11: =IF(OR($A11="",I$4=""),"",IF(每月预算!$B$29="雪崩法",计算_雪崩!AM30,计算_雪球!AM30)) | J11: =IF(OR($A11="",J$4=""),"",IF(每月预算!$B$29="雪崩法",计算_雪崩!AR30,计算_雪球!AR30)) | K11: =IF(OR($A11="",K$4=""),"",IF(每月预算!$B$29="雪崩法",计算_雪崩!AW30,计算_雪球!AW30)) | L11: =IF(OR($A11="",L$4=""),"",IF(每月预算!$B$29="雪崩法",计算_雪崩!BB30,计算_雪球!BB30)) | M11: =IF($A11="","",IF(每月预算!$B$29="雪崩法",计算_雪崩!BC30,计算_雪球!BC30)) -> 5822 | N11: =IF($A11="","",IF(每月预算!$B$29="雪崩法",计算_雪崩!BE30,计算_雪球!BE30)) -> 亲友借款（老王） | O11: =IF($A11="","",IF(每月预算!$B$29="雪崩法",计算_雪崩!BD30,计算_雪球!BD30)) -> 61397.4
A12: =IF(8<=$R$2,8,"") -> 8 | B12: =IF($A12="","",计算_雪球!B31) -> 46539 | C12: =IF(OR($A12="",C$4=""),"",IF(每月预算!$B$29="雪崩法",计算_雪崩!I31,计算_雪球!I31)) -> 0 | D12: =IF(OR($A12="",D$4=""),"",IF(每月预算!$B$29="雪崩法",计算_雪崩!N31,计算_雪球!N31)) -> 2572 | E12: =IF(OR($A12="",E$4=""),"",IF(每月预算!$B$29="雪崩法",计算_雪崩!S31,计算_雪球!S31)) -> 1350 | F12: =IF(OR($A12="",F$4=""),"",IF(每月预算!$B$29="雪崩法",计算_雪崩!X31,计算_雪球!X31)) -> 1900 | G12: =IF(OR($A12="",G$4=""),"",IF(每月预算!$B$29="雪崩法",计算_雪崩!AC31,计算_雪球!AC31)) | H12: =IF(OR($A12="",H$4=""),"",IF(每月预算!$B$29="雪崩法",计算_雪崩!AH31,计算_雪球!AH31)) | I12: =IF(OR($A12="",I$4=""),"",IF(每月预算!$B$29="雪崩法",计算_雪崩!AM31,计算_雪球!AM31)) | J12: =IF(OR($A12="",J$4=""),"",IF(每月预算!$B$29="雪崩法",计算_雪崩!AR31,计算_雪球!AR31)) | K12: =IF(OR($A12="",K$4=""),"",IF(每月预算!$B$29="雪崩法",计算_雪崩!AW31,计算_雪球!AW31)) | L12: =IF(OR($A12="",L$4=""),"",IF(每月预算!$B$29="雪崩法",计算_雪崩!BB31,计算_雪球!BB31)) | M12: =IF($A12="","",IF(每月预算!$B$29="雪崩法",计算_雪崩!BC31,计算_雪球!BC31)) -> 5822 | N12: =IF($A12="","",IF(每月预算!$B$29="雪崩法",计算_雪崩!BE31,计算_雪球!BE31)) -> 亲友借款（老王） | O12: =IF($A12="","",IF(每月预算!$B$29="雪崩法",计算_雪崩!BD31,计算_雪球!BD31)) -> 56372.93
A13: =IF(9<=$R$2,9,"") -> 9 | B13: =IF($A13="","",计算_雪球!B32) -> 46569 | C13: =IF(OR($A13="",C$4=""),"",IF(每月预算!$B$29="雪崩法",计算_雪崩!I32,计算_雪球!I32)) -> 0 | D13: =IF(OR($A13="",D$4=""),"",IF(每月预算!$B$29="雪崩法",计算_雪崩!N32,计算_雪球!N32)) -> 2572 | E13: =IF(OR($A13="",E$4=""),"",IF(每月预算!$B$29="雪崩法",计算_雪崩!S32,计算_雪球!S32)) -> 1350 | F13: =IF(OR($A13="",F$4=""),"",IF(每月预算!$B$29="雪崩法",计算_雪崩!X32,计算_雪球!X32)) -> 1900 | G13: =IF(OR($A13="",G$4=""),"",IF(每月预算!$B$29="雪崩法",计算_雪崩!AC32,计算_雪球!AC32)) | H13: =IF(OR($A13="",H$4=""),"",IF(每月预算!$B$29="雪崩法",计算_雪崩!AH32,计算_雪球!AH32)) | I13: =IF(OR($A13="",I$4=""),"",IF(每月预算!$B$29="雪崩法",计算_雪崩!AM32,计算_雪球!AM32)) | J13: =IF(OR($A13="",J$4=""),"",IF(每月预算!$B$29="雪崩法",计算_雪崩!AR32,计算_雪球!AR32)) | K13: =IF(OR($A13="",K$4=""),"",IF(每月预算!$B$29="雪崩法",计算_雪崩!AW32,计算_雪球!AW32)) | L13: =IF(OR($A13="",L$4=""),"",IF(每月预算!$B$29="雪崩法",计算_雪崩!BB32,计算_雪球!BB32)) | M13: =IF($A13="","",IF(每月预算!$B$29="雪崩法",计算_雪崩!BC32,计算_雪球!BC32)) -> 5822 | N13: =IF($A13="","",IF(每月预算!$B$29="雪崩法",计算_雪崩!BE32,计算_雪球!BE32)) -> 亲友借款（老王） | O13: =IF($A13="","",IF(每月预算!$B$29="雪崩法",计算_雪崩!BD32,计算_雪球!BD32)) -> 51306.78
A14: =IF(10<=$R$2,10,"") -> 10 | B14: =IF($A14="","",计算_雪球!B33) -> 46600 | C14: =IF(OR($A14="",C$4=""),"",IF(每月预算!$B$29="雪崩法",计算_雪崩!I33,计算_雪球!I33)) -> 0 | D14: =IF(OR($A14="",D$4=""),"",IF(每月预算!$B$29="雪崩法",计算_雪崩!N33,计算_雪球!N33)) -> 2572 | E14: =IF(OR($A14="",E$4=""),"",IF(每月预算!$B$29="雪崩法",计算_雪崩!S33,计算_雪球!S33)) -> 1350 | F14: =IF(OR($A14="",F$4=""),"",IF(每月预算!$B$29="雪崩法",计算_雪崩!X33,计算_雪球!X33)) -> 1900 | G14: =IF(OR($A14="",G$4=""),"",IF(每月预算!$B$29="雪崩法",计算_雪崩!AC33,计算_雪球!AC33)) | H14: =IF(OR($A14="",H$4=""),"",IF(每月预算!$B$29="雪崩法",计算_雪崩!AH33,计算_雪球!AH33)) | I14: =IF(OR($A14="",I$4=""),"",IF(每月预算!$B$29="雪崩法",计算_雪崩!AM33,计算_雪球!AM33)) | J14: =IF(OR($A14="",J$4=""),"",IF(每月预算!$B$29="雪崩法",计算_雪崩!AR33,计算_雪球!AR33)) | K14: =IF(OR($A14="",K$4=""),"",IF(每月预算!$B$29="雪崩法",计算_雪崩!AW33,计算_雪球!AW33)) | L14: =IF(OR($A14="",L$4=""),"",IF(每月预算!$B$29="雪崩法",计算_雪崩!BB33,计算_雪球!BB33)) | M14: =IF($A14="","",IF(每月预算!$B$29="雪崩法",计算_雪崩!BC33,计算_雪球!BC33)) -> 5822 | N14: =IF($A14="","",IF(每月预算!$B$29="雪崩法",计算_雪崩!BE33,计算_雪球!BE33)) -> 亲友借款（老王） | O14: =IF($A14="","",IF(每月预算!$B$29="雪崩法",计算_雪崩!BD33,计算_雪球!BD33)) -> 46198.24
A15: =IF(11<=$R$2,11,"") -> 11 | B15: =IF($A15="","",计算_雪球!B34) -> 46631 | C15: =IF(OR($A15="",C$4=""),"",IF(每月预算!$B$29="雪崩法",计算_雪崩!I34,计算_雪球!I34)) -> 0 | D15: =IF(OR($A15="",D$4=""),"",IF(每月预算!$B$29="雪崩法",计算_雪崩!N34,计算_雪球!N34)) -> 2572 | E15: =IF(OR($A15="",E$4=""),"",IF(每月预算!$B$29="雪崩法",计算_雪崩!S34,计算_雪球!S34)) -> 1350 | F15: =IF(OR($A15="",F$4=""),"",IF(每月预算!$B$29="雪崩法",计算_雪崩!X34,计算_雪球!X34)) -> 1900 | G15: =IF(OR($A15="",G$4=""),"",IF(每月预算!$B$29="雪崩法",计算_雪崩!AC34,计算_雪球!AC34)) | H15: =IF(OR($A15="",H$4=""),"",IF(每月预算!$B$29="雪崩法",计算_雪崩!AH34,计算_雪球!AH34)) | I15: =IF(OR($A15="",I$4=""),"",IF(每月预算!$B$29="雪崩法",计算_雪崩!AM34,计算_雪球!AM34)) | J15: =IF(OR($A15="",J$4=""),"",IF(每月预算!$B$29="雪崩法",计算_雪崩!AR34,计算_雪球!AR34)) | K15: =IF(OR($A15="",K$4=""),"",IF(每月预算!$B$29="雪崩法",计算_雪崩!AW34,计算_雪球!AW34)) | L15: =IF(OR($A15="",L$4=""),"",IF(每月预算!$B$29="雪崩法",计算_雪崩!BB34,计算_雪球!BB34)) | M15: =IF($A15="","",IF(每月预算!$B$29="雪崩法",计算_雪崩!BC34,计算_雪球!BC34)) -> 5822 | N15: =IF($A15="","",IF(每月预算!$B$29="雪崩法",计算_雪崩!BE34,计算_雪球!BE34)) -> 亲友借款（老王） | O15: =IF($A15="","",IF(每月预算!$B$29="雪崩法",计算_雪崩!BD34,计算_雪球!BD34)) -> 41046.57
A16: =IF(12<=$R$2,12,"") -> 12 | B16: =IF($A16="","",计算_雪球!B35) -> 46661 | C16: =IF(OR($A16="",C$4=""),"",IF(每月预算!$B$29="雪崩法",计算_雪崩!I35,计算_雪球!I35)) -> 0 | D16: =IF(OR($A16="",D$4=""),"",IF(每月预算!$B$29="雪崩法",计算_雪崩!N35,计算_雪球!N35)) -> 2572 | E16: =IF(OR($A16="",E$4=""),"",IF(每月预算!$B$29="雪崩法",计算_雪崩!S35,计算_雪球!S35)) -> 1350 | F16: =IF(OR($A16="",F$4=""),"",IF(每月预算!$B$29="雪崩法",计算_雪崩!X35,计算_雪球!X35)) -> 1900 | G16: =IF(OR($A16="",G$4=""),"",IF(每月预算!$B$29="雪崩法",计算_雪崩!AC35,计算_雪球!AC35)) | H16: =IF(OR($A16="",H$4=""),"",IF(每月预算!$B$29="雪崩法",计算_雪崩!AH35,计算_雪球!AH35)) | I16: =IF(OR($A16="",I$4=""),"",IF(每月预算!$B$29="雪崩法",计算_雪崩!AM35,计算_雪球!AM35)) | J16: =IF(OR($A16="",J$4=""),"",IF(每月预算!$B$29="雪崩法",计算_雪崩!AR35,计算_雪球!AR35)) | K16: =IF(OR($A16="",K$4=""),"",IF(每月预算!$B$29="雪崩法",计算_雪崩!AW35,计算_雪球!AW35)) | L16: =IF(OR($A16="",L$4=""),"",IF(每月预算!$B$29="雪崩法",计算_雪崩!BB35,计算_雪球!BB35)) | M16: =IF($A16="","",IF(每月预算!$B$29="雪崩法",计算_雪崩!BC35,计算_雪球!BC35)) -> 5822 | N16: =IF($A16="","",IF(每月预算!$B$29="雪崩法",计算_雪崩!BE35,计算_雪球!BE35)) -> 亲友借款（老王） | O16: =IF($A16="","",IF(每月预算!$B$29="雪崩法",计算_雪崩!BD35,计算_雪球!BD35)) -> 35851.03
A17: =IF(13<=$R$2,13,"") -> 13 | B17: =IF($A17="","",计算_雪球!B36) -> 46692 | C17: =IF(OR($A17="",C$4=""),"",IF(每月预算!$B$29="雪崩法",计算_雪崩!I36,计算_雪球!I36)) -> 0 | D17: =IF(OR($A17="",D$4=""),"",IF(每月预算!$B$29="雪崩法",计算_雪崩!N36,计算_雪球!N36)) -> 1596.13 | E17: =IF(OR($A17="",E$4=""),"",IF(每月预算!$B$29="雪崩法",计算_雪崩!S36,计算_雪球!S36)) -> 2325.87 | F17: =IF(OR($A17="",F$4=""),"",IF(每月预算!$B$29="雪崩法",计算_雪崩!X36,计算_雪球!X36)) -> 1900 | G17: =IF(OR($A17="",G$4=""),"",IF(每月预算!$B$29="雪崩法",计算_雪崩!AC36,计算_雪球!AC36)) | H17: =IF(OR($A17="",H$4=""),"",IF(每月预算!$B$29="雪崩法",计算_雪崩!AH36,计算_雪球!AH36)) | I17: =IF(OR($A17="",I$4=""),"",IF(每月预算!$B$29="雪崩法",计算_雪崩!AM36,计算_雪球!AM36)) | J17: =IF(OR($A17="",J$4=""),"",IF(每月预算!$B$29="雪崩法",计算_雪崩!AR36,计算_雪球!AR36)) | K17: =IF(OR($A17="",K$4=""),"",IF(每月预算!$B$29="雪崩法",计算_雪崩!AW36,计算_雪球!AW36)) | L17: =IF(OR($A17="",L$4=""),"",IF(每月预算!$B$29="雪崩法",计算_雪崩!BB36,计算_雪球!BB36)) | M17: =IF($A17="","",IF(每月预算!$B$29="雪崩法",计算_雪崩!BC36,计算_雪球!BC36)) -> 5822 | N17: =IF($A17="","",IF(每月预算!$B$29="雪崩法",计算_雪崩!BE36,计算_雪球!BE36)) -> 亲友借款（老王） | O17: =IF($A17="","",IF(每月预算!$B$29="雪崩法",计算_雪崩!BD36,计算_雪球!BD36)) -> 30610.85
A18: =IF(14<=$R$2,14,"") -> 14 | B18: =IF($A18="","",计算_雪球!B37) -> 46722 | C18: =IF(OR($A18="",C$4=""),"",IF(每月预算!$B$29="雪崩法",计算_雪崩!I37,计算_雪球!I37)) -> 0 | D18: =IF(OR($A18="",D$4=""),"",IF(每月预算!$B$29="雪崩法",计算_雪崩!N37,计算_雪球!N37)) -> 0 | E18: =IF(OR($A18="",E$4=""),"",IF(每月预算!$B$29="雪崩法",计算_雪崩!S37,计算_雪球!S37)) -> 3922 | F18: =IF(OR($A18="",F$4=""),"",IF(每月预算!$B$29="雪崩法",计算_雪崩!X37,计算_雪球!X37)) -> 1900 | G18: =IF(OR($A18="",G$4=""),"",IF(每月预算!$B$29="雪崩法",计算_雪崩!AC37,计算_雪球!AC37)) | H18: =IF(OR($A18="",H$4=""),"",IF(每月预算!$B$29="雪崩法",计算_雪崩!AH37,计算_雪球!AH37)) | I18: =IF(OR($A18="",I$4=""),"",IF(每月预算!$B$29="雪崩法",计算_雪崩!AM37,计算_雪球!AM37)) | J18: =IF(OR($A18="",J$4=""),"",IF(每月预算!$B$29="雪崩法",计算_雪崩!AR37,计算_雪球!AR37)) | K18: =IF(OR($A18="",K$4=""),"",IF(每月预算!$B$29="雪崩法",计算_雪崩!AW37,计算_雪球!AW37)) | L18: =IF(OR($A18="",L$4=""),"",IF(每月预算!$B$29="雪崩法",计算_雪崩!BB37,计算_雪球!BB37)) | M18: =IF($A18="","",IF(每月预算!$B$29="雪崩法",计算_雪崩!BC37,计算_雪球!BC37)) -> 5822 | N18: =IF($A18="","",IF(每月预算!$B$29="雪崩法",计算_雪崩!BE37,计算_雪球!BE37)) -> 网贷X | O18: =IF($A18="","",IF(每月预算!$B$29="雪崩法",计算_雪崩!BD37,计算_雪球!BD37)) -> 25305.75
A19: =IF(15<=$R$2,15,"") -> 15 | B19: =IF($A19="","",计算_雪球!B38) -> 46753 | C19: =IF(OR($A19="",C$4=""),"",IF(每月预算!$B$29="雪崩法",计算_雪崩!I38,计算_雪球!I38)) -> 0 | D19: =IF(OR($A19="",D$4=""),"",IF(每月预算!$B$29="雪崩法",计算_雪崩!N38,计算_雪球!N38)) -> 0 | E19: =IF(OR($A19="",E$4=""),"",IF(每月预算!$B$29="雪崩法",计算_雪崩!S38,计算_雪球!S38)) -> 3922 | F19: =IF(OR($A19="",F$4=""),"",IF(每月预算!$B$29="雪崩法",计算_雪崩!X38,计算_雪球!X38)) -> 1900 | G19: =IF(OR($A19="",G$4=""),"",IF(每月预算!$B$29="雪崩法",计算_雪崩!AC38,计算_雪球!AC38)) | H19: =IF(OR($A19="",H$4=""),"",IF(每月预算!$B$29="雪崩法",计算_雪崩!AH38,计算_雪球!AH38)) | I19: =IF(OR($A19="",I$4=""),"",IF(每月预算!$B$29="雪崩法",计算_雪崩!AM38,计算_雪球!AM38)) | J19: =IF(OR($A19="",J$4=""),"",IF(每月预算!$B$29="雪崩法",计算_雪崩!AR38,计算_雪球!AR38)) | K19: =IF(OR($A19="",K$4=""),"",IF(每月预算!$B$29="雪崩法",计算_雪崩!AW38,计算_雪球!AW38)) | L19: =IF(OR($A19="",L$4=""),"",IF(每月预算!$B$29="雪崩法",计算_雪崩!BB38,计算_雪球!BB38)) | M19: =IF($A19="","",IF(每月预算!$B$29="雪崩法",计算_雪崩!BC38,计算_雪球!BC38)) -> 5822 | N19: =IF($A19="","",IF(每月预算!$B$29="雪崩法",计算_雪崩!BE38,计算_雪球!BE38)) -> 网贷X | O19: =IF($A19="","",IF(每月预算!$B$29="雪崩法",计算_雪崩!BD38,计算_雪球!BD38)) -> 19902.62
A20: =IF(16<=$R$2,16,"") -> 16 | B20: =IF($A20="","",计算_雪球!B39) -> 46784 | C20: =IF(OR($A20="",C$4=""),"",IF(每月预算!$B$29="雪崩法",计算_雪崩!I39,计算_雪球!I39)) -> 0 | D20: =IF(OR($A20="",D$4=""),"",IF(每月预算!$B$29="雪崩法",计算_雪崩!N39,计算_雪球!N39)) -> 0 | E20: =IF(OR($A20="",E$4=""),"",IF(每月预算!$B$29="雪崩法",计算_雪崩!S39,计算_雪球!S39)) -> 3922 | F20: =IF(OR($A20="",F$4=""),"",IF(每月预算!$B$29="雪崩法",计算_雪崩!X39,计算_雪球!X39)) -> 1900 | G20: =IF(OR($A20="",G$4=""),"",IF(每月预算!$B$29="雪崩法",计算_雪崩!AC39,计算_雪球!AC39)) | H20: =IF(OR($A20="",H$4=""),"",IF(每月预算!$B$29="雪崩法",计算_雪崩!AH39,计算_雪球!AH39)) | I20: =IF(OR($A20="",I$4=""),"",IF(每月预算!$B$29="雪崩法",计算_雪崩!AM39,计算_雪球!AM39)) | J20: =IF(OR($A20="",J$4=""),"",IF(每月预算!$B$29="雪崩法",计算_雪崩!AR39,计算_雪球!AR39)) | K20: =IF(OR($A20="",K$4=""),"",IF(每月预算!$B$29="雪崩法",计算_雪崩!AW39,计算_雪球!AW39)) | L20: =IF(OR($A20="",L$4=""),"",IF(每月预算!$B$29="雪崩法",计算_雪崩!BB39,计算_雪球!BB39)) | M20: =IF($A20="","",IF(每月预算!$B$29="雪崩法",计算_雪崩!BC39,计算_雪球!BC39)) -> 5822 | N20: =IF($A20="","",IF(每月预算!$B$29="雪崩法",计算_雪崩!BE39,计算_雪球!BE39)) -> 网贷X | O20: =IF($A20="","",IF(每月预算!$B$29="雪崩法",计算_雪崩!BD39,计算_雪球!BD39)) -> 14399.61
A21: =IF(17<=$R$2,17,"") -> 17 | B21: =IF($A21="","",计算_雪球!B40) -> 46813 | C21: =IF(OR($A21="",C$4=""),"",IF(每月预算!$B$29="雪崩法",计算_雪崩!I40,计算_雪球!I40)) -> 0 | D21: =IF(OR($A21="",D$4=""),"",IF(每月预算!$B$29="雪崩法",计算_雪崩!N40,计算_雪球!N40)) -> 0 | E21: =IF(OR($A21="",E$4=""),"",IF(每月预算!$B$29="雪崩法",计算_雪崩!S40,计算_雪球!S40)) -> 254.64 | F21: =IF(OR($A21="",F$4=""),"",IF(每月预算!$B$29="雪崩法",计算_雪崩!X40,计算_雪球!X40)) -> 5567.36 | G21: =IF(OR($A21="",G$4=""),"",IF(每月预算!$B$29="雪崩法",计算_雪崩!AC40,计算_雪球!AC40)) | H21: =IF(OR($A21="",H$4=""),"",IF(每月预算!$B$29="雪崩法",计算_雪崩!AH40,计算_雪球!AH40)) | I21: =IF(OR($A21="",I$4=""),"",IF(每月预算!$B$29="雪崩法",计算_雪崩!AM40,计算_雪球!AM40)) | J21: =IF(OR($A21="",J$4=""),"",IF(每月预算!$B$29="雪崩法",计算_雪崩!AR40,计算_雪球!AR40)) | K21: =IF(OR($A21="",K$4=""),"",IF(每月预算!$B$29="雪崩法",计算_雪崩!AW40,计算_雪球!AW40)) | L21: =IF(OR($A21="",L$4=""),"",IF(每月预算!$B$29="雪崩法",计算_雪崩!BB40,计算_雪球!BB40)) | M21: =IF($A21="","",IF(每月预算!$B$29="雪崩法",计算_雪崩!BC40,计算_雪球!BC40)) -> 5822 | N21: =IF($A21="","",IF(每月预算!$B$29="雪崩法",计算_雪崩!BE40,计算_雪球!BE40)) -> 信用卡A | O21: =IF($A21="","",IF(每月预算!$B$29="雪崩法",计算_雪崩!BD40,计算_雪球!BD40)) -> 8794.85
A22: =IF(18<=$R$2,18,"") -> 18 | B22: =IF($A22="","",计算_雪球!B41) -> 46844 | C22: =IF(OR($A22="",C$4=""),"",IF(每月预算!$B$29="雪崩法",计算_雪崩!I41,计算_雪球!I41)) -> 0 | D22: =IF(OR($A22="",D$4=""),"",IF(每月预算!$B$29="雪崩法",计算_雪崩!N41,计算_雪球!N41)) -> 0 | E22: =IF(OR($A22="",E$4=""),"",IF(每月预算!$B$29="雪崩法",计算_雪崩!S41,计算_雪球!S41)) -> 0 | F22: =IF(OR($A22="",F$4=""),"",IF(每月预算!$B$29="雪崩法",计算_雪崩!X41,计算_雪球!X41)) -> 5822 | G22: =IF(OR($A22="",G$4=""),"",IF(每月预算!$B$29="雪崩法",计算_雪崩!AC41,计算_雪球!AC41)) | H22: =IF(OR($A22="",H$4=""),"",IF(每月预算!$B$29="雪崩法",计算_雪崩!AH41,计算_雪球!AH41)) | I22: =IF(OR($A22="",I$4=""),"",IF(每月预算!$B$29="雪崩法",计算_雪崩!AM41,计算_雪球!AM41)) | J22: =IF(OR($A22="",J$4=""),"",IF(每月预算!$B$29="雪崩法",计算_雪崩!AR41,计算_雪球!AR41)) | K22: =IF(OR($A22="",K$4=""),"",IF(每月预算!$B$29="雪崩法",计算_雪崩!AW41,计算_雪球!AW41)) | L22: =IF(OR($A22="",L$4=""),"",IF(每月预算!$B$29="雪崩法",计算_雪崩!BB41,计算_雪球!BB41)) | M22: =IF($A22="","",IF(每月预算!$B$29="雪崩法",计算_雪崩!BC41,计算_雪球!BC41)) -> 5822 | N22: =IF($A22="","",IF(每月预算!$B$29="雪崩法",计算_雪崩!BE41,计算_雪球!BE41)) -> 信用卡A | O22: =IF($A22="","",IF(每月预算!$B$29="雪崩法",计算_雪崩!BD41,计算_雪球!BD41)) -> 3104.77
A23: =IF(19<=$R$2,19,"") -> 19 | B23: =IF($A23="","",计算_雪球!B42) -> 46874 | C23: =IF(OR($A23="",C$4=""),"",IF(每月预算!$B$29="雪崩法",计算_雪崩!I42,计算_雪球!I42)) -> 0 | D23: =IF(OR($A23="",D$4=""),"",IF(每月预算!$B$29="雪崩法",计算_雪崩!N42,计算_雪球!N42)) -> 0 | E23: =IF(OR($A23="",E$4=""),"",IF(每月预算!$B$29="雪崩法",计算_雪崩!S42,计算_雪球!S42)) -> 0 | F23: =IF(OR($A23="",F$4=""),"",IF(每月预算!$B$29="雪崩法",计算_雪崩!X42,计算_雪球!X42)) -> 3151.34 | G23: =IF(OR($A23="",G$4=""),"",IF(每月预算!$B$29="雪崩法",计算_雪崩!AC42,计算_雪球!AC42)) | H23: =IF(OR($A23="",H$4=""),"",IF(每月预算!$B$29="雪崩法",计算_雪崩!AH42,计算_雪球!AH42)) | I23: =IF(OR($A23="",I$4=""),"",IF(每月预算!$B$29="雪崩法",计算_雪崩!AM42,计算_雪球!AM42)) | J23: =IF(OR($A23="",J$4=""),"",IF(每月预算!$B$29="雪崩法",计算_雪崩!AR42,计算_雪球!AR42)) | K23: =IF(OR($A23="",K$4=""),"",IF(每月预算!$B$29="雪崩法",计算_雪崩!AW42,计算_雪球!AW42)) | L23: =IF(OR($A23="",L$4=""),"",IF(每月预算!$B$29="雪崩法",计算_雪崩!BB42,计算_雪球!BB42)) | M23: =IF($A23="","",IF(每月预算!$B$29="雪崩法",计算_雪崩!BC42,计算_雪球!BC42)) -> 3151.34 | N23: =IF($A23="","",IF(每月预算!$B$29="雪崩法",计算_雪崩!BE42,计算_雪球!BE42)) -> 信用卡A | O23: =IF($A23="","",IF(每月预算!$B$29="雪崩法",计算_雪崩!BD42,计算_雪球!BD42)) -> 0
A24: =IF(20<=$R$2,20,"") | B24: =IF($A24="","",计算_雪球!B43) | C24: =IF(OR($A24="",C$4=""),"",IF(每月预算!$B$29="雪崩法",计算_雪崩!I43,计算_雪球!I43)) | D24: =IF(OR($A24="",D$4=""),"",IF(每月预算!$B$29="雪崩法",计算_雪崩!N43,计算_雪球!N43)) | E24: =IF(OR($A24="",E$4=""),"",IF(每月预算!$B$29="雪崩法",计算_雪崩!S43,计算_雪球!S43)) | F24: =IF(OR($A24="",F$4=""),"",IF(每月预算!$B$29="雪崩法",计算_雪崩!X43,计算_雪球!X43)) | G24: =IF(OR($A24="",G$4=""),"",IF(每月预算!$B$29="雪崩法",计算_雪崩!AC43,计算_雪球!AC43)) | H24: =IF(OR($A24="",H$4=""),"",IF(每月预算!$B$29="雪崩法",计算_雪崩!AH43,计算_雪球!AH43)) | I24: =IF(OR($A24="",I$4=""),"",IF(每月预算!$B$29="雪崩法",计算_雪崩!AM43,计算_雪球!AM43)) | J24: =IF(OR($A24="",J$4=""),"",IF(每月预算!$B$29="雪崩法",计算_雪崩!AR43,计算_雪球!AR43)) | K24: =IF(OR($A24="",K$4=""),"",IF(每月预算!$B$29="雪崩法",计算_雪崩!AW43,计算_雪球!AW43)) | L24: =IF(OR($A24="",L$4=""),"",IF(每月预算!$B$29="雪崩法",计算_雪崩!BB43,计算_雪球!BB43)) | M24: =IF($A24="","",IF(每月预算!$B$29="雪崩法",计算_雪崩!BC43,计算_雪球!BC43)) | N24: =IF($A24="","",IF(每月预算!$B$29="雪崩法",计算_雪崩!BE43,计算_雪球!BE43)) | O24: =IF($A24="","",IF(每月预算!$B$29="雪崩法",计算_雪崩!BD43,计算_雪球!BD43))
A25: =IF(21<=$R$2,21,"") | B25: =IF($A25="","",计算_雪球!B44) | C25: =IF(OR($A25="",C$4=""),"",IF(每月预算!$B$29="雪崩法",计算_雪崩!I44,计算_雪球!I44)) | D25: =IF(OR($A25="",D$4=""),"",IF(每月预算!$B$29="雪崩法",计算_雪崩!N44,计算_雪球!N44)) | E25: =IF(OR($A25="",E$4=""),"",IF(每月预算!$B$29="雪崩法",计算_雪崩!S44,计算_雪球!S44)) | F25: =IF(OR($A25="",F$4=""),"",IF(每月预算!$B$29="雪崩法",计算_雪崩!X44,计算_雪球!X44)) | G25: =IF(OR($A25="",G$4=""),"",IF(每月预算!$B$29="雪崩法",计算_雪崩!AC44,计算_雪球!AC44)) | H25: =IF(OR($A25="",H$4=""),"",IF(每月预算!$B$29="雪崩法",计算_雪崩!AH44,计算_雪球!AH44)) | I25: =IF(OR($A25="",I$4=""),"",IF(每月预算!$B$29="雪崩法",计算_雪崩!AM44,计算_雪球!AM44)) | J25: =IF(OR($A25="",J$4=""),"",IF(每月预算!$B$29="雪崩法",计算_雪崩!AR44,计算_雪球!AR44)) | K25: =IF(OR($A25="",K$4=""),"",IF(每月预算!$B$29="雪崩法",计算_雪崩!AW44,计算_雪球!AW44)) | L25: =IF(OR($A25="",L$4=""),"",IF(每月预算!$B$29="雪崩法",计算_雪崩!BB44,计算_雪球!BB44)) | M25: =IF($A25="","",IF(每月预算!$B$29="雪崩法",计算_雪崩!BC44,计算_雪球!BC44)) | N25: =IF($A25="","",IF(每月预算!$B$29="雪崩法",计算_雪崩!BE44,计算_雪球!BE44)) | O25: =IF($A25="","",IF(每月预算!$B$29="雪崩法",计算_雪崩!BD44,计算_雪球!BD44))
A26: =IF(22<=$R$2,22,"") | B26: =IF($A26="","",计算_雪球!B45) | C26: =IF(OR($A26="",C$4=""),"",IF(每月预算!$B$29="雪崩法",计算_雪崩!I45,计算_雪球!I45)) | D26: =IF(OR($A26="",D$4=""),"",IF(每月预算!$B$29="雪崩法",计算_雪崩!N45,计算_雪球!N45)) | E26: =IF(OR($A26="",E$4=""),"",IF(每月预算!$B$29="雪崩法",计算_雪崩!S45,计算_雪球!S45)) | F26: =IF(OR($A26="",F$4=""),"",IF(每月预算!$B$29="雪崩法",计算_雪崩!X45,计算_雪球!X45)) | G26: =IF(OR($A26="",G$4=""),"",IF(每月预算!$B$29="雪崩法",计算_雪崩!AC45,计算_雪球!AC45)) | H26: =IF(OR($A26="",H$4=""),"",IF(每月预算!$B$29="雪崩法",计算_雪崩!AH45,计算_雪球!AH45)) | I26: =IF(OR($A26="",I$4=""),"",IF(每月预算!$B$29="雪崩法",计算_雪崩!AM45,计算_雪球!AM45)) | J26: =IF(OR($A26="",J$4=""),"",IF(每月预算!$B$29="雪崩法",计算_雪崩!AR45,计算_雪球!AR45)) | K26: =IF(OR($A26="",K$4=""),"",IF(每月预算!$B$29="雪崩法",计算_雪崩!AW45,计算_雪球!AW45)) | L26: =IF(OR($A26="",L$4=""),"",IF(每月预算!$B$29="雪崩法",计算_雪崩!BB45,计算_雪球!BB45)) | M26: =IF($A26="","",IF(每月预算!$B$29="雪崩法",计算_雪崩!BC45,计算_雪球!BC45)) | N26: =IF($A26="","",IF(每月预算!$B$29="雪崩法",计算_雪崩!BE45,计算_雪球!BE45)) | O26: =IF($A26="","",IF(每月预算!$B$29="雪崩法",计算_雪崩!BD45,计算_雪球!BD45))
A27: =IF(23<=$R$2,23,"") | B27: =IF($A27="","",计算_雪球!B46) | C27: =IF(OR($A27="",C$4=""),"",IF(每月预算!$B$29="雪崩法",计算_雪崩!I46,计算_雪球!I46)) | D27: =IF(OR($A27="",D$4=""),"",IF(每月预算!$B$29="雪崩法",计算_雪崩!N46,计算_雪球!N46)) | E27: =IF(OR($A27="",E$4=""),"",IF(每月预算!$B$29="雪崩法",计算_雪崩!S46,计算_雪球!S46)) | F27: =IF(OR($A27="",F$4=""),"",IF(每月预算!$B$29="雪崩法",计算_雪崩!X46,计算_雪球!X46)) | G27: =IF(OR($A27="",G$4=""),"",IF(每月预算!$B$29="雪崩法",计算_雪崩!AC46,计算_雪球!AC46)) | H27: =IF(OR($A27="",H$4=""),"",IF(每月预算!$B$29="雪崩法",计算_雪崩!AH46,计算_雪球!AH46)) | I27: =IF(OR($A27="",I$4=""),"",IF(每月预算!$B$29="雪崩法",计算_雪崩!AM46,计算_雪球!AM46)) | J27: =IF(OR($A27="",J$4=""),"",IF(每月预算!$B$29="雪崩法",计算_雪崩!AR46,计算_雪球!AR46)) | K27: =IF(OR($A27="",K$4=""),"",IF(每月预算!$B$29="雪崩法",计算_雪崩!AW46,计算_雪球!AW46)) | L27: =IF(OR($A27="",L$4=""),"",IF(每月预算!$B$29="雪崩法",计算_雪崩!BB46,计算_雪球!BB46)) | M27: =IF($A27="","",IF(每月预算!$B$29="雪崩法",计算_雪崩!BC46,计算_雪球!BC46)) | N27: =IF($A27="","",IF(每月预算!$B$29="雪崩法",计算_雪崩!BE46,计算_雪球!BE46)) | O27: =IF($A27="","",IF(每月预算!$B$29="雪崩法",计算_雪崩!BD46,计算_雪球!BD46))
A28: =IF(24<=$R$2,24,"") | B28: =IF($A28="","",计算_雪球!B47) | C28: =IF(OR($A28="",C$4=""),"",IF(每月预算!$B$29="雪崩法",计算_雪崩!I47,计算_雪球!I47)) | D28: =IF(OR($A28="",D$4=""),"",IF(每月预算!$B$29="雪崩法",计算_雪崩!N47,计算_雪球!N47)) | E28: =IF(OR($A28="",E$4=""),"",IF(每月预算!$B$29="雪崩法",计算_雪崩!S47,计算_雪球!S47)) | F28: =IF(OR($A28="",F$4=""),"",IF(每月预算!$B$29="雪崩法",计算_雪崩!X47,计算_雪球!X47)) | G28: =IF(OR($A28="",G$4=""),"",IF(每月预算!$B$29="雪崩法",计算_雪崩!AC47,计算_雪球!AC47)) | H28: =IF(OR($A28="",H$4=""),"",IF(每月预算!$B$29="雪崩法",计算_雪崩!AH47,计算_雪球!AH47)) | I28: =IF(OR($A28="",I$4=""),"",IF(每月预算!$B$29="雪崩法",计算_雪崩!AM47,计算_雪球!AM47)) | J28: =IF(OR($A28="",J$4=""),"",IF(每月预算!$B$29="雪崩法",计算_雪崩!AR47,计算_雪球!AR47)) | K28: =IF(OR($A28="",K$4=""),"",IF(每月预算!$B$29="雪崩法",计算_雪崩!AW47,计算_雪球!AW47)) | L28: =IF(OR($A28="",L$4=""),"",IF(每月预算!$B$29="雪崩法",计算_雪崩!BB47,计算_雪球!BB47)) | M28: =IF($A28="","",IF(每月预算!$B$29="雪崩法",计算_雪崩!BC47,计算_雪球!BC47)) | N28: =IF($A28="","",IF(每月预算!$B$29="雪崩法",计算_雪崩!BE47,计算_雪球!BE47)) | O28: =IF($A28="","",IF(每月预算!$B$29="雪崩法",计算_雪崩!BD47,计算_雪球!BD47))
A29: =IF(25<=$R$2,25,"") | B29: =IF($A29="","",计算_雪球!B48) | C29: =IF(OR($A29="",C$4=""),"",IF(每月预算!$B$29="雪崩法",计算_雪崩!I48,计算_雪球!I48)) | D29: =IF(OR($A29="",D$4=""),"",IF(每月预算!$B$29="雪崩法",计算_雪崩!N48,计算_雪球!N48)) | E29: =IF(OR($A29="",E$4=""),"",IF(每月预算!$B$29="雪崩法",计算_雪崩!S48,计算_雪球!S48)) | F29: =IF(OR($A29="",F$4=""),"",IF(每月预算!$B$29="雪崩法",计算_雪崩!X48,计算_雪球!X48)) | G29: =IF(OR($A29="",G$4=""),"",IF(每月预算!$B$29="雪崩法",计算_雪崩!AC48,计算_雪球!AC48)) | H29: =IF(OR($A29="",H$4=""),"",IF(每月预算!$B$29="雪崩法",计算_雪崩!AH48,计算_雪球!AH48)) | I29: =IF(OR($A29="",I$4=""),"",IF(每月预算!$B$29="雪崩法",计算_雪崩!AM48,计算_雪球!AM48)) | J29: =IF(OR($A29="",J$4=""),"",IF(每月预算!$B$29="雪崩法",计算_雪崩!AR48,计算_雪球!AR48)) | K29: =IF(OR($A29="",K$4=""),"",IF(每月预算!$B$29="雪崩法",计算_雪崩!AW48,计算_雪球!AW48)) | L29: =IF(OR($A29="",L$4=""),"",IF(每月预算!$B$29="雪崩法",计算_雪崩!BB48,计算_雪球!BB48)) | M29: =IF($A29="","",IF(每月预算!$B$29="雪崩法",计算_雪崩!BC48,计算_雪球!BC48)) | N29: =IF($A29="","",IF(每月预算!$B$29="雪崩法",计算_雪崩!BE48,计算_雪球!BE48)) | O29: =IF($A29="","",IF(每月预算!$B$29="雪崩法",计算_雪崩!BD48,计算_雪球!BD48))
A30: =IF(26<=$R$2,26,"") | B30: =IF($A30="","",计算_雪球!B49) | C30: =IF(OR($A30="",C$4=""),"",IF(每月预算!$B$29="雪崩法",计算_雪崩!I49,计算_雪球!I49)) | D30: =IF(OR($A30="",D$4=""),"",IF(每月预算!$B$29="雪崩法",计算_雪崩!N49,计算_雪球!N49)) | E30: =IF(OR($A30="",E$4=""),"",IF(每月预算!$B$29="雪崩法",计算_雪崩!S49,计算_雪球!S49)) | F30: =IF(OR($A30="",F$4=""),"",IF(每月预算!$B$29="雪崩法",计算_雪崩!X49,计算_雪球!X49)) | G30: =IF(OR($A30="",G$4=""),"",IF(每月预算!$B$29="雪崩法",计算_雪崩!AC49,计算_雪球!AC49)) | H30: =IF(OR($A30="",H$4=""),"",IF(每月预算!$B$29="雪崩法",计算_雪崩!AH49,计算_雪球!AH49)) | I30: =IF(OR($A30="",I$4=""),"",IF(每月预算!$B$29="雪崩法",计算_雪崩!AM49,计算_雪球!AM49)) | J30: =IF(OR($A30="",J$4=""),"",IF(每月预算!$B$29="雪崩法",计算_雪崩!AR49,计算_雪球!AR49)) | K30: =IF(OR($A30="",K$4=""),"",IF(每月预算!$B$29="雪崩法",计算_雪崩!AW49,计算_雪球!AW49)) | L30: =IF(OR($A30="",L$4=""),"",IF(每月预算!$B$29="雪崩法",计算_雪崩!BB49,计算_雪球!BB49)) | M30: =IF($A30="","",IF(每月预算!$B$29="雪崩法",计算_雪崩!BC49,计算_雪球!BC49)) | N30: =IF($A30="","",IF(每月预算!$B$29="雪崩法",计算_雪崩!BE49,计算_雪球!BE49)) | O30: =IF($A30="","",IF(每月预算!$B$29="雪崩法",计算_雪崩!BD49,计算_雪球!BD49))
A31: =IF(27<=$R$2,27,"") | B31: =IF($A31="","",计算_雪球!B50) | C31: =IF(OR($A31="",C$4=""),"",IF(每月预算!$B$29="雪崩法",计算_雪崩!I50,计算_雪球!I50)) | D31: =IF(OR($A31="",D$4=""),"",IF(每月预算!$B$29="雪崩法",计算_雪崩!N50,计算_雪球!N50)) | E31: =IF(OR($A31="",E$4=""),"",IF(每月预算!$B$29="雪崩法",计算_雪崩!S50,计算_雪球!S50)) | F31: =IF(OR($A31="",F$4=""),"",IF(每月预算!$B$29="雪崩法",计算_雪崩!X50,计算_雪球!X50)) | G31: =IF(OR($A31="",G$4=""),"",IF(每月预算!$B$29="雪崩法",计算_雪崩!AC50,计算_雪球!AC50)) | H31: =IF(OR($A31="",H$4=""),"",IF(每月预算!$B$29="雪崩法",计算_雪崩!AH50,计算_雪球!AH50)) | I31: =IF(OR($A31="",I$4=""),"",IF(每月预算!$B$29="雪崩法",计算_雪崩!AM50,计算_雪球!AM50)) | J31: =IF(OR($A31="",J$4=""),"",IF(每月预算!$B$29="雪崩法",计算_雪崩!AR50,计算_雪球!AR50)) | K31: =IF(OR($A31="",K$4=""),"",IF(每月预算!$B$29="雪崩法",计算_雪崩!AW50,计算_雪球!AW50)) | L31: =IF(OR($A31="",L$4=""),"",IF(每月预算!$B$29="雪崩法",计算_雪崩!BB50,计算_雪球!BB50)) | M31: =IF($A31="","",IF(每月预算!$B$29="雪崩法",计算_雪崩!BC50,计算_雪球!BC50)) | N31: =IF($A31="","",IF(每月预算!$B$29="雪崩法",计算_雪崩!BE50,计算_雪球!BE50)) | O31: =IF($A31="","",IF(每月预算!$B$29="雪崩法",计算_雪崩!BD50,计算_雪球!BD50))
A32: =IF(28<=$R$2,28,"") | B32: =IF($A32="","",计算_雪球!B51) | C32: =IF(OR($A32="",C$4=""),"",IF(每月预算!$B$29="雪崩法",计算_雪崩!I51,计算_雪球!I51)) | D32: =IF(OR($A32="",D$4=""),"",IF(每月预算!$B$29="雪崩法",计算_雪崩!N51,计算_雪球!N51)) | E32: =IF(OR($A32="",E$4=""),"",IF(每月预算!$B$29="雪崩法",计算_雪崩!S51,计算_雪球!S51)) | F32: =IF(OR($A32="",F$4=""),"",IF(每月预算!$B$29="雪崩法",计算_雪崩!X51,计算_雪球!X51)) | G32: =IF(OR($A32="",G$4=""),"",IF(每月预算!$B$29="雪崩法",计算_雪崩!AC51,计算_雪球!AC51)) | H32: =IF(OR($A32="",H$4=""),"",IF(每月预算!$B$29="雪崩法",计算_雪崩!AH51,计算_雪球!AH51)) | I32: =IF(OR($A32="",I$4=""),"",IF(每月预算!$B$29="雪崩法",计算_雪崩!AM51,计算_雪球!AM51)) | J32: =IF(OR($A32="",J$4=""),"",IF(每月预算!$B$29="雪崩法",计算_雪崩!AR51,计算_雪球!AR51)) | K32: =IF(OR($A32="",K$4=""),"",IF(每月预算!$B$29="雪崩法",计算_雪崩!AW51,计算_雪球!AW51)) | L32: =IF(OR($A32="",L$4=""),"",IF(每月预算!$B$29="雪崩法",计算_雪崩!BB51,计算_雪球!BB51)) | M32: =IF($A32="","",IF(每月预算!$B$29="雪崩法",计算_雪崩!BC51,计算_雪球!BC51)) | N32: =IF($A32="","",IF(每月预算!$B$29="雪崩法",计算_雪崩!BE51,计算_雪球!BE51)) | O32: =IF($A32="","",IF(每月预算!$B$29="雪崩法",计算_雪崩!BD51,计算_雪球!BD51))
A33: =IF(29<=$R$2,29,"") | B33: =IF($A33="","",计算_雪球!B52) | C33: =IF(OR($A33="",C$4=""),"",IF(每月预算!$B$29="雪崩法",计算_雪崩!I52,计算_雪球!I52)) | D33: =IF(OR($A33="",D$4=""),"",IF(每月预算!$B$29="雪崩法",计算_雪崩!N52,计算_雪球!N52)) | E33: =IF(OR($A33="",E$4=""),"",IF(每月预算!$B$29="雪崩法",计算_雪崩!S52,计算_雪球!S52)) | F33: =IF(OR($A33="",F$4=""),"",IF(每月预算!$B$29="雪崩法",计算_雪崩!X52,计算_雪球!X52)) | G33: =IF(OR($A33="",G$4=""),"",IF(每月预算!$B$29="雪崩法",计算_雪崩!AC52,计算_雪球!AC52)) | H33: =IF(OR($A33="",H$4=""),"",IF(每月预算!$B$29="雪崩法",计算_雪崩!AH52,计算_雪球!AH52)) | I33: =IF(OR($A33="",I$4=""),"",IF(每月预算!$B$29="雪崩法",计算_雪崩!AM52,计算_雪球!AM52)) | J33: =IF(OR($A33="",J$4=""),"",IF(每月预算!$B$29="雪崩法",计算_雪崩!AR52,计算_雪球!AR52)) | K33: =IF(OR($A33="",K$4=""),"",IF(每月预算!$B$29="雪崩法",计算_雪崩!AW52,计算_雪球!AW52)) | L33: =IF(OR($A33="",L$4=""),"",IF(每月预算!$B$29="雪崩法",计算_雪崩!BB52,计算_雪球!BB52)) | M33: =IF($A33="","",IF(每月预算!$B$29="雪崩法",计算_雪崩!BC52,计算_雪球!BC52)) | N33: =IF($A33="","",IF(每月预算!$B$29="雪崩法",计算_雪崩!BE52,计算_雪球!BE52)) | O33: =IF($A33="","",IF(每月预算!$B$29="雪崩法",计算_雪崩!BD52,计算_雪球!BD52))
A34: =IF(30<=$R$2,30,"") | B34: =IF($A34="","",计算_雪球!B53) | C34: =IF(OR($A34="",C$4=""),"",IF(每月预算!$B$29="雪崩法",计算_雪崩!I53,计算_雪球!I53)) | D34: =IF(OR($A34="",D$4=""),"",IF(每月预算!$B$29="雪崩法",计算_雪崩!N53,计算_雪球!N53)) | E34: =IF(OR($A34="",E$4=""),"",IF(每月预算!$B$29="雪崩法",计算_雪崩!S53,计算_雪球!S53)) | F34: =IF(OR($A34="",F$4=""),"",IF(每月预算!$B$29="雪崩法",计算_雪崩!X53,计算_雪球!X53)) | G34: =IF(OR($A34="",G$4=""),"",IF(每月预算!$B$29="雪崩法",计算_雪崩!AC53,计算_雪球!AC53)) | H34: =IF(OR($A34="",H$4=""),"",IF(每月预算!$B$29="雪崩法",计算_雪崩!AH53,计算_雪球!AH53)) | I34: =IF(OR($A34="",I$4=""),"",IF(每月预算!$B$29="雪崩法",计算_雪崩!AM53,计算_雪球!AM53)) | J34: =IF(OR($A34="",J$4=""),"",IF(每月预算!$B$29="雪崩法",计算_雪崩!AR53,计算_雪球!AR53)) | K34: =IF(OR($A34="",K$4=""),"",IF(每月预算!$B$29="雪崩法",计算_雪崩!AW53,计算_雪球!AW53)) | L34: =IF(OR($A34="",L$4=""),"",IF(每月预算!$B$29="雪崩法",计算_雪崩!BB53,计算_雪球!BB53)) | M34: =IF($A34="","",IF(每月预算!$B$29="雪崩法",计算_雪崩!BC53,计算_雪球!BC53)) | N34: =IF($A34="","",IF(每月预算!$B$29="雪崩法",计算_雪崩!BE53,计算_雪球!BE53)) | O34: =IF($A34="","",IF(每月预算!$B$29="雪崩法",计算_雪崩!BD53,计算_雪球!BD53))
A35: =IF(31<=$R$2,31,"") | B35: =IF($A35="","",计算_雪球!B54) | C35: =IF(OR($A35="",C$4=""),"",IF(每月预算!$B$29="雪崩法",计算_雪崩!I54,计算_雪球!I54)) | D35: =IF(OR($A35="",D$4=""),"",IF(每月预算!$B$29="雪崩法",计算_雪崩!N54,计算_雪球!N54)) | E35: =IF(OR($A35="",E$4=""),"",IF(每月预算!$B$29="雪崩法",计算_雪崩!S54,计算_雪球!S54)) | F35: =IF(OR($A35="",F$4=""),"",IF(每月预算!$B$29="雪崩法",计算_雪崩!X54,计算_雪球!X54)) | G35: =IF(OR($A35="",G$4=""),"",IF(每月预算!$B$29="雪崩法",计算_雪崩!AC54,计算_雪球!AC54)) | H35: =IF(OR($A35="",H$4=""),"",IF(每月预算!$B$29="雪崩法",计算_雪崩!AH54,计算_雪球!AH54)) | I35: =IF(OR($A35="",I$4=""),"",IF(每月预算!$B$29="雪崩法",计算_雪崩!AM54,计算_雪球!AM54)) | J35: =IF(OR($A35="",J$4=""),"",IF(每月预算!$B$29="雪崩法",计算_雪崩!AR54,计算_雪球!AR54)) | K35: =IF(OR($A35="",K$4=""),"",IF(每月预算!$B$29="雪崩法",计算_雪崩!AW54,计算_雪球!AW54)) | L35: =IF(OR($A35="",L$4=""),"",IF(每月预算!$B$29="雪崩法",计算_雪崩!BB54,计算_雪球!BB54)) | M35: =IF($A35="","",IF(每月预算!$B$29="雪崩法",计算_雪崩!BC54,计算_雪球!BC54)) | N35: =IF($A35="","",IF(每月预算!$B$29="雪崩法",计算_雪崩!BE54,计算_雪球!BE54)) | O35: =IF($A35="","",IF(每月预算!$B$29="雪崩法",计算_雪崩!BD54,计算_雪球!BD54))
A36: =IF(32<=$R$2,32,"") | B36: =IF($A36="","",计算_雪球!B55) | C36: =IF(OR($A36="",C$4=""),"",IF(每月预算!$B$29="雪崩法",计算_雪崩!I55,计算_雪球!I55)) | D36: =IF(OR($A36="",D$4=""),"",IF(每月预算!$B$29="雪崩法",计算_雪崩!N55,计算_雪球!N55)) | E36: =IF(OR($A36="",E$4=""),"",IF(每月预算!$B$29="雪崩法",计算_雪崩!S55,计算_雪球!S55)) | F36: =IF(OR($A36="",F$4=""),"",IF(每月预算!$B$29="雪崩法",计算_雪崩!X55,计算_雪球!X55)) | G36: =IF(OR($A36="",G$4=""),"",IF(每月预算!$B$29="雪崩法",计算_雪崩!AC55,计算_雪球!AC55)) | H36: =IF(OR($A36="",H$4=""),"",IF(每月预算!$B$29="雪崩法",计算_雪崩!AH55,计算_雪球!AH55)) | I36: =IF(OR($A36="",I$4=""),"",IF(每月预算!$B$29="雪崩法",计算_雪崩!AM55,计算_雪球!AM55)) | J36: =IF(OR($A36="",J$4=""),"",IF(每月预算!$B$29="雪崩法",计算_雪崩!AR55,计算_雪球!AR55)) | K36: =IF(OR($A36="",K$4=""),"",IF(每月预算!$B$29="雪崩法",计算_雪崩!AW55,计算_雪球!AW55)) | L36: =IF(OR($A36="",L$4=""),"",IF(每月预算!$B$29="雪崩法",计算_雪崩!BB55,计算_雪球!BB55)) | M36: =IF($A36="","",IF(每月预算!$B$29="雪崩法",计算_雪崩!BC55,计算_雪球!BC55)) | N36: =IF($A36="","",IF(每月预算!$B$29="雪崩法",计算_雪崩!BE55,计算_雪球!BE55)) | O36: =IF($A36="","",IF(每月预算!$B$29="雪崩法",计算_雪崩!BD55,计算_雪球!BD55))
A37: =IF(33<=$R$2,33,"") | B37: =IF($A37="","",计算_雪球!B56) | C37: =IF(OR($A37="",C$4=""),"",IF(每月预算!$B$29="雪崩法",计算_雪崩!I56,计算_雪球!I56)) | D37: =IF(OR($A37="",D$4=""),"",IF(每月预算!$B$29="雪崩法",计算_雪崩!N56,计算_雪球!N56)) | E37: =IF(OR($A37="",E$4=""),"",IF(每月预算!$B$29="雪崩法",计算_雪崩!S56,计算_雪球!S56)) | F37: =IF(OR($A37="",F$4=""),"",IF(每月预算!$B$29="雪崩法",计算_雪崩!X56,计算_雪球!X56)) | G37: =IF(OR($A37="",G$4=""),"",IF(每月预算!$B$29="雪崩法",计算_雪崩!AC56,计算_雪球!AC56)) | H37: =IF(OR($A37="",H$4=""),"",IF(每月预算!$B$29="雪崩法",计算_雪崩!AH56,计算_雪球!AH56)) | I37: =IF(OR($A37="",I$4=""),"",IF(每月预算!$B$29="雪崩法",计算_雪崩!AM56,计算_雪球!AM56)) | J37: =IF(OR($A37="",J$4=""),"",IF(每月预算!$B$29="雪崩法",计算_雪崩!AR56,计算_雪球!AR56)) | K37: =IF(OR($A37="",K$4=""),"",IF(每月预算!$B$29="雪崩法",计算_雪崩!AW56,计算_雪球!AW56)) | L37: =IF(OR($A37="",L$4=""),"",IF(每月预算!$B$29="雪崩法",计算_雪崩!BB56,计算_雪球!BB56)) | M37: =IF($A37="","",IF(每月预算!$B$29="雪崩法",计算_雪崩!BC56,计算_雪球!BC56)) | N37: =IF($A37="","",IF(每月预算!$B$29="雪崩法",计算_雪崩!BE56,计算_雪球!BE56)) | O37: =IF($A37="","",IF(每月预算!$B$29="雪崩法",计算_雪崩!BD56,计算_雪球!BD56))
A38: =IF(34<=$R$2,34,"") | B38: =IF($A38="","",计算_雪球!B57) | C38: =IF(OR($A38="",C$4=""),"",IF(每月预算!$B$29="雪崩法",计算_雪崩!I57,计算_雪球!I57)) | D38: =IF(OR($A38="",D$4=""),"",IF(每月预算!$B$29="雪崩法",计算_雪崩!N57,计算_雪球!N57)) | E38: =IF(OR($A38="",E$4=""),"",IF(每月预算!$B$29="雪崩法",计算_雪崩!S57,计算_雪球!S57)) | F38: =IF(OR($A38="",F$4=""),"",IF(每月预算!$B$29="雪崩法",计算_雪崩!X57,计算_雪球!X57)) | G38: =IF(OR($A38="",G$4=""),"",IF(每月预算!$B$29="雪崩法",计算_雪崩!AC57,计算_雪球!AC57)) | H38: =IF(OR($A38="",H$4=""),"",IF(每月预算!$B$29="雪崩法",计算_雪崩!AH57,计算_雪球!AH57)) | I38: =IF(OR($A38="",I$4=""),"",IF(每月预算!$B$29="雪崩法",计算_雪崩!AM57,计算_雪球!AM57)) | J38: =IF(OR($A38="",J$4=""),"",IF(每月预算!$B$29="雪崩法",计算_雪崩!AR57,计算_雪球!AR57)) | K38: =IF(OR($A38="",K$4=""),"",IF(每月预算!$B$29="雪崩法",计算_雪崩!AW57,计算_雪球!AW57)) | L38: =IF(OR($A38="",L$4=""),"",IF(每月预算!$B$29="雪崩法",计算_雪崩!BB57,计算_雪球!BB57)) | M38: =IF($A38="","",IF(每月预算!$B$29="雪崩法",计算_雪崩!BC57,计算_雪球!BC57)) | N38: =IF($A38="","",IF(每月预算!$B$29="雪崩法",计算_雪崩!BE57,计算_雪球!BE57)) | O38: =IF($A38="","",IF(每月预算!$B$29="雪崩法",计算_雪崩!BD57,计算_雪球!BD57))
A39: =IF(35<=$R$2,35,"") | B39: =IF($A39="","",计算_雪球!B58) | C39: =IF(OR($A39="",C$4=""),"",IF(每月预算!$B$29="雪崩法",计算_雪崩!I58,计算_雪球!I58)) | D39: =IF(OR($A39="",D$4=""),"",IF(每月预算!$B$29="雪崩法",计算_雪崩!N58,计算_雪球!N58)) | E39: =IF(OR($A39="",E$4=""),"",IF(每月预算!$B$29="雪崩法",计算_雪崩!S58,计算_雪球!S58)) | F39: =IF(OR($A39="",F$4=""),"",IF(每月预算!$B$29="雪崩法",计算_雪崩!X58,计算_雪球!X58)) | G39: =IF(OR($A39="",G$4=""),"",IF(每月预算!$B$29="雪崩法",计算_雪崩!AC58,计算_雪球!AC58)) | H39: =IF(OR($A39="",H$4=""),"",IF(每月预算!$B$29="雪崩法",计算_雪崩!AH58,计算_雪球!AH58)) | I39: =IF(OR($A39="",I$4=""),"",IF(每月预算!$B$29="雪崩法",计算_雪崩!AM58,计算_雪球!AM58)) | J39: =IF(OR($A39="",J$4=""),"",IF(每月预算!$B$29="雪崩法",计算_雪崩!AR58,计算_雪球!AR58)) | K39: =IF(OR($A39="",K$4=""),"",IF(每月预算!$B$29="雪崩法",计算_雪崩!AW58,计算_雪球!AW58)) | L39: =IF(OR($A39="",L$4=""),"",IF(每月预算!$B$29="雪崩法",计算_雪崩!BB58,计算_雪球!BB58)) | M39: =IF($A39="","",IF(每月预算!$B$29="雪崩法",计算_雪崩!BC58,计算_雪球!BC58)) | N39: =IF($A39="","",IF(每月预算!$B$29="雪崩法",计算_雪崩!BE58,计算_雪球!BE58)) | O39: =IF($A39="","",IF(每月预算!$B$29="雪崩法",计算_雪崩!BD58,计算_雪球!BD58))
A40: =IF(36<=$R$2,36,"") | B40: =IF($A40="","",计算_雪球!B59) | C40: =IF(OR($A40="",C$4=""),"",IF(每月预算!$B$29="雪崩法",计算_雪崩!I59,计算_雪球!I59)) | D40: =IF(OR($A40="",D$4=""),"",IF(每月预算!$B$29="雪崩法",计算_雪崩!N59,计算_雪球!N59)) | E40: =IF(OR($A40="",E$4=""),"",IF(每月预算!$B$29="雪崩法",计算_雪崩!S59,计算_雪球!S59)) | F40: =IF(OR($A40="",F$4=""),"",IF(每月预算!$B$29="雪崩法",计算_雪崩!X59,计算_雪球!X59)) | G40: =IF(OR($A40="",G$4=""),"",IF(每月预算!$B$29="雪崩法",计算_雪崩!AC59,计算_雪球!AC59)) | H40: =IF(OR($A40="",H$4=""),"",IF(每月预算!$B$29="雪崩法",计算_雪崩!AH59,计算_雪球!AH59)) | I40: =IF(OR($A40="",I$4=""),"",IF(每月预算!$B$29="雪崩法",计算_雪崩!AM59,计算_雪球!AM59)) | J40: =IF(OR($A40="",J$4=""),"",IF(每月预算!$B$29="雪崩法",计算_雪崩!AR59,计算_雪球!AR59)) | K40: =IF(OR($A40="",K$4=""),"",IF(每月预算!$B$29="雪崩法",计算_雪崩!AW59,计算_雪球!AW59)) | L40: =IF(OR($A40="",L$4=""),"",IF(每月预算!$B$29="雪崩法",计算_雪崩!BB59,计算_雪球!BB59)) | M40: =IF($A40="","",IF(每月预算!$B$29="雪崩法",计算_雪崩!BC59,计算_雪球!BC59)) | N40: =IF($A40="","",IF(每月预算!$B$29="雪崩法",计算_雪崩!BE59,计算_雪球!BE59)) | O40: =IF($A40="","",IF(每月预算!$B$29="雪崩法",计算_雪崩!BD59,计算_雪球!BD59))
A41: =IF(37<=$R$2,37,"") | B41: =IF($A41="","",计算_雪球!B60) | C41: =IF(OR($A41="",C$4=""),"",IF(每月预算!$B$29="雪崩法",计算_雪崩!I60,计算_雪球!I60)) | D41: =IF(OR($A41="",D$4=""),"",IF(每月预算!$B$29="雪崩法",计算_雪崩!N60,计算_雪球!N60)) | E41: =IF(OR($A41="",E$4=""),"",IF(每月预算!$B$29="雪崩法",计算_雪崩!S60,计算_雪球!S60)) | F41: =IF(OR($A41="",F$4=""),"",IF(每月预算!$B$29="雪崩法",计算_雪崩!X60,计算_雪球!X60)) | G41: =IF(OR($A41="",G$4=""),"",IF(每月预算!$B$29="雪崩法",计算_雪崩!AC60,计算_雪球!AC60)) | H41: =IF(OR($A41="",H$4=""),"",IF(每月预算!$B$29="雪崩法",计算_雪崩!AH60,计算_雪球!AH60)) | I41: =IF(OR($A41="",I$4=""),"",IF(每月预算!$B$29="雪崩法",计算_雪崩!AM60,计算_雪球!AM60)) | J41: =IF(OR($A41="",J$4=""),"",IF(每月预算!$B$29="雪崩法",计算_雪崩!AR60,计算_雪球!AR60)) | K41: =IF(OR($A41="",K$4=""),"",IF(每月预算!$B$29="雪崩法",计算_雪崩!AW60,计算_雪球!AW60)) | L41: =IF(OR($A41="",L$4=""),"",IF(每月预算!$B$29="雪崩法",计算_雪崩!BB60,计算_雪球!BB60)) | M41: =IF($A41="","",IF(每月预算!$B$29="雪崩法",计算_雪崩!BC60,计算_雪球!BC60)) | N41: =IF($A41="","",IF(每月预算!$B$29="雪崩法",计算_雪崩!BE60,计算_雪球!BE60)) | O41: =IF($A41="","",IF(每月预算!$B$29="雪崩法",计算_雪崩!BD60,计算_雪球!BD60))
A42: =IF(38<=$R$2,38,"") | B42: =IF($A42="","",计算_雪球!B61) | C42: =IF(OR($A42="",C$4=""),"",IF(每月预算!$B$29="雪崩法",计算_雪崩!I61,计算_雪球!I61)) | D42: =IF(OR($A42="",D$4=""),"",IF(每月预算!$B$29="雪崩法",计算_雪崩!N61,计算_雪球!N61)) | E42: =IF(OR($A42="",E$4=""),"",IF(每月预算!$B$29="雪崩法",计算_雪崩!S61,计算_雪球!S61)) | F42: =IF(OR($A42="",F$4=""),"",IF(每月预算!$B$29="雪崩法",计算_雪崩!X61,计算_雪球!X61)) | G42: =IF(OR($A42="",G$4=""),"",IF(每月预算!$B$29="雪崩法",计算_雪崩!AC61,计算_雪球!AC61)) | H42: =IF(OR($A42="",H$4=""),"",IF(每月预算!$B$29="雪崩法",计算_雪崩!AH61,计算_雪球!AH61)) | I42: =IF(OR($A42="",I$4=""),"",IF(每月预算!$B$29="雪崩法",计算_雪崩!AM61,计算_雪球!AM61)) | J42: =IF(OR($A42="",J$4=""),"",IF(每月预算!$B$29="雪崩法",计算_雪崩!AR61,计算_雪球!AR61)) | K42: =IF(OR($A42="",K$4=""),"",IF(每月预算!$B$29="雪崩法",计算_雪崩!AW61,计算_雪球!AW61)) | L42: =IF(OR($A42="",L$4=""),"",IF(每月预算!$B$29="雪崩法",计算_雪崩!BB61,计算_雪球!BB61)) | M42: =IF($A42="","",IF(每月预算!$B$29="雪崩法",计算_雪崩!BC61,计算_雪球!BC61)) | N42: =IF($A42="","",IF(每月预算!$B$29="雪崩法",计算_雪崩!BE61,计算_雪球!BE61)) | O42: =IF($A42="","",IF(每月预算!$B$29="雪崩法",计算_雪崩!BD61,计算_雪球!BD61))
A43: =IF(39<=$R$2,39,"") | B43: =IF($A43="","",计算_雪球!B62) | C43: =IF(OR($A43="",C$4=""),"",IF(每月预算!$B$29="雪崩法",计算_雪崩!I62,计算_雪球!I62)) | D43: =IF(OR($A43="",D$4=""),"",IF(每月预算!$B$29="雪崩法",计算_雪崩!N62,计算_雪球!N62)) | E43: =IF(OR($A43="",E$4=""),"",IF(每月预算!$B$29="雪崩法",计算_雪崩!S62,计算_雪球!S62)) | F43: =IF(OR($A43="",F$4=""),"",IF(每月预算!$B$29="雪崩法",计算_雪崩!X62,计算_雪球!X62)) | G43: =IF(OR($A43="",G$4=""),"",IF(每月预算!$B$29="雪崩法",计算_雪崩!AC62,计算_雪球!AC62)) | H43: =IF(OR($A43="",H$4=""),"",IF(每月预算!$B$29="雪崩法",计算_雪崩!AH62,计算_雪球!AH62)) | I43: =IF(OR($A43="",I$4=""),"",IF(每月预算!$B$29="雪崩法",计算_雪崩!AM62,计算_雪球!AM62)) | J43: =IF(OR($A43="",J$4=""),"",IF(每月预算!$B$29="雪崩法",计算_雪崩!AR62,计算_雪球!AR62)) | K43: =IF(OR($A43="",K$4=""),"",IF(每月预算!$B$29="雪崩法",计算_雪崩!AW62,计算_雪球!AW62)) | L43: =IF(OR($A43="",L$4=""),"",IF(每月预算!$B$29="雪崩法",计算_雪崩!BB62,计算_雪球!BB62)) | M43: =IF($A43="","",IF(每月预算!$B$29="雪崩法",计算_雪崩!BC62,计算_雪球!BC62)) | N43: =IF($A43="","",IF(每月预算!$B$29="雪崩法",计算_雪崩!BE62,计算_雪球!BE62)) | O43: =IF($A43="","",IF(每月预算!$B$29="雪崩法",计算_雪崩!BD62,计算_雪球!BD62))
A44: =IF(40<=$R$2,40,"") | B44: =IF($A44="","",计算_雪球!B63) | C44: =IF(OR($A44="",C$4=""),"",IF(每月预算!$B$29="雪崩法",计算_雪崩!I63,计算_雪球!I63)) | D44: =IF(OR($A44="",D$4=""),"",IF(每月预算!$B$29="雪崩法",计算_雪崩!N63,计算_雪球!N63)) | E44: =IF(OR($A44="",E$4=""),"",IF(每月预算!$B$29="雪崩法",计算_雪崩!S63,计算_雪球!S63)) | F44: =IF(OR($A44="",F$4=""),"",IF(每月预算!$B$29="雪崩法",计算_雪崩!X63,计算_雪球!X63)) | G44: =IF(OR($A44="",G$4=""),"",IF(每月预算!$B$29="雪崩法",计算_雪崩!AC63,计算_雪球!AC63)) | H44: =IF(OR($A44="",H$4=""),"",IF(每月预算!$B$29="雪崩法",计算_雪崩!AH63,计算_雪球!AH63)) | I44: =IF(OR($A44="",I$4=""),"",IF(每月预算!$B$29="雪崩法",计算_雪崩!AM63,计算_雪球!AM63)) | J44: =IF(OR($A44="",J$4=""),"",IF(每月预算!$B$29="雪崩法",计算_雪崩!AR63,计算_雪球!AR63)) | K44: =IF(OR($A44="",K$4=""),"",IF(每月预算!$B$29="雪崩法",计算_雪崩!AW63,计算_雪球!AW63)) | L44: =IF(OR($A44="",L$4=""),"",IF(每月预算!$B$29="雪崩法",计算_雪崩!BB63,计算_雪球!BB63)) | M44: =IF($A44="","",IF(每月预算!$B$29="雪崩法",计算_雪崩!BC63,计算_雪球!BC63)) | N44: =IF($A44="","",IF(每月预算!$B$29="雪崩法",计算_雪崩!BE63,计算_雪球!BE63)) | O44: =IF($A44="","",IF(每月预算!$B$29="雪崩法",计算_雪崩!BD63,计算_雪球!BD63))
A45: =IF(41<=$R$2,41,"") | B45: =IF($A45="","",计算_雪球!B64) | C45: =IF(OR($A45="",C$4=""),"",IF(每月预算!$B$29="雪崩法",计算_雪崩!I64,计算_雪球!I64)) | D45: =IF(OR($A45="",D$4=""),"",IF(每月预算!$B$29="雪崩法",计算_雪崩!N64,计算_雪球!N64)) | E45: =IF(OR($A45="",E$4=""),"",IF(每月预算!$B$29="雪崩法",计算_雪崩!S64,计算_雪球!S64)) | F45: =IF(OR($A45="",F$4=""),"",IF(每月预算!$B$29="雪崩法",计算_雪崩!X64,计算_雪球!X64)) | G45: =IF(OR($A45="",G$4=""),"",IF(每月预算!$B$29="雪崩法",计算_雪崩!AC64,计算_雪球!AC64)) | H45: =IF(OR($A45="",H$4=""),"",IF(每月预算!$B$29="雪崩法",计算_雪崩!AH64,计算_雪球!AH64)) | I45: =IF(OR($A45="",I$4=""),"",IF(每月预算!$B$29="雪崩法",计算_雪崩!AM64,计算_雪球!AM64)) | J45: =IF(OR($A45="",J$4=""),"",IF(每月预算!$B$29="雪崩法",计算_雪崩!AR64,计算_雪球!AR64)) | K45: =IF(OR($A45="",K$4=""),"",IF(每月预算!$B$29="雪崩法",计算_雪崩!AW64,计算_雪球!AW64)) | L45: =IF(OR($A45="",L$4=""),"",IF(每月预算!$B$29="雪崩法",计算_雪崩!BB64,计算_雪球!BB64)) | M45: =IF($A45="","",IF(每月预算!$B$29="雪崩法",计算_雪崩!BC64,计算_雪球!BC64)) | N45: =IF($A45="","",IF(每月预算!$B$29="雪崩法",计算_雪崩!BE64,计算_雪球!BE64)) | O45: =IF($A45="","",IF(每月预算!$B$29="雪崩法",计算_雪崩!BD64,计算_雪球!BD64))
A46: =IF(42<=$R$2,42,"") | B46: =IF($A46="","",计算_雪球!B65) | C46: =IF(OR($A46="",C$4=""),"",IF(每月预算!$B$29="雪崩法",计算_雪崩!I65,计算_雪球!I65)) | D46: =IF(OR($A46="",D$4=""),"",IF(每月预算!$B$29="雪崩法",计算_雪崩!N65,计算_雪球!N65)) | E46: =IF(OR($A46="",E$4=""),"",IF(每月预算!$B$29="雪崩法",计算_雪崩!S65,计算_雪球!S65)) | F46: =IF(OR($A46="",F$4=""),"",IF(每月预算!$B$29="雪崩法",计算_雪崩!X65,计算_雪球!X65)) | G46: =IF(OR($A46="",G$4=""),"",IF(每月预算!$B$29="雪崩法",计算_雪崩!AC65,计算_雪球!AC65)) | H46: =IF(OR($A46="",H$4=""),"",IF(每月预算!$B$29="雪崩法",计算_雪崩!AH65,计算_雪球!AH65)) | I46: =IF(OR($A46="",I$4=""),"",IF(每月预算!$B$29="雪崩法",计算_雪崩!AM65,计算_雪球!AM65)) | J46: =IF(OR($A46="",J$4=""),"",IF(每月预算!$B$29="雪崩法",计算_雪崩!AR65,计算_雪球!AR65)) | K46: =IF(OR($A46="",K$4=""),"",IF(每月预算!$B$29="雪崩法",计算_雪崩!AW65,计算_雪球!AW65)) | L46: =IF(OR($A46="",L$4=""),"",IF(每月预算!$B$29="雪崩法",计算_雪崩!BB65,计算_雪球!BB65)) | M46: =IF($A46="","",IF(每月预算!$B$29="雪崩法",计算_雪崩!BC65,计算_雪球!BC65)) | N46: =IF($A46="","",IF(每月预算!$B$29="雪崩法",计算_雪崩!BE65,计算_雪球!BE65)) | O46: =IF($A46="","",IF(每月预算!$B$29="雪崩法",计算_雪崩!BD65,计算_雪球!BD65))
A47: =IF(43<=$R$2,43,"") | B47: =IF($A47="","",计算_雪球!B66) | C47: =IF(OR($A47="",C$4=""),"",IF(每月预算!$B$29="雪崩法",计算_雪崩!I66,计算_雪球!I66)) | D47: =IF(OR($A47="",D$4=""),"",IF(每月预算!$B$29="雪崩法",计算_雪崩!N66,计算_雪球!N66)) | E47: =IF(OR($A47="",E$4=""),"",IF(每月预算!$B$29="雪崩法",计算_雪崩!S66,计算_雪球!S66)) | F47: =IF(OR($A47="",F$4=""),"",IF(每月预算!$B$29="雪崩法",计算_雪崩!X66,计算_雪球!X66)) | G47: =IF(OR($A47="",G$4=""),"",IF(每月预算!$B$29="雪崩法",计算_雪崩!AC66,计算_雪球!AC66)) | H47: =IF(OR($A47="",H$4=""),"",IF(每月预算!$B$29="雪崩法",计算_雪崩!AH66,计算_雪球!AH66)) | I47: =IF(OR($A47="",I$4=""),"",IF(每月预算!$B$29="雪崩法",计算_雪崩!AM66,计算_雪球!AM66)) | J47: =IF(OR($A47="",J$4=""),"",IF(每月预算!$B$29="雪崩法",计算_雪崩!AR66,计算_雪球!AR66)) | K47: =IF(OR($A47="",K$4=""),"",IF(每月预算!$B$29="雪崩法",计算_雪崩!AW66,计算_雪球!AW66)) | L47: =IF(OR($A47="",L$4=""),"",IF(每月预算!$B$29="雪崩法",计算_雪崩!BB66,计算_雪球!BB66)) | M47: =IF($A47="","",IF(每月预算!$B$29="雪崩法",计算_雪崩!BC66,计算_雪球!BC66)) | N47: =IF($A47="","",IF(每月预算!$B$29="雪崩法",计算_雪崩!BE66,计算_雪球!BE66)) | O47: =IF($A47="","",IF(每月预算!$B$29="雪崩法",计算_雪崩!BD66,计算_雪球!BD66))
A48: =IF(44<=$R$2,44,"") | B48: =IF($A48="","",计算_雪球!B67) | C48: =IF(OR($A48="",C$4=""),"",IF(每月预算!$B$29="雪崩法",计算_雪崩!I67,计算_雪球!I67)) | D48: =IF(OR($A48="",D$4=""),"",IF(每月预算!$B$29="雪崩法",计算_雪崩!N67,计算_雪球!N67)) | E48: =IF(OR($A48="",E$4=""),"",IF(每月预算!$B$29="雪崩法",计算_雪崩!S67,计算_雪球!S67)) | F48: =IF(OR($A48="",F$4=""),"",IF(每月预算!$B$29="雪崩法",计算_雪崩!X67,计算_雪球!X67)) | G48: =IF(OR($A48="",G$4=""),"",IF(每月预算!$B$29="雪崩法",计算_雪崩!AC67,计算_雪球!AC67)) | H48: =IF(OR($A48="",H$4=""),"",IF(每月预算!$B$29="雪崩法",计算_雪崩!AH67,计算_雪球!AH67)) | I48: =IF(OR($A48="",I$4=""),"",IF(每月预算!$B$29="雪崩法",计算_雪崩!AM67,计算_雪球!AM67)) | J48: =IF(OR($A48="",J$4=""),"",IF(每月预算!$B$29="雪崩法",计算_雪崩!AR67,计算_雪球!AR67)) | K48: =IF(OR($A48="",K$4=""),"",IF(每月预算!$B$29="雪崩法",计算_雪崩!AW67,计算_雪球!AW67)) | L48: =IF(OR($A48="",L$4=""),"",IF(每月预算!$B$29="雪崩法",计算_雪崩!BB67,计算_雪球!BB67)) | M48: =IF($A48="","",IF(每月预算!$B$29="雪崩法",计算_雪崩!BC67,计算_雪球!BC67)) | N48: =IF($A48="","",IF(每月预算!$B$29="雪崩法",计算_雪崩!BE67,计算_雪球!BE67)) | O48: =IF($A48="","",IF(每月预算!$B$29="雪崩法",计算_雪崩!BD67,计算_雪球!BD67))
A49: =IF(45<=$R$2,45,"") | B49: =IF($A49="","",计算_雪球!B68) | C49: =IF(OR($A49="",C$4=""),"",IF(每月预算!$B$29="雪崩法",计算_雪崩!I68,计算_雪球!I68)) | D49: =IF(OR($A49="",D$4=""),"",IF(每月预算!$B$29="雪崩法",计算_雪崩!N68,计算_雪球!N68)) | E49: =IF(OR($A49="",E$4=""),"",IF(每月预算!$B$29="雪崩法",计算_雪崩!S68,计算_雪球!S68)) | F49: =IF(OR($A49="",F$4=""),"",IF(每月预算!$B$29="雪崩法",计算_雪崩!X68,计算_雪球!X68)) | G49: =IF(OR($A49="",G$4=""),"",IF(每月预算!$B$29="雪崩法",计算_雪崩!AC68,计算_雪球!AC68)) | H49: =IF(OR($A49="",H$4=""),"",IF(每月预算!$B$29="雪崩法",计算_雪崩!AH68,计算_雪球!AH68)) | I49: =IF(OR($A49="",I$4=""),"",IF(每月预算!$B$29="雪崩法",计算_雪崩!AM68,计算_雪球!AM68)) | J49: =IF(OR($A49="",J$4=""),"",IF(每月预算!$B$29="雪崩法",计算_雪崩!AR68,计算_雪球!AR68)) | K49: =IF(OR($A49="",K$4=""),"",IF(每月预算!$B$29="雪崩法",计算_雪崩!AW68,计算_雪球!AW68)) | L49: =IF(OR($A49="",L$4=""),"",IF(每月预算!$B$29="雪崩法",计算_雪崩!BB68,计算_雪球!BB68)) | M49: =IF($A49="","",IF(每月预算!$B$29="雪崩法",计算_雪崩!BC68,计算_雪球!BC68)) | N49: =IF($A49="","",IF(每月预算!$B$29="雪崩法",计算_雪崩!BE68,计算_雪球!BE68)) | O49: =IF($A49="","",IF(每月预算!$B$29="雪崩法",计算_雪崩!BD68,计算_雪球!BD68))
A50: =IF(46<=$R$2,46,"") | B50: =IF($A50="","",计算_雪球!B69) | C50: =IF(OR($A50="",C$4=""),"",IF(每月预算!$B$29="雪崩法",计算_雪崩!I69,计算_雪球!I69)) | D50: =IF(OR($A50="",D$4=""),"",IF(每月预算!$B$29="雪崩法",计算_雪崩!N69,计算_雪球!N69)) | E50: =IF(OR($A50="",E$4=""),"",IF(每月预算!$B$29="雪崩法",计算_雪崩!S69,计算_雪球!S69)) | F50: =IF(OR($A50="",F$4=""),"",IF(每月预算!$B$29="雪崩法",计算_雪崩!X69,计算_雪球!X69)) | G50: =IF(OR($A50="",G$4=""),"",IF(每月预算!$B$29="雪崩法",计算_雪崩!AC69,计算_雪球!AC69)) | H50: =IF(OR($A50="",H$4=""),"",IF(每月预算!$B$29="雪崩法",计算_雪崩!AH69,计算_雪球!AH69)) | I50: =IF(OR($A50="",I$4=""),"",IF(每月预算!$B$29="雪崩法",计算_雪崩!AM69,计算_雪球!AM69)) | J50: =IF(OR($A50="",J$4=""),"",IF(每月预算!$B$29="雪崩法",计算_雪崩!AR69,计算_雪球!AR69)) | K50: =IF(OR($A50="",K$4=""),"",IF(每月预算!$B$29="雪崩法",计算_雪崩!AW69,计算_雪球!AW69)) | L50: =IF(OR($A50="",L$4=""),"",IF(每月预算!$B$29="雪崩法",计算_雪崩!BB69,计算_雪球!BB69)) | M50: =IF($A50="","",IF(每月预算!$B$29="雪崩法",计算_雪崩!BC69,计算_雪球!BC69)) | N50: =IF($A50="","",IF(每月预算!$B$29="雪崩法",计算_雪崩!BE69,计算_雪球!BE69)) | O50: =IF($A50="","",IF(每月预算!$B$29="雪崩法",计算_雪崩!BD69,计算_雪球!BD69))
A51: =IF(47<=$R$2,47,"") | B51: =IF($A51="","",计算_雪球!B70) | C51: =IF(OR($A51="",C$4=""),"",IF(每月预算!$B$29="雪崩法",计算_雪崩!I70,计算_雪球!I70)) | D51: =IF(OR($A51="",D$4=""),"",IF(每月预算!$B$29="雪崩法",计算_雪崩!N70,计算_雪球!N70)) | E51: =IF(OR($A51="",E$4=""),"",IF(每月预算!$B$29="雪崩法",计算_雪崩!S70,计算_雪球!S70)) | F51: =IF(OR($A51="",F$4=""),"",IF(每月预算!$B$29="雪崩法",计算_雪崩!X70,计算_雪球!X70)) | G51: =IF(OR($A51="",G$4=""),"",IF(每月预算!$B$29="雪崩法",计算_雪崩!AC70,计算_雪球!AC70)) | H51: =IF(OR($A51="",H$4=""),"",IF(每月预算!$B$29="雪崩法",计算_雪崩!AH70,计算_雪球!AH70)) | I51: =IF(OR($A51="",I$4=""),"",IF(每月预算!$B$29="雪崩法",计算_雪崩!AM70,计算_雪球!AM70)) | J51: =IF(OR($A51="",J$4=""),"",IF(每月预算!$B$29="雪崩法",计算_雪崩!AR70,计算_雪球!AR70)) | K51: =IF(OR($A51="",K$4=""),"",IF(每月预算!$B$29="雪崩法",计算_雪崩!AW70,计算_雪球!AW70)) | L51: =IF(OR($A51="",L$4=""),"",IF(每月预算!$B$29="雪崩法",计算_雪崩!BB70,计算_雪球!BB70)) | M51: =IF($A51="","",IF(每月预算!$B$29="雪崩法",计算_雪崩!BC70,计算_雪球!BC70)) | N51: =IF($A51="","",IF(每月预算!$B$29="雪崩法",计算_雪崩!BE70,计算_雪球!BE70)) | O51: =IF($A51="","",IF(每月预算!$B$29="雪崩法",计算_雪崩!BD70,计算_雪球!BD70))
A52: =IF(48<=$R$2,48,"") | B52: =IF($A52="","",计算_雪球!B71) | C52: =IF(OR($A52="",C$4=""),"",IF(每月预算!$B$29="雪崩法",计算_雪崩!I71,计算_雪球!I71)) | D52: =IF(OR($A52="",D$4=""),"",IF(每月预算!$B$29="雪崩法",计算_雪崩!N71,计算_雪球!N71)) | E52: =IF(OR($A52="",E$4=""),"",IF(每月预算!$B$29="雪崩法",计算_雪崩!S71,计算_雪球!S71)) | F52: =IF(OR($A52="",F$4=""),"",IF(每月预算!$B$29="雪崩法",计算_雪崩!X71,计算_雪球!X71)) | G52: =IF(OR($A52="",G$4=""),"",IF(每月预算!$B$29="雪崩法",计算_雪崩!AC71,计算_雪球!AC71)) | H52: =IF(OR($A52="",H$4=""),"",IF(每月预算!$B$29="雪崩法",计算_雪崩!AH71,计算_雪球!AH71)) | I52: =IF(OR($A52="",I$4=""),"",IF(每月预算!$B$29="雪崩法",计算_雪崩!AM71,计算_雪球!AM71)) | J52: =IF(OR($A52="",J$4=""),"",IF(每月预算!$B$29="雪崩法",计算_雪崩!AR71,计算_雪球!AR71)) | K52: =IF(OR($A52="",K$4=""),"",IF(每月预算!$B$29="雪崩法",计算_雪崩!AW71,计算_雪球!AW71)) | L52: =IF(OR($A52="",L$4=""),"",IF(每月预算!$B$29="雪崩法",计算_雪崩!BB71,计算_雪球!BB71)) | M52: =IF($A52="","",IF(每月预算!$B$29="雪崩法",计算_雪崩!BC71,计算_雪球!BC71)) | N52: =IF($A52="","",IF(每月预算!$B$29="雪崩法",计算_雪崩!BE71,计算_雪球!BE71)) | O52: =IF($A52="","",IF(每月预算!$B$29="雪崩法",计算_雪崩!BD71,计算_雪球!BD71))
A53: =IF(49<=$R$2,49,"") | B53: =IF($A53="","",计算_雪球!B72) | C53: =IF(OR($A53="",C$4=""),"",IF(每月预算!$B$29="雪崩法",计算_雪崩!I72,计算_雪球!I72)) | D53: =IF(OR($A53="",D$4=""),"",IF(每月预算!$B$29="雪崩法",计算_雪崩!N72,计算_雪球!N72)) | E53: =IF(OR($A53="",E$4=""),"",IF(每月预算!$B$29="雪崩法",计算_雪崩!S72,计算_雪球!S72)) | F53: =IF(OR($A53="",F$4=""),"",IF(每月预算!$B$29="雪崩法",计算_雪崩!X72,计算_雪球!X72)) | G53: =IF(OR($A53="",G$4=""),"",IF(每月预算!$B$29="雪崩法",计算_雪崩!AC72,计算_雪球!AC72)) | H53: =IF(OR($A53="",H$4=""),"",IF(每月预算!$B$29="雪崩法",计算_雪崩!AH72,计算_雪球!AH72)) | I53: =IF(OR($A53="",I$4=""),"",IF(每月预算!$B$29="雪崩法",计算_雪崩!AM72,计算_雪球!AM72)) | J53: =IF(OR($A53="",J$4=""),"",IF(每月预算!$B$29="雪崩法",计算_雪崩!AR72,计算_雪球!AR72)) | K53: =IF(OR($A53="",K$4=""),"",IF(每月预算!$B$29="雪崩法",计算_雪崩!AW72,计算_雪球!AW72)) | L53: =IF(OR($A53="",L$4=""),"",IF(每月预算!$B$29="雪崩法",计算_雪崩!BB72,计算_雪球!BB72)) | M53: =IF($A53="","",IF(每月预算!$B$29="雪崩法",计算_雪崩!BC72,计算_雪球!BC72)) | N53: =IF($A53="","",IF(每月预算!$B$29="雪崩法",计算_雪崩!BE72,计算_雪球!BE72)) | O53: =IF($A53="","",IF(每月预算!$B$29="雪崩法",计算_雪崩!BD72,计算_雪球!BD72))
A54: =IF(50<=$R$2,50,"") | B54: =IF($A54="","",计算_雪球!B73) | C54: =IF(OR($A54="",C$4=""),"",IF(每月预算!$B$29="雪崩法",计算_雪崩!I73,计算_雪球!I73)) | D54: =IF(OR($A54="",D$4=""),"",IF(每月预算!$B$29="雪崩法",计算_雪崩!N73,计算_雪球!N73)) | E54: =IF(OR($A54="",E$4=""),"",IF(每月预算!$B$29="雪崩法",计算_雪崩!S73,计算_雪球!S73)) | F54: =IF(OR($A54="",F$4=""),"",IF(每月预算!$B$29="雪崩法",计算_雪崩!X73,计算_雪球!X73)) | G54: =IF(OR($A54="",G$4=""),"",IF(每月预算!$B$29="雪崩法",计算_雪崩!AC73,计算_雪球!AC73)) | H54: =IF(OR($A54="",H$4=""),"",IF(每月预算!$B$29="雪崩法",计算_雪崩!AH73,计算_雪球!AH73)) | I54: =IF(OR($A54="",I$4=""),"",IF(每月预算!$B$29="雪崩法",计算_雪崩!AM73,计算_雪球!AM73)) | J54: =IF(OR($A54="",J$4=""),"",IF(每月预算!$B$29="雪崩法",计算_雪崩!AR73,计算_雪球!AR73)) | K54: =IF(OR($A54="",K$4=""),"",IF(每月预算!$B$29="雪崩法",计算_雪崩!AW73,计算_雪球!AW73)) | L54: =IF(OR($A54="",L$4=""),"",IF(每月预算!$B$29="雪崩法",计算_雪崩!BB73,计算_雪球!BB73)) | M54: =IF($A54="","",IF(每月预算!$B$29="雪崩法",计算_雪崩!BC73,计算_雪球!BC73)) | N54: =IF($A54="","",IF(每月预算!$B$29="雪崩法",计算_雪崩!BE73,计算_雪球!BE73)) | O54: =IF($A54="","",IF(每月预算!$B$29="雪崩法",计算_雪崩!BD73,计算_雪球!BD73))
A55: =IF(51<=$R$2,51,"") | B55: =IF($A55="","",计算_雪球!B74) | C55: =IF(OR($A55="",C$4=""),"",IF(每月预算!$B$29="雪崩法",计算_雪崩!I74,计算_雪球!I74)) | D55: =IF(OR($A55="",D$4=""),"",IF(每月预算!$B$29="雪崩法",计算_雪崩!N74,计算_雪球!N74)) | E55: =IF(OR($A55="",E$4=""),"",IF(每月预算!$B$29="雪崩法",计算_雪崩!S74,计算_雪球!S74)) | F55: =IF(OR($A55="",F$4=""),"",IF(每月预算!$B$29="雪崩法",计算_雪崩!X74,计算_雪球!X74)) | G55: =IF(OR($A55="",G$4=""),"",IF(每月预算!$B$29="雪崩法",计算_雪崩!AC74,计算_雪球!AC74)) | H55: =IF(OR($A55="",H$4=""),"",IF(每月预算!$B$29="雪崩法",计算_雪崩!AH74,计算_雪球!AH74)) | I55: =IF(OR($A55="",I$4=""),"",IF(每月预算!$B$29="雪崩法",计算_雪崩!AM74,计算_雪球!AM74)) | J55: =IF(OR($A55="",J$4=""),"",IF(每月预算!$B$29="雪崩法",计算_雪崩!AR74,计算_雪球!AR74)) | K55: =IF(OR($A55="",K$4=""),"",IF(每月预算!$B$29="雪崩法",计算_雪崩!AW74,计算_雪球!AW74)) | L55: =IF(OR($A55="",L$4=""),"",IF(每月预算!$B$29="雪崩法",计算_雪崩!BB74,计算_雪球!BB74)) | M55: =IF($A55="","",IF(每月预算!$B$29="雪崩法",计算_雪崩!BC74,计算_雪球!BC74)) | N55: =IF($A55="","",IF(每月预算!$B$29="雪崩法",计算_雪崩!BE74,计算_雪球!BE74)) | O55: =IF($A55="","",IF(每月预算!$B$29="雪崩法",计算_雪崩!BD74,计算_雪球!BD74))
A56: =IF(52<=$R$2,52,"") | B56: =IF($A56="","",计算_雪球!B75) | C56: =IF(OR($A56="",C$4=""),"",IF(每月预算!$B$29="雪崩法",计算_雪崩!I75,计算_雪球!I75)) | D56: =IF(OR($A56="",D$4=""),"",IF(每月预算!$B$29="雪崩法",计算_雪崩!N75,计算_雪球!N75)) | E56: =IF(OR($A56="",E$4=""),"",IF(每月预算!$B$29="雪崩法",计算_雪崩!S75,计算_雪球!S75)) | F56: =IF(OR($A56="",F$4=""),"",IF(每月预算!$B$29="雪崩法",计算_雪崩!X75,计算_雪球!X75)) | G56: =IF(OR($A56="",G$4=""),"",IF(每月预算!$B$29="雪崩法",计算_雪崩!AC75,计算_雪球!AC75)) | H56: =IF(OR($A56="",H$4=""),"",IF(每月预算!$B$29="雪崩法",计算_雪崩!AH75,计算_雪球!AH75)) | I56: =IF(OR($A56="",I$4=""),"",IF(每月预算!$B$29="雪崩法",计算_雪崩!AM75,计算_雪球!AM75)) | J56: =IF(OR($A56="",J$4=""),"",IF(每月预算!$B$29="雪崩法",计算_雪崩!AR75,计算_雪球!AR75)) | K56: =IF(OR($A56="",K$4=""),"",IF(每月预算!$B$29="雪崩法",计算_雪崩!AW75,计算_雪球!AW75)) | L56: =IF(OR($A56="",L$4=""),"",IF(每月预算!$B$29="雪崩法",计算_雪崩!BB75,计算_雪球!BB75)) | M56: =IF($A56="","",IF(每月预算!$B$29="雪崩法",计算_雪崩!BC75,计算_雪球!BC75)) | N56: =IF($A56="","",IF(每月预算!$B$29="雪崩法",计算_雪崩!BE75,计算_雪球!BE75)) | O56: =IF($A56="","",IF(每月预算!$B$29="雪崩法",计算_雪崩!BD75,计算_雪球!BD75))
A57: =IF(53<=$R$2,53,"") | B57: =IF($A57="","",计算_雪球!B76) | C57: =IF(OR($A57="",C$4=""),"",IF(每月预算!$B$29="雪崩法",计算_雪崩!I76,计算_雪球!I76)) | D57: =IF(OR($A57="",D$4=""),"",IF(每月预算!$B$29="雪崩法",计算_雪崩!N76,计算_雪球!N76)) | E57: =IF(OR($A57="",E$4=""),"",IF(每月预算!$B$29="雪崩法",计算_雪崩!S76,计算_雪球!S76)) | F57: =IF(OR($A57="",F$4=""),"",IF(每月预算!$B$29="雪崩法",计算_雪崩!X76,计算_雪球!X76)) | G57: =IF(OR($A57="",G$4=""),"",IF(每月预算!$B$29="雪崩法",计算_雪崩!AC76,计算_雪球!AC76)) | H57: =IF(OR($A57="",H$4=""),"",IF(每月预算!$B$29="雪崩法",计算_雪崩!AH76,计算_雪球!AH76)) | I57: =IF(OR($A57="",I$4=""),"",IF(每月预算!$B$29="雪崩法",计算_雪崩!AM76,计算_雪球!AM76)) | J57: =IF(OR($A57="",J$4=""),"",IF(每月预算!$B$29="雪崩法",计算_雪崩!AR76,计算_雪球!AR76)) | K57: =IF(OR($A57="",K$4=""),"",IF(每月预算!$B$29="雪崩法",计算_雪崩!AW76,计算_雪球!AW76)) | L57: =IF(OR($A57="",L$4=""),"",IF(每月预算!$B$29="雪崩法",计算_雪崩!BB76,计算_雪球!BB76)) | M57: =IF($A57="","",IF(每月预算!$B$29="雪崩法",计算_雪崩!BC76,计算_雪球!BC76)) | N57: =IF($A57="","",IF(每月预算!$B$29="雪崩法",计算_雪崩!BE76,计算_雪球!BE76)) | O57: =IF($A57="","",IF(每月预算!$B$29="雪崩法",计算_雪崩!BD76,计算_雪球!BD76))
A58: =IF(54<=$R$2,54,"") | B58: =IF($A58="","",计算_雪球!B77) | C58: =IF(OR($A58="",C$4=""),"",IF(每月预算!$B$29="雪崩法",计算_雪崩!I77,计算_雪球!I77)) | D58: =IF(OR($A58="",D$4=""),"",IF(每月预算!$B$29="雪崩法",计算_雪崩!N77,计算_雪球!N77)) | E58: =IF(OR($A58="",E$4=""),"",IF(每月预算!$B$29="雪崩法",计算_雪崩!S77,计算_雪球!S77)) | F58: =IF(OR($A58="",F$4=""),"",IF(每月预算!$B$29="雪崩法",计算_雪崩!X77,计算_雪球!X77)) | G58: =IF(OR($A58="",G$4=""),"",IF(每月预算!$B$29="雪崩法",计算_雪崩!AC77,计算_雪球!AC77)) | H58: =IF(OR($A58="",H$4=""),"",IF(每月预算!$B$29="雪崩法",计算_雪崩!AH77,计算_雪球!AH77)) | I58: =IF(OR($A58="",I$4=""),"",IF(每月预算!$B$29="雪崩法",计算_雪崩!AM77,计算_雪球!AM77)) | J58: =IF(OR($A58="",J$4=""),"",IF(每月预算!$B$29="雪崩法",计算_雪崩!AR77,计算_雪球!AR77)) | K58: =IF(OR($A58="",K$4=""),"",IF(每月预算!$B$29="雪崩法",计算_雪崩!AW77,计算_雪球!AW77)) | L58: =IF(OR($A58="",L$4=""),"",IF(每月预算!$B$29="雪崩法",计算_雪崩!BB77,计算_雪球!BB77)) | M58: =IF($A58="","",IF(每月预算!$B$29="雪崩法",计算_雪崩!BC77,计算_雪球!BC77)) | N58: =IF($A58="","",IF(每月预算!$B$29="雪崩法",计算_雪崩!BE77,计算_雪球!BE77)) | O58: =IF($A58="","",IF(每月预算!$B$29="雪崩法",计算_雪崩!BD77,计算_雪球!BD77))
A59: =IF(55<=$R$2,55,"") | B59: =IF($A59="","",计算_雪球!B78) | C59: =IF(OR($A59="",C$4=""),"",IF(每月预算!$B$29="雪崩法",计算_雪崩!I78,计算_雪球!I78)) | D59: =IF(OR($A59="",D$4=""),"",IF(每月预算!$B$29="雪崩法",计算_雪崩!N78,计算_雪球!N78)) | E59: =IF(OR($A59="",E$4=""),"",IF(每月预算!$B$29="雪崩法",计算_雪崩!S78,计算_雪球!S78)) | F59: =IF(OR($A59="",F$4=""),"",IF(每月预算!$B$29="雪崩法",计算_雪崩!X78,计算_雪球!X78)) | G59: =IF(OR($A59="",G$4=""),"",IF(每月预算!$B$29="雪崩法",计算_雪崩!AC78,计算_雪球!AC78)) | H59: =IF(OR($A59="",H$4=""),"",IF(每月预算!$B$29="雪崩法",计算_雪崩!AH78,计算_雪球!AH78)) | I59: =IF(OR($A59="",I$4=""),"",IF(每月预算!$B$29="雪崩法",计算_雪崩!AM78,计算_雪球!AM78)) | J59: =IF(OR($A59="",J$4=""),"",IF(每月预算!$B$29="雪崩法",计算_雪崩!AR78,计算_雪球!AR78)) | K59: =IF(OR($A59="",K$4=""),"",IF(每月预算!$B$29="雪崩法",计算_雪崩!AW78,计算_雪球!AW78)) | L59: =IF(OR($A59="",L$4=""),"",IF(每月预算!$B$29="雪崩法",计算_雪崩!BB78,计算_雪球!BB78)) | M59: =IF($A59="","",IF(每月预算!$B$29="雪崩法",计算_雪崩!BC78,计算_雪球!BC78)) | N59: =IF($A59="","",IF(每月预算!$B$29="雪崩法",计算_雪崩!BE78,计算_雪球!BE78)) | O59: =IF($A59="","",IF(每月预算!$B$29="雪崩法",计算_雪崩!BD78,计算_雪球!BD78))
A60: =IF(56<=$R$2,56,"") | B60: =IF($A60="","",计算_雪球!B79) | C60: =IF(OR($A60="",C$4=""),"",IF(每月预算!$B$29="雪崩法",计算_雪崩!I79,计算_雪球!I79)) | D60: =IF(OR($A60="",D$4=""),"",IF(每月预算!$B$29="雪崩法",计算_雪崩!N79,计算_雪球!N79)) | E60: =IF(OR($A60="",E$4=""),"",IF(每月预算!$B$29="雪崩法",计算_雪崩!S79,计算_雪球!S79)) | F60: =IF(OR($A60="",F$4=""),"",IF(每月预算!$B$29="雪崩法",计算_雪崩!X79,计算_雪球!X79)) | G60: =IF(OR($A60="",G$4=""),"",IF(每月预算!$B$29="雪崩法",计算_雪崩!AC79,计算_雪球!AC79)) | H60: =IF(OR($A60="",H$4=""),"",IF(每月预算!$B$29="雪崩法",计算_雪崩!AH79,计算_雪球!AH79)) | I60: =IF(OR($A60="",I$4=""),"",IF(每月预算!$B$29="雪崩法",计算_雪崩!AM79,计算_雪球!AM79)) | J60: =IF(OR($A60="",J$4=""),"",IF(每月预算!$B$29="雪崩法",计算_雪崩!AR79,计算_雪球!AR79)) | K60: =IF(OR($A60="",K$4=""),"",IF(每月预算!$B$29="雪崩法",计算_雪崩!AW79,计算_雪球!AW79)) | L60: =IF(OR($A60="",L$4=""),"",IF(每月预算!$B$29="雪崩法",计算_雪崩!BB79,计算_雪球!BB79)) | M60: =IF($A60="","",IF(每月预算!$B$29="雪崩法",计算_雪崩!BC79,计算_雪球!BC79)) | N60: =IF($A60="","",IF(每月预算!$B$29="雪崩法",计算_雪崩!BE79,计算_雪球!BE79)) | O60: =IF($A60="","",IF(每月预算!$B$29="雪崩法",计算_雪崩!BD79,计算_雪球!BD79))
A61: =IF(57<=$R$2,57,"") | B61: =IF($A61="","",计算_雪球!B80) | C61: =IF(OR($A61="",C$4=""),"",IF(每月预算!$B$29="雪崩法",计算_雪崩!I80,计算_雪球!I80)) | D61: =IF(OR($A61="",D$4=""),"",IF(每月预算!$B$29="雪崩法",计算_雪崩!N80,计算_雪球!N80)) | E61: =IF(OR($A61="",E$4=""),"",IF(每月预算!$B$29="雪崩法",计算_雪崩!S80,计算_雪球!S80)) | F61: =IF(OR($A61="",F$4=""),"",IF(每月预算!$B$29="雪崩法",计算_雪崩!X80,计算_雪球!X80)) | G61: =IF(OR($A61="",G$4=""),"",IF(每月预算!$B$29="雪崩法",计算_雪崩!AC80,计算_雪球!AC80)) | H61: =IF(OR($A61="",H$4=""),"",IF(每月预算!$B$29="雪崩法",计算_雪崩!AH80,计算_雪球!AH80)) | I61: =IF(OR($A61="",I$4=""),"",IF(每月预算!$B$29="雪崩法",计算_雪崩!AM80,计算_雪球!AM80)) | J61: =IF(OR($A61="",J$4=""),"",IF(每月预算!$B$29="雪崩法",计算_雪崩!AR80,计算_雪球!AR80)) | K61: =IF(OR($A61="",K$4=""),"",IF(每月预算!$B$29="雪崩法",计算_雪崩!AW80,计算_雪球!AW80)) | L61: =IF(OR($A61="",L$4=""),"",IF(每月预算!$B$29="雪崩法",计算_雪崩!BB80,计算_雪球!BB80)) | M61: =IF($A61="","",IF(每月预算!$B$29="雪崩法",计算_雪崩!BC80,计算_雪球!BC80)) | N61: =IF($A61="","",IF(每月预算!$B$29="雪崩法",计算_雪崩!BE80,计算_雪球!BE80)) | O61: =IF($A61="","",IF(每月预算!$B$29="雪崩法",计算_雪崩!BD80,计算_雪球!BD80))
A62: =IF(58<=$R$2,58,"") | B62: =IF($A62="","",计算_雪球!B81) | C62: =IF(OR($A62="",C$4=""),"",IF(每月预算!$B$29="雪崩法",计算_雪崩!I81,计算_雪球!I81)) | D62: =IF(OR($A62="",D$4=""),"",IF(每月预算!$B$29="雪崩法",计算_雪崩!N81,计算_雪球!N81)) | E62: =IF(OR($A62="",E$4=""),"",IF(每月预算!$B$29="雪崩法",计算_雪崩!S81,计算_雪球!S81)) | F62: =IF(OR($A62="",F$4=""),"",IF(每月预算!$B$29="雪崩法",计算_雪崩!X81,计算_雪球!X81)) | G62: =IF(OR($A62="",G$4=""),"",IF(每月预算!$B$29="雪崩法",计算_雪崩!AC81,计算_雪球!AC81)) | H62: =IF(OR($A62="",H$4=""),"",IF(每月预算!$B$29="雪崩法",计算_雪崩!AH81,计算_雪球!AH81)) | I62: =IF(OR($A62="",I$4=""),"",IF(每月预算!$B$29="雪崩法",计算_雪崩!AM81,计算_雪球!AM81)) | J62: =IF(OR($A62="",J$4=""),"",IF(每月预算!$B$29="雪崩法",计算_雪崩!AR81,计算_雪球!AR81)) | K62: =IF(OR($A62="",K$4=""),"",IF(每月预算!$B$29="雪崩法",计算_雪崩!AW81,计算_雪球!AW81)) | L62: =IF(OR($A62="",L$4=""),"",IF(每月预算!$B$29="雪崩法",计算_雪崩!BB81,计算_雪球!BB81)) | M62: =IF($A62="","",IF(每月预算!$B$29="雪崩法",计算_雪崩!BC81,计算_雪球!BC81)) | N62: =IF($A62="","",IF(每月预算!$B$29="雪崩法",计算_雪崩!BE81,计算_雪球!BE81)) | O62: =IF($A62="","",IF(每月预算!$B$29="雪崩法",计算_雪崩!BD81,计算_雪球!BD81))
A63: =IF(59<=$R$2,59,"") | B63: =IF($A63="","",计算_雪球!B82) | C63: =IF(OR($A63="",C$4=""),"",IF(每月预算!$B$29="雪崩法",计算_雪崩!I82,计算_雪球!I82)) | D63: =IF(OR($A63="",D$4=""),"",IF(每月预算!$B$29="雪崩法",计算_雪崩!N82,计算_雪球!N82)) | E63: =IF(OR($A63="",E$4=""),"",IF(每月预算!$B$29="雪崩法",计算_雪崩!S82,计算_雪球!S82)) | F63: =IF(OR($A63="",F$4=""),"",IF(每月预算!$B$29="雪崩法",计算_雪崩!X82,计算_雪球!X82)) | G63: =IF(OR($A63="",G$4=""),"",IF(每月预算!$B$29="雪崩法",计算_雪崩!AC82,计算_雪球!AC82)) | H63: =IF(OR($A63="",H$4=""),"",IF(每月预算!$B$29="雪崩法",计算_雪崩!AH82,计算_雪球!AH82)) | I63: =IF(OR($A63="",I$4=""),"",IF(每月预算!$B$29="雪崩法",计算_雪崩!AM82,计算_雪球!AM82)) | J63: =IF(OR($A63="",J$4=""),"",IF(每月预算!$B$29="雪崩法",计算_雪崩!AR82,计算_雪球!AR82)) | K63: =IF(OR($A63="",K$4=""),"",IF(每月预算!$B$29="雪崩法",计算_雪崩!AW82,计算_雪球!AW82)) | L63: =IF(OR($A63="",L$4=""),"",IF(每月预算!$B$29="雪崩法",计算_雪崩!BB82,计算_雪球!BB82)) | M63: =IF($A63="","",IF(每月预算!$B$29="雪崩法",计算_雪崩!BC82,计算_雪球!BC82)) | N63: =IF($A63="","",IF(每月预算!$B$29="雪崩法",计算_雪崩!BE82,计算_雪球!BE82)) | O63: =IF($A63="","",IF(每月预算!$B$29="雪崩法",计算_雪崩!BD82,计算_雪球!BD82))
A64: =IF(60<=$R$2,60,"") | B64: =IF($A64="","",计算_雪球!B83) | C64: =IF(OR($A64="",C$4=""),"",IF(每月预算!$B$29="雪崩法",计算_雪崩!I83,计算_雪球!I83)) | D64: =IF(OR($A64="",D$4=""),"",IF(每月预算!$B$29="雪崩法",计算_雪崩!N83,计算_雪球!N83)) | E64: =IF(OR($A64="",E$4=""),"",IF(每月预算!$B$29="雪崩法",计算_雪崩!S83,计算_雪球!S83)) | F64: =IF(OR($A64="",F$4=""),"",IF(每月预算!$B$29="雪崩法",计算_雪崩!X83,计算_雪球!X83)) | G64: =IF(OR($A64="",G$4=""),"",IF(每月预算!$B$29="雪崩法",计算_雪崩!AC83,计算_雪球!AC83)) | H64: =IF(OR($A64="",H$4=""),"",IF(每月预算!$B$29="雪崩法",计算_雪崩!AH83,计算_雪球!AH83)) | I64: =IF(OR($A64="",I$4=""),"",IF(每月预算!$B$29="雪崩法",计算_雪崩!AM83,计算_雪球!AM83)) | J64: =IF(OR($A64="",J$4=""),"",IF(每月预算!$B$29="雪崩法",计算_雪崩!AR83,计算_雪球!AR83)) | K64: =IF(OR($A64="",K$4=""),"",IF(每月预算!$B$29="雪崩法",计算_雪崩!AW83,计算_雪球!AW83)) | L64: =IF(OR($A64="",L$4=""),"",IF(每月预算!$B$29="雪崩法",计算_雪崩!BB83,计算_雪球!BB83)) | M64: =IF($A64="","",IF(每月预算!$B$29="雪崩法",计算_雪崩!BC83,计算_雪球!BC83)) | N64: =IF($A64="","",IF(每月预算!$B$29="雪崩法",计算_雪崩!BE83,计算_雪球!BE83)) | O64: =IF($A64="","",IF(每月预算!$B$29="雪崩法",计算_雪崩!BD83,计算_雪球!BD83))
A65: =IF(61<=$R$2,61,"") | B65: =IF($A65="","",计算_雪球!B84) | C65: =IF(OR($A65="",C$4=""),"",IF(每月预算!$B$29="雪崩法",计算_雪崩!I84,计算_雪球!I84)) | D65: =IF(OR($A65="",D$4=""),"",IF(每月预算!$B$29="雪崩法",计算_雪崩!N84,计算_雪球!N84)) | E65: =IF(OR($A65="",E$4=""),"",IF(每月预算!$B$29="雪崩法",计算_雪崩!S84,计算_雪球!S84)) | F65: =IF(OR($A65="",F$4=""),"",IF(每月预算!$B$29="雪崩法",计算_雪崩!X84,计算_雪球!X84)) | G65: =IF(OR($A65="",G$4=""),"",IF(每月预算!$B$29="雪崩法",计算_雪崩!AC84,计算_雪球!AC84)) | H65: =IF(OR($A65="",H$4=""),"",IF(每月预算!$B$29="雪崩法",计算_雪崩!AH84,计算_雪球!AH84)) | I65: =IF(OR($A65="",I$4=""),"",IF(每月预算!$B$29="雪崩法",计算_雪崩!AM84,计算_雪球!AM84)) | J65: =IF(OR($A65="",J$4=""),"",IF(每月预算!$B$29="雪崩法",计算_雪崩!AR84,计算_雪球!AR84)) | K65: =IF(OR($A65="",K$4=""),"",IF(每月预算!$B$29="雪崩法",计算_雪崩!AW84,计算_雪球!AW84)) | L65: =IF(OR($A65="",L$4=""),"",IF(每月预算!$B$29="雪崩法",计算_雪崩!BB84,计算_雪球!BB84)) | M65: =IF($A65="","",IF(每月预算!$B$29="雪崩法",计算_雪崩!BC84,计算_雪球!BC84)) | N65: =IF($A65="","",IF(每月预算!$B$29="雪崩法",计算_雪崩!BE84,计算_雪球!BE84)) | O65: =IF($A65="","",IF(每月预算!$B$29="雪崩法",计算_雪崩!BD84,计算_雪球!BD84))
A66: =IF(62<=$R$2,62,"") | B66: =IF($A66="","",计算_雪球!B85) | C66: =IF(OR($A66="",C$4=""),"",IF(每月预算!$B$29="雪崩法",计算_雪崩!I85,计算_雪球!I85)) | D66: =IF(OR($A66="",D$4=""),"",IF(每月预算!$B$29="雪崩法",计算_雪崩!N85,计算_雪球!N85)) | E66: =IF(OR($A66="",E$4=""),"",IF(每月预算!$B$29="雪崩法",计算_雪崩!S85,计算_雪球!S85)) | F66: =IF(OR($A66="",F$4=""),"",IF(每月预算!$B$29="雪崩法",计算_雪崩!X85,计算_雪球!X85)) | G66: =IF(OR($A66="",G$4=""),"",IF(每月预算!$B$29="雪崩法",计算_雪崩!AC85,计算_雪球!AC85)) | H66: =IF(OR($A66="",H$4=""),"",IF(每月预算!$B$29="雪崩法",计算_雪崩!AH85,计算_雪球!AH85)) | I66: =IF(OR($A66="",I$4=""),"",IF(每月预算!$B$29="雪崩法",计算_雪崩!AM85,计算_雪球!AM85)) | J66: =IF(OR($A66="",J$4=""),"",IF(每月预算!$B$29="雪崩法",计算_雪崩!AR85,计算_雪球!AR85)) | K66: =IF(OR($A66="",K$4=""),"",IF(每月预算!$B$29="雪崩法",计算_雪崩!AW85,计算_雪球!AW85)) | L66: =IF(OR($A66="",L$4=""),"",IF(每月预算!$B$29="雪崩法",计算_雪崩!BB85,计算_雪球!BB85)) | M66: =IF($A66="","",IF(每月预算!$B$29="雪崩法",计算_雪崩!BC85,计算_雪球!BC85)) | N66: =IF($A66="","",IF(每月预算!$B$29="雪崩法",计算_雪崩!BE85,计算_雪球!BE85)) | O66: =IF($A66="","",IF(每月预算!$B$29="雪崩法",计算_雪崩!BD85,计算_雪球!BD85))
A67: =IF(63<=$R$2,63,"") | B67: =IF($A67="","",计算_雪球!B86) | C67: =IF(OR($A67="",C$4=""),"",IF(每月预算!$B$29="雪崩法",计算_雪崩!I86,计算_雪球!I86)) | D67: =IF(OR($A67="",D$4=""),"",IF(每月预算!$B$29="雪崩法",计算_雪崩!N86,计算_雪球!N86)) | E67: =IF(OR($A67="",E$4=""),"",IF(每月预算!$B$29="雪崩法",计算_雪崩!S86,计算_雪球!S86)) | F67: =IF(OR($A67="",F$4=""),"",IF(每月预算!$B$29="雪崩法",计算_雪崩!X86,计算_雪球!X86)) | G67: =IF(OR($A67="",G$4=""),"",IF(每月预算!$B$29="雪崩法",计算_雪崩!AC86,计算_雪球!AC86)) | H67: =IF(OR($A67="",H$4=""),"",IF(每月预算!$B$29="雪崩法",计算_雪崩!AH86,计算_雪球!AH86)) | I67: =IF(OR($A67="",I$4=""),"",IF(每月预算!$B$29="雪崩法",计算_雪崩!AM86,计算_雪球!AM86)) | J67: =IF(OR($A67="",J$4=""),"",IF(每月预算!$B$29="雪崩法",计算_雪崩!AR86,计算_雪球!AR86)) | K67: =IF(OR($A67="",K$4=""),"",IF(每月预算!$B$29="雪崩法",计算_雪崩!AW86,计算_雪球!AW86)) | L67: =IF(OR($A67="",L$4=""),"",IF(每月预算!$B$29="雪崩法",计算_雪崩!BB86,计算_雪球!BB86)) | M67: =IF($A67="","",IF(每月预算!$B$29="雪崩法",计算_雪崩!BC86,计算_雪球!BC86)) | N67: =IF($A67="","",IF(每月预算!$B$29="雪崩法",计算_雪崩!BE86,计算_雪球!BE86)) | O67: =IF($A67="","",IF(每月预算!$B$29="雪崩法",计算_雪崩!BD86,计算_雪球!BD86))
A68: =IF(64<=$R$2,64,"") | B68: =IF($A68="","",计算_雪球!B87) | C68: =IF(OR($A68="",C$4=""),"",IF(每月预算!$B$29="雪崩法",计算_雪崩!I87,计算_雪球!I87)) | D68: =IF(OR($A68="",D$4=""),"",IF(每月预算!$B$29="雪崩法",计算_雪崩!N87,计算_雪球!N87)) | E68: =IF(OR($A68="",E$4=""),"",IF(每月预算!$B$29="雪崩法",计算_雪崩!S87,计算_雪球!S87)) | F68: =IF(OR($A68="",F$4=""),"",IF(每月预算!$B$29="雪崩法",计算_雪崩!X87,计算_雪球!X87)) | G68: =IF(OR($A68="",G$4=""),"",IF(每月预算!$B$29="雪崩法",计算_雪崩!AC87,计算_雪球!AC87)) | H68: =IF(OR($A68="",H$4=""),"",IF(每月预算!$B$29="雪崩法",计算_雪崩!AH87,计算_雪球!AH87)) | I68: =IF(OR($A68="",I$4=""),"",IF(每月预算!$B$29="雪崩法",计算_雪崩!AM87,计算_雪球!AM87)) | J68: =IF(OR($A68="",J$4=""),"",IF(每月预算!$B$29="雪崩法",计算_雪崩!AR87,计算_雪球!AR87)) | K68: =IF(OR($A68="",K$4=""),"",IF(每月预算!$B$29="雪崩法",计算_雪崩!AW87,计算_雪球!AW87)) | L68: =IF(OR($A68="",L$4=""),"",IF(每月预算!$B$29="雪崩法",计算_雪崩!BB87,计算_雪球!BB87)) | M68: =IF($A68="","",IF(每月预算!$B$29="雪崩法",计算_雪崩!BC87,计算_雪球!BC87)) | N68: =IF($A68="","",IF(每月预算!$B$29="雪崩法",计算_雪崩!BE87,计算_雪球!BE87)) | O68: =IF($A68="","",IF(每月预算!$B$29="雪崩法",计算_雪崩!BD87,计算_雪球!BD87))
A69: =IF(65<=$R$2,65,"") | B69: =IF($A69="","",计算_雪球!B88) | C69: =IF(OR($A69="",C$4=""),"",IF(每月预算!$B$29="雪崩法",计算_雪崩!I88,计算_雪球!I88)) | D69: =IF(OR($A69="",D$4=""),"",IF(每月预算!$B$29="雪崩法",计算_雪崩!N88,计算_雪球!N88)) | E69: =IF(OR($A69="",E$4=""),"",IF(每月预算!$B$29="雪崩法",计算_雪崩!S88,计算_雪球!S88)) | F69: =IF(OR($A69="",F$4=""),"",IF(每月预算!$B$29="雪崩法",计算_雪崩!X88,计算_雪球!X88)) | G69: =IF(OR($A69="",G$4=""),"",IF(每月预算!$B$29="雪崩法",计算_雪崩!AC88,计算_雪球!AC88)) | H69: =IF(OR($A69="",H$4=""),"",IF(每月预算!$B$29="雪崩法",计算_雪崩!AH88,计算_雪球!AH88)) | I69: =IF(OR($A69="",I$4=""),"",IF(每月预算!$B$29="雪崩法",计算_雪崩!AM88,计算_雪球!AM88)) | J69: =IF(OR($A69="",J$4=""),"",IF(每月预算!$B$29="雪崩法",计算_雪崩!AR88,计算_雪球!AR88)) | K69: =IF(OR($A69="",K$4=""),"",IF(每月预算!$B$29="雪崩法",计算_雪崩!AW88,计算_雪球!AW88)) | L69: =IF(OR($A69="",L$4=""),"",IF(每月预算!$B$29="雪崩法",计算_雪崩!BB88,计算_雪球!BB88)) | M69: =IF($A69="","",IF(每月预算!$B$29="雪崩法",计算_雪崩!BC88,计算_雪球!BC88)) | N69: =IF($A69="","",IF(每月预算!$B$29="雪崩法",计算_雪崩!BE88,计算_雪球!BE88)) | O69: =IF($A69="","",IF(每月预算!$B$29="雪崩法",计算_雪崩!BD88,计算_雪球!BD88))
A70: =IF(66<=$R$2,66,"") | B70: =IF($A70="","",计算_雪球!B89) | C70: =IF(OR($A70="",C$4=""),"",IF(每月预算!$B$29="雪崩法",计算_雪崩!I89,计算_雪球!I89)) | D70: =IF(OR($A70="",D$4=""),"",IF(每月预算!$B$29="雪崩法",计算_雪崩!N89,计算_雪球!N89)) | E70: =IF(OR($A70="",E$4=""),"",IF(每月预算!$B$29="雪崩法",计算_雪崩!S89,计算_雪球!S89)) | F70: =IF(OR($A70="",F$4=""),"",IF(每月预算!$B$29="雪崩法",计算_雪崩!X89,计算_雪球!X89)) | G70: =IF(OR($A70="",G$4=""),"",IF(每月预算!$B$29="雪崩法",计算_雪崩!AC89,计算_雪球!AC89)) | H70: =IF(OR($A70="",H$4=""),"",IF(每月预算!$B$29="雪崩法",计算_雪崩!AH89,计算_雪球!AH89)) | I70: =IF(OR($A70="",I$4=""),"",IF(每月预算!$B$29="雪崩法",计算_雪崩!AM89,计算_雪球!AM89)) | J70: =IF(OR($A70="",J$4=""),"",IF(每月预算!$B$29="雪崩法",计算_雪崩!AR89,计算_雪球!AR89)) | K70: =IF(OR($A70="",K$4=""),"",IF(每月预算!$B$29="雪崩法",计算_雪崩!AW89,计算_雪球!AW89)) | L70: =IF(OR($A70="",L$4=""),"",IF(每月预算!$B$29="雪崩法",计算_雪崩!BB89,计算_雪球!BB89)) | M70: =IF($A70="","",IF(每月预算!$B$29="雪崩法",计算_雪崩!BC89,计算_雪球!BC89)) | N70: =IF($A70="","",IF(每月预算!$B$29="雪崩法",计算_雪崩!BE89,计算_雪球!BE89)) | O70: =IF($A70="","",IF(每月预算!$B$29="雪崩法",计算_雪崩!BD89,计算_雪球!BD89))
A71: =IF(67<=$R$2,67,"") | B71: =IF($A71="","",计算_雪球!B90) | C71: =IF(OR($A71="",C$4=""),"",IF(每月预算!$B$29="雪崩法",计算_雪崩!I90,计算_雪球!I90)) | D71: =IF(OR($A71="",D$4=""),"",IF(每月预算!$B$29="雪崩法",计算_雪崩!N90,计算_雪球!N90)) | E71: =IF(OR($A71="",E$4=""),"",IF(每月预算!$B$29="雪崩法",计算_雪崩!S90,计算_雪球!S90)) | F71: =IF(OR($A71="",F$4=""),"",IF(每月预算!$B$29="雪崩法",计算_雪崩!X90,计算_雪球!X90)) | G71: =IF(OR($A71="",G$4=""),"",IF(每月预算!$B$29="雪崩法",计算_雪崩!AC90,计算_雪球!AC90)) | H71: =IF(OR($A71="",H$4=""),"",IF(每月预算!$B$29="雪崩法",计算_雪崩!AH90,计算_雪球!AH90)) | I71: =IF(OR($A71="",I$4=""),"",IF(每月预算!$B$29="雪崩法",计算_雪崩!AM90,计算_雪球!AM90)) | J71: =IF(OR($A71="",J$4=""),"",IF(每月预算!$B$29="雪崩法",计算_雪崩!AR90,计算_雪球!AR90)) | K71: =IF(OR($A71="",K$4=""),"",IF(每月预算!$B$29="雪崩法",计算_雪崩!AW90,计算_雪球!AW90)) | L71: =IF(OR($A71="",L$4=""),"",IF(每月预算!$B$29="雪崩法",计算_雪崩!BB90,计算_雪球!BB90)) | M71: =IF($A71="","",IF(每月预算!$B$29="雪崩法",计算_雪崩!BC90,计算_雪球!BC90)) | N71: =IF($A71="","",IF(每月预算!$B$29="雪崩法",计算_雪崩!BE90,计算_雪球!BE90)) | O71: =IF($A71="","",IF(每月预算!$B$29="雪崩法",计算_雪崩!BD90,计算_雪球!BD90))
A72: =IF(68<=$R$2,68,"") | B72: =IF($A72="","",计算_雪球!B91) | C72: =IF(OR($A72="",C$4=""),"",IF(每月预算!$B$29="雪崩法",计算_雪崩!I91,计算_雪球!I91)) | D72: =IF(OR($A72="",D$4=""),"",IF(每月预算!$B$29="雪崩法",计算_雪崩!N91,计算_雪球!N91)) | E72: =IF(OR($A72="",E$4=""),"",IF(每月预算!$B$29="雪崩法",计算_雪崩!S91,计算_雪球!S91)) | F72: =IF(OR($A72="",F$4=""),"",IF(每月预算!$B$29="雪崩法",计算_雪崩!X91,计算_雪球!X91)) | G72: =IF(OR($A72="",G$4=""),"",IF(每月预算!$B$29="雪崩法",计算_雪崩!AC91,计算_雪球!AC91)) | H72: =IF(OR($A72="",H$4=""),"",IF(每月预算!$B$29="雪崩法",计算_雪崩!AH91,计算_雪球!AH91)) | I72: =IF(OR($A72="",I$4=""),"",IF(每月预算!$B$29="雪崩法",计算_雪崩!AM91,计算_雪球!AM91)) | J72: =IF(OR($A72="",J$4=""),"",IF(每月预算!$B$29="雪崩法",计算_雪崩!AR91,计算_雪球!AR91)) | K72: =IF(OR($A72="",K$4=""),"",IF(每月预算!$B$29="雪崩法",计算_雪崩!AW91,计算_雪球!AW91)) | L72: =IF(OR($A72="",L$4=""),"",IF(每月预算!$B$29="雪崩法",计算_雪崩!BB91,计算_雪球!BB91)) | M72: =IF($A72="","",IF(每月预算!$B$29="雪崩法",计算_雪崩!BC91,计算_雪球!BC91)) | N72: =IF($A72="","",IF(每月预算!$B$29="雪崩法",计算_雪崩!BE91,计算_雪球!BE91)) | O72: =IF($A72="","",IF(每月预算!$B$29="雪崩法",计算_雪崩!BD91,计算_雪球!BD91))
A73: =IF(69<=$R$2,69,"") | B73: =IF($A73="","",计算_雪球!B92) | C73: =IF(OR($A73="",C$4=""),"",IF(每月预算!$B$29="雪崩法",计算_雪崩!I92,计算_雪球!I92)) | D73: =IF(OR($A73="",D$4=""),"",IF(每月预算!$B$29="雪崩法",计算_雪崩!N92,计算_雪球!N92)) | E73: =IF(OR($A73="",E$4=""),"",IF(每月预算!$B$29="雪崩法",计算_雪崩!S92,计算_雪球!S92)) | F73: =IF(OR($A73="",F$4=""),"",IF(每月预算!$B$29="雪崩法",计算_雪崩!X92,计算_雪球!X92)) | G73: =IF(OR($A73="",G$4=""),"",IF(每月预算!$B$29="雪崩法",计算_雪崩!AC92,计算_雪球!AC92)) | H73: =IF(OR($A73="",H$4=""),"",IF(每月预算!$B$29="雪崩法",计算_雪崩!AH92,计算_雪球!AH92)) | I73: =IF(OR($A73="",I$4=""),"",IF(每月预算!$B$29="雪崩法",计算_雪崩!AM92,计算_雪球!AM92)) | J73: =IF(OR($A73="",J$4=""),"",IF(每月预算!$B$29="雪崩法",计算_雪崩!AR92,计算_雪球!AR92)) | K73: =IF(OR($A73="",K$4=""),"",IF(每月预算!$B$29="雪崩法",计算_雪崩!AW92,计算_雪球!AW92)) | L73: =IF(OR($A73="",L$4=""),"",IF(每月预算!$B$29="雪崩法",计算_雪崩!BB92,计算_雪球!BB92)) | M73: =IF($A73="","",IF(每月预算!$B$29="雪崩法",计算_雪崩!BC92,计算_雪球!BC92)) | N73: =IF($A73="","",IF(每月预算!$B$29="雪崩法",计算_雪崩!BE92,计算_雪球!BE92)) | O73: =IF($A73="","",IF(每月预算!$B$29="雪崩法",计算_雪崩!BD92,计算_雪球!BD92))
A74: =IF(70<=$R$2,70,"") | B74: =IF($A74="","",计算_雪球!B93) | C74: =IF(OR($A74="",C$4=""),"",IF(每月预算!$B$29="雪崩法",计算_雪崩!I93,计算_雪球!I93)) | D74: =IF(OR($A74="",D$4=""),"",IF(每月预算!$B$29="雪崩法",计算_雪崩!N93,计算_雪球!N93)) | E74: =IF(OR($A74="",E$4=""),"",IF(每月预算!$B$29="雪崩法",计算_雪崩!S93,计算_雪球!S93)) | F74: =IF(OR($A74="",F$4=""),"",IF(每月预算!$B$29="雪崩法",计算_雪崩!X93,计算_雪球!X93)) | G74: =IF(OR($A74="",G$4=""),"",IF(每月预算!$B$29="雪崩法",计算_雪崩!AC93,计算_雪球!AC93)) | H74: =IF(OR($A74="",H$4=""),"",IF(每月预算!$B$29="雪崩法",计算_雪崩!AH93,计算_雪球!AH93)) | I74: =IF(OR($A74="",I$4=""),"",IF(每月预算!$B$29="雪崩法",计算_雪崩!AM93,计算_雪球!AM93)) | J74: =IF(OR($A74="",J$4=""),"",IF(每月预算!$B$29="雪崩法",计算_雪崩!AR93,计算_雪球!AR93)) | K74: =IF(OR($A74="",K$4=""),"",IF(每月预算!$B$29="雪崩法",计算_雪崩!AW93,计算_雪球!AW93)) | L74: =IF(OR($A74="",L$4=""),"",IF(每月预算!$B$29="雪崩法",计算_雪崩!BB93,计算_雪球!BB93)) | M74: =IF($A74="","",IF(每月预算!$B$29="雪崩法",计算_雪崩!BC93,计算_雪球!BC93)) | N74: =IF($A74="","",IF(每月预算!$B$29="雪崩法",计算_雪崩!BE93,计算_雪球!BE93)) | O74: =IF($A74="","",IF(每月预算!$B$29="雪崩法",计算_雪崩!BD93,计算_雪球!BD93))
A75: =IF(71<=$R$2,71,"") | B75: =IF($A75="","",计算_雪球!B94) | C75: =IF(OR($A75="",C$4=""),"",IF(每月预算!$B$29="雪崩法",计算_雪崩!I94,计算_雪球!I94)) | D75: =IF(OR($A75="",D$4=""),"",IF(每月预算!$B$29="雪崩法",计算_雪崩!N94,计算_雪球!N94)) | E75: =IF(OR($A75="",E$4=""),"",IF(每月预算!$B$29="雪崩法",计算_雪崩!S94,计算_雪球!S94)) | F75: =IF(OR($A75="",F$4=""),"",IF(每月预算!$B$29="雪崩法",计算_雪崩!X94,计算_雪球!X94)) | G75: =IF(OR($A75="",G$4=""),"",IF(每月预算!$B$29="雪崩法",计算_雪崩!AC94,计算_雪球!AC94)) | H75: =IF(OR($A75="",H$4=""),"",IF(每月预算!$B$29="雪崩法",计算_雪崩!AH94,计算_雪球!AH94)) | I75: =IF(OR($A75="",I$4=""),"",IF(每月预算!$B$29="雪崩法",计算_雪崩!AM94,计算_雪球!AM94)) | J75: =IF(OR($A75="",J$4=""),"",IF(每月预算!$B$29="雪崩法",计算_雪崩!AR94,计算_雪球!AR94)) | K75: =IF(OR($A75="",K$4=""),"",IF(每月预算!$B$29="雪崩法",计算_雪崩!AW94,计算_雪球!AW94)) | L75: =IF(OR($A75="",L$4=""),"",IF(每月预算!$B$29="雪崩法",计算_雪崩!BB94,计算_雪球!BB94)) | M75: =IF($A75="","",IF(每月预算!$B$29="雪崩法",计算_雪崩!BC94,计算_雪球!BC94)) | N75: =IF($A75="","",IF(每月预算!$B$29="雪崩法",计算_雪崩!BE94,计算_雪球!BE94)) | O75: =IF($A75="","",IF(每月预算!$B$29="雪崩法",计算_雪崩!BD94,计算_雪球!BD94))
A76: =IF(72<=$R$2,72,"") | B76: =IF($A76="","",计算_雪球!B95) | C76: =IF(OR($A76="",C$4=""),"",IF(每月预算!$B$29="雪崩法",计算_雪崩!I95,计算_雪球!I95)) | D76: =IF(OR($A76="",D$4=""),"",IF(每月预算!$B$29="雪崩法",计算_雪崩!N95,计算_雪球!N95)) | E76: =IF(OR($A76="",E$4=""),"",IF(每月预算!$B$29="雪崩法",计算_雪崩!S95,计算_雪球!S95)) | F76: =IF(OR($A76="",F$4=""),"",IF(每月预算!$B$29="雪崩法",计算_雪崩!X95,计算_雪球!X95)) | G76: =IF(OR($A76="",G$4=""),"",IF(每月预算!$B$29="雪崩法",计算_雪崩!AC95,计算_雪球!AC95)) | H76: =IF(OR($A76="",H$4=""),"",IF(每月预算!$B$29="雪崩法",计算_雪崩!AH95,计算_雪球!AH95)) | I76: =IF(OR($A76="",I$4=""),"",IF(每月预算!$B$29="雪崩法",计算_雪崩!AM95,计算_雪球!AM95)) | J76: =IF(OR($A76="",J$4=""),"",IF(每月预算!$B$29="雪崩法",计算_雪崩!AR95,计算_雪球!AR95)) | K76: =IF(OR($A76="",K$4=""),"",IF(每月预算!$B$29="雪崩法",计算_雪崩!AW95,计算_雪球!AW95)) | L76: =IF(OR($A76="",L$4=""),"",IF(每月预算!$B$29="雪崩法",计算_雪崩!BB95,计算_雪球!BB95)) | M76: =IF($A76="","",IF(每月预算!$B$29="雪崩法",计算_雪崩!BC95,计算_雪球!BC95)) | N76: =IF($A76="","",IF(每月预算!$B$29="雪崩法",计算_雪崩!BE95,计算_雪球!BE95)) | O76: =IF($A76="","",IF(每月预算!$B$29="雪崩法",计算_雪崩!BD95,计算_雪球!BD95))
A77: =IF(73<=$R$2,73,"") | B77: =IF($A77="","",计算_雪球!B96) | C77: =IF(OR($A77="",C$4=""),"",IF(每月预算!$B$29="雪崩法",计算_雪崩!I96,计算_雪球!I96)) | D77: =IF(OR($A77="",D$4=""),"",IF(每月预算!$B$29="雪崩法",计算_雪崩!N96,计算_雪球!N96)) | E77: =IF(OR($A77="",E$4=""),"",IF(每月预算!$B$29="雪崩法",计算_雪崩!S96,计算_雪球!S96)) | F77: =IF(OR($A77="",F$4=""),"",IF(每月预算!$B$29="雪崩法",计算_雪崩!X96,计算_雪球!X96)) | G77: =IF(OR($A77="",G$4=""),"",IF(每月预算!$B$29="雪崩法",计算_雪崩!AC96,计算_雪球!AC96)) | H77: =IF(OR($A77="",H$4=""),"",IF(每月预算!$B$29="雪崩法",计算_雪崩!AH96,计算_雪球!AH96)) | I77: =IF(OR($A77="",I$4=""),"",IF(每月预算!$B$29="雪崩法",计算_雪崩!AM96,计算_雪球!AM96)) | J77: =IF(OR($A77="",J$4=""),"",IF(每月预算!$B$29="雪崩法",计算_雪崩!AR96,计算_雪球!AR96)) | K77: =IF(OR($A77="",K$4=""),"",IF(每月预算!$B$29="雪崩法",计算_雪崩!AW96,计算_雪球!AW96)) | L77: =IF(OR($A77="",L$4=""),"",IF(每月预算!$B$29="雪崩法",计算_雪崩!BB96,计算_雪球!BB96)) | M77: =IF($A77="","",IF(每月预算!$B$29="雪崩法",计算_雪崩!BC96,计算_雪球!BC96)) | N77: =IF($A77="","",IF(每月预算!$B$29="雪崩法",计算_雪崩!BE96,计算_雪球!BE96)) | O77: =IF($A77="","",IF(每月预算!$B$29="雪崩法",计算_雪崩!BD96,计算_雪球!BD96))
A78: =IF(74<=$R$2,74,"") | B78: =IF($A78="","",计算_雪球!B97) | C78: =IF(OR($A78="",C$4=""),"",IF(每月预算!$B$29="雪崩法",计算_雪崩!I97,计算_雪球!I97)) | D78: =IF(OR($A78="",D$4=""),"",IF(每月预算!$B$29="雪崩法",计算_雪崩!N97,计算_雪球!N97)) | E78: =IF(OR($A78="",E$4=""),"",IF(每月预算!$B$29="雪崩法",计算_雪崩!S97,计算_雪球!S97)) | F78: =IF(OR($A78="",F$4=""),"",IF(每月预算!$B$29="雪崩法",计算_雪崩!X97,计算_雪球!X97)) | G78: =IF(OR($A78="",G$4=""),"",IF(每月预算!$B$29="雪崩法",计算_雪崩!AC97,计算_雪球!AC97)) | H78: =IF(OR($A78="",H$4=""),"",IF(每月预算!$B$29="雪崩法",计算_雪崩!AH97,计算_雪球!AH97)) | I78: =IF(OR($A78="",I$4=""),"",IF(每月预算!$B$29="雪崩法",计算_雪崩!AM97,计算_雪球!AM97)) | J78: =IF(OR($A78="",J$4=""),"",IF(每月预算!$B$29="雪崩法",计算_雪崩!AR97,计算_雪球!AR97)) | K78: =IF(OR($A78="",K$4=""),"",IF(每月预算!$B$29="雪崩法",计算_雪崩!AW97,计算_雪球!AW97)) | L78: =IF(OR($A78="",L$4=""),"",IF(每月预算!$B$29="雪崩法",计算_雪崩!BB97,计算_雪球!BB97)) | M78: =IF($A78="","",IF(每月预算!$B$29="雪崩法",计算_雪崩!BC97,计算_雪球!BC97)) | N78: =IF($A78="","",IF(每月预算!$B$29="雪崩法",计算_雪崩!BE97,计算_雪球!BE97)) | O78: =IF($A78="","",IF(每月预算!$B$29="雪崩法",计算_雪崩!BD97,计算_雪球!BD97))
A79: =IF(75<=$R$2,75,"") | B79: =IF($A79="","",计算_雪球!B98) | C79: =IF(OR($A79="",C$4=""),"",IF(每月预算!$B$29="雪崩法",计算_雪崩!I98,计算_雪球!I98)) | D79: =IF(OR($A79="",D$4=""),"",IF(每月预算!$B$29="雪崩法",计算_雪崩!N98,计算_雪球!N98)) | E79: =IF(OR($A79="",E$4=""),"",IF(每月预算!$B$29="雪崩法",计算_雪崩!S98,计算_雪球!S98)) | F79: =IF(OR($A79="",F$4=""),"",IF(每月预算!$B$29="雪崩法",计算_雪崩!X98,计算_雪球!X98)) | G79: =IF(OR($A79="",G$4=""),"",IF(每月预算!$B$29="雪崩法",计算_雪崩!AC98,计算_雪球!AC98)) | H79: =IF(OR($A79="",H$4=""),"",IF(每月预算!$B$29="雪崩法",计算_雪崩!AH98,计算_雪球!AH98)) | I79: =IF(OR($A79="",I$4=""),"",IF(每月预算!$B$29="雪崩法",计算_雪崩!AM98,计算_雪球!AM98)) | J79: =IF(OR($A79="",J$4=""),"",IF(每月预算!$B$29="雪崩法",计算_雪崩!AR98,计算_雪球!AR98)) | K79: =IF(OR($A79="",K$4=""),"",IF(每月预算!$B$29="雪崩法",计算_雪崩!AW98,计算_雪球!AW98)) | L79: =IF(OR($A79="",L$4=""),"",IF(每月预算!$B$29="雪崩法",计算_雪崩!BB98,计算_雪球!BB98)) | M79: =IF($A79="","",IF(每月预算!$B$29="雪崩法",计算_雪崩!BC98,计算_雪球!BC98)) | N79: =IF($A79="","",IF(每月预算!$B$29="雪崩法",计算_雪崩!BE98,计算_雪球!BE98)) | O79: =IF($A79="","",IF(每月预算!$B$29="雪崩法",计算_雪崩!BD98,计算_雪球!BD98))
A80: =IF(76<=$R$2,76,"") | B80: =IF($A80="","",计算_雪球!B99) | C80: =IF(OR($A80="",C$4=""),"",IF(每月预算!$B$29="雪崩法",计算_雪崩!I99,计算_雪球!I99)) | D80: =IF(OR($A80="",D$4=""),"",IF(每月预算!$B$29="雪崩法",计算_雪崩!N99,计算_雪球!N99)) | E80: =IF(OR($A80="",E$4=""),"",IF(每月预算!$B$29="雪崩法",计算_雪崩!S99,计算_雪球!S99)) | F80: =IF(OR($A80="",F$4=""),"",IF(每月预算!$B$29="雪崩法",计算_雪崩!X99,计算_雪球!X99)) | G80: =IF(OR($A80="",G$4=""),"",IF(每月预算!$B$29="雪崩法",计算_雪崩!AC99,计算_雪球!AC99)) | H80: =IF(OR($A80="",H$4=""),"",IF(每月预算!$B$29="雪崩法",计算_雪崩!AH99,计算_雪球!AH99)) | I80: =IF(OR($A80="",I$4=""),"",IF(每月预算!$B$29="雪崩法",计算_雪崩!AM99,计算_雪球!AM99)) | J80: =IF(OR($A80="",J$4=""),"",IF(每月预算!$B$29="雪崩法",计算_雪崩!AR99,计算_雪球!AR99)) | K80: =IF(OR($A80="",K$4=""),"",IF(每月预算!$B$29="雪崩法",计算_雪崩!AW99,计算_雪球!AW99)) | L80: =IF(OR($A80="",L$4=""),"",IF(每月预算!$B$29="雪崩法",计算_雪崩!BB99,计算_雪球!BB99)) | M80: =IF($A80="","",IF(每月预算!$B$29="雪崩法",计算_雪崩!BC99,计算_雪球!BC99)) | N80: =IF($A80="","",IF(每月预算!$B$29="雪崩法",计算_雪崩!BE99,计算_雪球!BE99)) | O80: =IF($A80="","",IF(每月预算!$B$29="雪崩法",计算_雪崩!BD99,计算_雪球!BD99))
A81: =IF(77<=$R$2,77,"") | B81: =IF($A81="","",计算_雪球!B100) | C81: =IF(OR($A81="",C$4=""),"",IF(每月预算!$B$29="雪崩法",计算_雪崩!I100,计算_雪球!I100)) | D81: =IF(OR($A81="",D$4=""),"",IF(每月预算!$B$29="雪崩法",计算_雪崩!N100,计算_雪球!N100)) | E81: =IF(OR($A81="",E$4=""),"",IF(每月预算!$B$29="雪崩法",计算_雪崩!S100,计算_雪球!S100)) | F81: =IF(OR($A81="",F$4=""),"",IF(每月预算!$B$29="雪崩法",计算_雪崩!X100,计算_雪球!X100)) | G81: =IF(OR($A81="",G$4=""),"",IF(每月预算!$B$29="雪崩法",计算_雪崩!AC100,计算_雪球!AC100)) | H81: =IF(OR($A81="",H$4=""),"",IF(每月预算!$B$29="雪崩法",计算_雪崩!AH100,计算_雪球!AH100)) | I81: =IF(OR($A81="",I$4=""),"",IF(每月预算!$B$29="雪崩法",计算_雪崩!AM100,计算_雪球!AM100)) | J81: =IF(OR($A81="",J$4=""),"",IF(每月预算!$B$29="雪崩法",计算_雪崩!AR100,计算_雪球!AR100)) | K81: =IF(OR($A81="",K$4=""),"",IF(每月预算!$B$29="雪崩法",计算_雪崩!AW100,计算_雪球!AW100)) | L81: =IF(OR($A81="",L$4=""),"",IF(每月预算!$B$29="雪崩法",计算_雪崩!BB100,计算_雪球!BB100)) | M81: =IF($A81="","",IF(每月预算!$B$29="雪崩法",计算_雪崩!BC100,计算_雪球!BC100)) | N81: =IF($A81="","",IF(每月预算!$B$29="雪崩法",计算_雪崩!BE100,计算_雪球!BE100)) | O81: =IF($A81="","",IF(每月预算!$B$29="雪崩法",计算_雪崩!BD100,计算_雪球!BD100))
A82: =IF(78<=$R$2,78,"") | B82: =IF($A82="","",计算_雪球!B101) | C82: =IF(OR($A82="",C$4=""),"",IF(每月预算!$B$29="雪崩法",计算_雪崩!I101,计算_雪球!I101)) | D82: =IF(OR($A82="",D$4=""),"",IF(每月预算!$B$29="雪崩法",计算_雪崩!N101,计算_雪球!N101)) | E82: =IF(OR($A82="",E$4=""),"",IF(每月预算!$B$29="雪崩法",计算_雪崩!S101,计算_雪球!S101)) | F82: =IF(OR($A82="",F$4=""),"",IF(每月预算!$B$29="雪崩法",计算_雪崩!X101,计算_雪球!X101)) | G82: =IF(OR($A82="",G$4=""),"",IF(每月预算!$B$29="雪崩法",计算_雪崩!AC101,计算_雪球!AC101)) | H82: =IF(OR($A82="",H$4=""),"",IF(每月预算!$B$29="雪崩法",计算_雪崩!AH101,计算_雪球!AH101)) | I82: =IF(OR($A82="",I$4=""),"",IF(每月预算!$B$29="雪崩法",计算_雪崩!AM101,计算_雪球!AM101)) | J82: =IF(OR($A82="",J$4=""),"",IF(每月预算!$B$29="雪崩法",计算_雪崩!AR101,计算_雪球!AR101)) | K82: =IF(OR($A82="",K$4=""),"",IF(每月预算!$B$29="雪崩法",计算_雪崩!AW101,计算_雪球!AW101)) | L82: =IF(OR($A82="",L$4=""),"",IF(每月预算!$B$29="雪崩法",计算_雪崩!BB101,计算_雪球!BB101)) | M82: =IF($A82="","",IF(每月预算!$B$29="雪崩法",计算_雪崩!BC101,计算_雪球!BC101)) | N82: =IF($A82="","",IF(每月预算!$B$29="雪崩法",计算_雪崩!BE101,计算_雪球!BE101)) | O82: =IF($A82="","",IF(每月预算!$B$29="雪崩法",计算_雪崩!BD101,计算_雪球!BD101))
A83: =IF(79<=$R$2,79,"") | B83: =IF($A83="","",计算_雪球!B102) | C83: =IF(OR($A83="",C$4=""),"",IF(每月预算!$B$29="雪崩法",计算_雪崩!I102,计算_雪球!I102)) | D83: =IF(OR($A83="",D$4=""),"",IF(每月预算!$B$29="雪崩法",计算_雪崩!N102,计算_雪球!N102)) | E83: =IF(OR($A83="",E$4=""),"",IF(每月预算!$B$29="雪崩法",计算_雪崩!S102,计算_雪球!S102)) | F83: =IF(OR($A83="",F$4=""),"",IF(每月预算!$B$29="雪崩法",计算_雪崩!X102,计算_雪球!X102)) | G83: =IF(OR($A83="",G$4=""),"",IF(每月预算!$B$29="雪崩法",计算_雪崩!AC102,计算_雪球!AC102)) | H83: =IF(OR($A83="",H$4=""),"",IF(每月预算!$B$29="雪崩法",计算_雪崩!AH102,计算_雪球!AH102)) | I83: =IF(OR($A83="",I$4=""),"",IF(每月预算!$B$29="雪崩法",计算_雪崩!AM102,计算_雪球!AM102)) | J83: =IF(OR($A83="",J$4=""),"",IF(每月预算!$B$29="雪崩法",计算_雪崩!AR102,计算_雪球!AR102)) | K83: =IF(OR($A83="",K$4=""),"",IF(每月预算!$B$29="雪崩法",计算_雪崩!AW102,计算_雪球!AW102)) | L83: =IF(OR($A83="",L$4=""),"",IF(每月预算!$B$29="雪崩法",计算_雪崩!BB102,计算_雪球!BB102)) | M83: =IF($A83="","",IF(每月预算!$B$29="雪崩法",计算_雪崩!BC102,计算_雪球!BC102)) | N83: =IF($A83="","",IF(每月预算!$B$29="雪崩法",计算_雪崩!BE102,计算_雪球!BE102)) | O83: =IF($A83="","",IF(每月预算!$B$29="雪崩法",计算_雪崩!BD102,计算_雪球!BD102))
A84: =IF(80<=$R$2,80,"") | B84: =IF($A84="","",计算_雪球!B103) | C84: =IF(OR($A84="",C$4=""),"",IF(每月预算!$B$29="雪崩法",计算_雪崩!I103,计算_雪球!I103)) | D84: =IF(OR($A84="",D$4=""),"",IF(每月预算!$B$29="雪崩法",计算_雪崩!N103,计算_雪球!N103)) | E84: =IF(OR($A84="",E$4=""),"",IF(每月预算!$B$29="雪崩法",计算_雪崩!S103,计算_雪球!S103)) | F84: =IF(OR($A84="",F$4=""),"",IF(每月预算!$B$29="雪崩法",计算_雪崩!X103,计算_雪球!X103)) | G84: =IF(OR($A84="",G$4=""),"",IF(每月预算!$B$29="雪崩法",计算_雪崩!AC103,计算_雪球!AC103)) | H84: =IF(OR($A84="",H$4=""),"",IF(每月预算!$B$29="雪崩法",计算_雪崩!AH103,计算_雪球!AH103)) | I84: =IF(OR($A84="",I$4=""),"",IF(每月预算!$B$29="雪崩法",计算_雪崩!AM103,计算_雪球!AM103)) | J84: =IF(OR($A84="",J$4=""),"",IF(每月预算!$B$29="雪崩法",计算_雪崩!AR103,计算_雪球!AR103)) | K84: =IF(OR($A84="",K$4=""),"",IF(每月预算!$B$29="雪崩法",计算_雪崩!AW103,计算_雪球!AW103)) | L84: =IF(OR($A84="",L$4=""),"",IF(每月预算!$B$29="雪崩法",计算_雪崩!BB103,计算_雪球!BB103)) | M84: =IF($A84="","",IF(每月预算!$B$29="雪崩法",计算_雪崩!BC103,计算_雪球!BC103)) | N84: =IF($A84="","",IF(每月预算!$B$29="雪崩法",计算_雪崩!BE103,计算_雪球!BE103)) | O84: =IF($A84="","",IF(每月预算!$B$29="雪崩法",计算_雪崩!BD103,计算_雪球!BD103))
A85: =IF(81<=$R$2,81,"") | B85: =IF($A85="","",计算_雪球!B104) | C85: =IF(OR($A85="",C$4=""),"",IF(每月预算!$B$29="雪崩法",计算_雪崩!I104,计算_雪球!I104)) | D85: =IF(OR($A85="",D$4=""),"",IF(每月预算!$B$29="雪崩法",计算_雪崩!N104,计算_雪球!N104)) | E85: =IF(OR($A85="",E$4=""),"",IF(每月预算!$B$29="雪崩法",计算_雪崩!S104,计算_雪球!S104)) | F85: =IF(OR($A85="",F$4=""),"",IF(每月预算!$B$29="雪崩法",计算_雪崩!X104,计算_雪球!X104)) | G85: =IF(OR($A85="",G$4=""),"",IF(每月预算!$B$29="雪崩法",计算_雪崩!AC104,计算_雪球!AC104)) | H85: =IF(OR($A85="",H$4=""),"",IF(每月预算!$B$29="雪崩法",计算_雪崩!AH104,计算_雪球!AH104)) | I85: =IF(OR($A85="",I$4=""),"",IF(每月预算!$B$29="雪崩法",计算_雪崩!AM104,计算_雪球!AM104)) | J85: =IF(OR($A85="",J$4=""),"",IF(每月预算!$B$29="雪崩法",计算_雪崩!AR104,计算_雪球!AR104)) | K85: =IF(OR($A85="",K$4=""),"",IF(每月预算!$B$29="雪崩法",计算_雪崩!AW104,计算_雪球!AW104)) | L85: =IF(OR($A85="",L$4=""),"",IF(每月预算!$B$29="雪崩法",计算_雪崩!BB104,计算_雪球!BB104)) | M85: =IF($A85="","",IF(每月预算!$B$29="雪崩法",计算_雪崩!BC104,计算_雪球!BC104)) | N85: =IF($A85="","",IF(每月预算!$B$29="雪崩法",计算_雪崩!BE104,计算_雪球!BE104)) | O85: =IF($A85="","",IF(每月预算!$B$29="雪崩法",计算_雪崩!BD104,计算_雪球!BD104))
A86: =IF(82<=$R$2,82,"") | B86: =IF($A86="","",计算_雪球!B105) | C86: =IF(OR($A86="",C$4=""),"",IF(每月预算!$B$29="雪崩法",计算_雪崩!I105,计算_雪球!I105)) | D86: =IF(OR($A86="",D$4=""),"",IF(每月预算!$B$29="雪崩法",计算_雪崩!N105,计算_雪球!N105)) | E86: =IF(OR($A86="",E$4=""),"",IF(每月预算!$B$29="雪崩法",计算_雪崩!S105,计算_雪球!S105)) | F86: =IF(OR($A86="",F$4=""),"",IF(每月预算!$B$29="雪崩法",计算_雪崩!X105,计算_雪球!X105)) | G86: =IF(OR($A86="",G$4=""),"",IF(每月预算!$B$29="雪崩法",计算_雪崩!AC105,计算_雪球!AC105)) | H86: =IF(OR($A86="",H$4=""),"",IF(每月预算!$B$29="雪崩法",计算_雪崩!AH105,计算_雪球!AH105)) | I86: =IF(OR($A86="",I$4=""),"",IF(每月预算!$B$29="雪崩法",计算_雪崩!AM105,计算_雪球!AM105)) | J86: =IF(OR($A86="",J$4=""),"",IF(每月预算!$B$29="雪崩法",计算_雪崩!AR105,计算_雪球!AR105)) | K86: =IF(OR($A86="",K$4=""),"",IF(每月预算!$B$29="雪崩法",计算_雪崩!AW105,计算_雪球!AW105)) | L86: =IF(OR($A86="",L$4=""),"",IF(每月预算!$B$29="雪崩法",计算_雪崩!BB105,计算_雪球!BB105)) | M86: =IF($A86="","",IF(每月预算!$B$29="雪崩法",计算_雪崩!BC105,计算_雪球!BC105)) | N86: =IF($A86="","",IF(每月预算!$B$29="雪崩法",计算_雪崩!BE105,计算_雪球!BE105)) | O86: =IF($A86="","",IF(每月预算!$B$29="雪崩法",计算_雪崩!BD105,计算_雪球!BD105))
A87: =IF(83<=$R$2,83,"") | B87: =IF($A87="","",计算_雪球!B106) | C87: =IF(OR($A87="",C$4=""),"",IF(每月预算!$B$29="雪崩法",计算_雪崩!I106,计算_雪球!I106)) | D87: =IF(OR($A87="",D$4=""),"",IF(每月预算!$B$29="雪崩法",计算_雪崩!N106,计算_雪球!N106)) | E87: =IF(OR($A87="",E$4=""),"",IF(每月预算!$B$29="雪崩法",计算_雪崩!S106,计算_雪球!S106)) | F87: =IF(OR($A87="",F$4=""),"",IF(每月预算!$B$29="雪崩法",计算_雪崩!X106,计算_雪球!X106)) | G87: =IF(OR($A87="",G$4=""),"",IF(每月预算!$B$29="雪崩法",计算_雪崩!AC106,计算_雪球!AC106)) | H87: =IF(OR($A87="",H$4=""),"",IF(每月预算!$B$29="雪崩法",计算_雪崩!AH106,计算_雪球!AH106)) | I87: =IF(OR($A87="",I$4=""),"",IF(每月预算!$B$29="雪崩法",计算_雪崩!AM106,计算_雪球!AM106)) | J87: =IF(OR($A87="",J$4=""),"",IF(每月预算!$B$29="雪崩法",计算_雪崩!AR106,计算_雪球!AR106)) | K87: =IF(OR($A87="",K$4=""),"",IF(每月预算!$B$29="雪崩法",计算_雪崩!AW106,计算_雪球!AW106)) | L87: =IF(OR($A87="",L$4=""),"",IF(每月预算!$B$29="雪崩法",计算_雪崩!BB106,计算_雪球!BB106)) | M87: =IF($A87="","",IF(每月预算!$B$29="雪崩法",计算_雪崩!BC106,计算_雪球!BC106)) | N87: =IF($A87="","",IF(每月预算!$B$29="雪崩法",计算_雪崩!BE106,计算_雪球!BE106)) | O87: =IF($A87="","",IF(每月预算!$B$29="雪崩法",计算_雪崩!BD106,计算_雪球!BD106))
A88: =IF(84<=$R$2,84,"") | B88: =IF($A88="","",计算_雪球!B107) | C88: =IF(OR($A88="",C$4=""),"",IF(每月预算!$B$29="雪崩法",计算_雪崩!I107,计算_雪球!I107)) | D88: =IF(OR($A88="",D$4=""),"",IF(每月预算!$B$29="雪崩法",计算_雪崩!N107,计算_雪球!N107)) | E88: =IF(OR($A88="",E$4=""),"",IF(每月预算!$B$29="雪崩法",计算_雪崩!S107,计算_雪球!S107)) | F88: =IF(OR($A88="",F$4=""),"",IF(每月预算!$B$29="雪崩法",计算_雪崩!X107,计算_雪球!X107)) | G88: =IF(OR($A88="",G$4=""),"",IF(每月预算!$B$29="雪崩法",计算_雪崩!AC107,计算_雪球!AC107)) | H88: =IF(OR($A88="",H$4=""),"",IF(每月预算!$B$29="雪崩法",计算_雪崩!AH107,计算_雪球!AH107)) | I88: =IF(OR($A88="",I$4=""),"",IF(每月预算!$B$29="雪崩法",计算_雪崩!AM107,计算_雪球!AM107)) | J88: =IF(OR($A88="",J$4=""),"",IF(每月预算!$B$29="雪崩法",计算_雪崩!AR107,计算_雪球!AR107)) | K88: =IF(OR($A88="",K$4=""),"",IF(每月预算!$B$29="雪崩法",计算_雪崩!AW107,计算_雪球!AW107)) | L88: =IF(OR($A88="",L$4=""),"",IF(每月预算!$B$29="雪崩法",计算_雪崩!BB107,计算_雪球!BB107)) | M88: =IF($A88="","",IF(每月预算!$B$29="雪崩法",计算_雪崩!BC107,计算_雪球!BC107)) | N88: =IF($A88="","",IF(每月预算!$B$29="雪崩法",计算_雪崩!BE107,计算_雪球!BE107)) | O88: =IF($A88="","",IF(每月预算!$B$29="雪崩法",计算_雪崩!BD107,计算_雪球!BD107))
A89: =IF(85<=$R$2,85,"") | B89: =IF($A89="","",计算_雪球!B108) | C89: =IF(OR($A89="",C$4=""),"",IF(每月预算!$B$29="雪崩法",计算_雪崩!I108,计算_雪球!I108)) | D89: =IF(OR($A89="",D$4=""),"",IF(每月预算!$B$29="雪崩法",计算_雪崩!N108,计算_雪球!N108)) | E89: =IF(OR($A89="",E$4=""),"",IF(每月预算!$B$29="雪崩法",计算_雪崩!S108,计算_雪球!S108)) | F89: =IF(OR($A89="",F$4=""),"",IF(每月预算!$B$29="雪崩法",计算_雪崩!X108,计算_雪球!X108)) | G89: =IF(OR($A89="",G$4=""),"",IF(每月预算!$B$29="雪崩法",计算_雪崩!AC108,计算_雪球!AC108)) | H89: =IF(OR($A89="",H$4=""),"",IF(每月预算!$B$29="雪崩法",计算_雪崩!AH108,计算_雪球!AH108)) | I89: =IF(OR($A89="",I$4=""),"",IF(每月预算!$B$29="雪崩法",计算_雪崩!AM108,计算_雪球!AM108)) | J89: =IF(OR($A89="",J$4=""),"",IF(每月预算!$B$29="雪崩法",计算_雪崩!AR108,计算_雪球!AR108)) | K89: =IF(OR($A89="",K$4=""),"",IF(每月预算!$B$29="雪崩法",计算_雪崩!AW108,计算_雪球!AW108)) | L89: =IF(OR($A89="",L$4=""),"",IF(每月预算!$B$29="雪崩法",计算_雪崩!BB108,计算_雪球!BB108)) | M89: =IF($A89="","",IF(每月预算!$B$29="雪崩法",计算_雪崩!BC108,计算_雪球!BC108)) | N89: =IF($A89="","",IF(每月预算!$B$29="雪崩法",计算_雪崩!BE108,计算_雪球!BE108)) | O89: =IF($A89="","",IF(每月预算!$B$29="雪崩法",计算_雪崩!BD108,计算_雪球!BD108))
A90: =IF(86<=$R$2,86,"") | B90: =IF($A90="","",计算_雪球!B109) | C90: =IF(OR($A90="",C$4=""),"",IF(每月预算!$B$29="雪崩法",计算_雪崩!I109,计算_雪球!I109)) | D90: =IF(OR($A90="",D$4=""),"",IF(每月预算!$B$29="雪崩法",计算_雪崩!N109,计算_雪球!N109)) | E90: =IF(OR($A90="",E$4=""),"",IF(每月预算!$B$29="雪崩法",计算_雪崩!S109,计算_雪球!S109)) | F90: =IF(OR($A90="",F$4=""),"",IF(每月预算!$B$29="雪崩法",计算_雪崩!X109,计算_雪球!X109)) | G90: =IF(OR($A90="",G$4=""),"",IF(每月预算!$B$29="雪崩法",计算_雪崩!AC109,计算_雪球!AC109)) | H90: =IF(OR($A90="",H$4=""),"",IF(每月预算!$B$29="雪崩法",计算_雪崩!AH109,计算_雪球!AH109)) | I90: =IF(OR($A90="",I$4=""),"",IF(每月预算!$B$29="雪崩法",计算_雪崩!AM109,计算_雪球!AM109)) | J90: =IF(OR($A90="",J$4=""),"",IF(每月预算!$B$29="雪崩法",计算_雪崩!AR109,计算_雪球!AR109)) | K90: =IF(OR($A90="",K$4=""),"",IF(每月预算!$B$29="雪崩法",计算_雪崩!AW109,计算_雪球!AW109)) | L90: =IF(OR($A90="",L$4=""),"",IF(每月预算!$B$29="雪崩法",计算_雪崩!BB109,计算_雪球!BB109)) | M90: =IF($A90="","",IF(每月预算!$B$29="雪崩法",计算_雪崩!BC109,计算_雪球!BC109)) | N90: =IF($A90="","",IF(每月预算!$B$29="雪崩法",计算_雪崩!BE109,计算_雪球!BE109)) | O90: =IF($A90="","",IF(每月预算!$B$29="雪崩法",计算_雪崩!BD109,计算_雪球!BD109))
A91: =IF(87<=$R$2,87,"") | B91: =IF($A91="","",计算_雪球!B110) | C91: =IF(OR($A91="",C$4=""),"",IF(每月预算!$B$29="雪崩法",计算_雪崩!I110,计算_雪球!I110)) | D91: =IF(OR($A91="",D$4=""),"",IF(每月预算!$B$29="雪崩法",计算_雪崩!N110,计算_雪球!N110)) | E91: =IF(OR($A91="",E$4=""),"",IF(每月预算!$B$29="雪崩法",计算_雪崩!S110,计算_雪球!S110)) | F91: =IF(OR($A91="",F$4=""),"",IF(每月预算!$B$29="雪崩法",计算_雪崩!X110,计算_雪球!X110)) | G91: =IF(OR($A91="",G$4=""),"",IF(每月预算!$B$29="雪崩法",计算_雪崩!AC110,计算_雪球!AC110)) | H91: =IF(OR($A91="",H$4=""),"",IF(每月预算!$B$29="雪崩法",计算_雪崩!AH110,计算_雪球!AH110)) | I91: =IF(OR($A91="",I$4=""),"",IF(每月预算!$B$29="雪崩法",计算_雪崩!AM110,计算_雪球!AM110)) | J91: =IF(OR($A91="",J$4=""),"",IF(每月预算!$B$29="雪崩法",计算_雪崩!AR110,计算_雪球!AR110)) | K91: =IF(OR($A91="",K$4=""),"",IF(每月预算!$B$29="雪崩法",计算_雪崩!AW110,计算_雪球!AW110)) | L91: =IF(OR($A91="",L$4=""),"",IF(每月预算!$B$29="雪崩法",计算_雪崩!BB110,计算_雪球!BB110)) | M91: =IF($A91="","",IF(每月预算!$B$29="雪崩法",计算_雪崩!BC110,计算_雪球!BC110)) | N91: =IF($A91="","",IF(每月预算!$B$29="雪崩法",计算_雪崩!BE110,计算_雪球!BE110)) | O91: =IF($A91="","",IF(每月预算!$B$29="雪崩法",计算_雪崩!BD110,计算_雪球!BD110))
A92: =IF(88<=$R$2,88,"") | B92: =IF($A92="","",计算_雪球!B111) | C92: =IF(OR($A92="",C$4=""),"",IF(每月预算!$B$29="雪崩法",计算_雪崩!I111,计算_雪球!I111)) | D92: =IF(OR($A92="",D$4=""),"",IF(每月预算!$B$29="雪崩法",计算_雪崩!N111,计算_雪球!N111)) | E92: =IF(OR($A92="",E$4=""),"",IF(每月预算!$B$29="雪崩法",计算_雪崩!S111,计算_雪球!S111)) | F92: =IF(OR($A92="",F$4=""),"",IF(每月预算!$B$29="雪崩法",计算_雪崩!X111,计算_雪球!X111)) | G92: =IF(OR($A92="",G$4=""),"",IF(每月预算!$B$29="雪崩法",计算_雪崩!AC111,计算_雪球!AC111)) | H92: =IF(OR($A92="",H$4=""),"",IF(每月预算!$B$29="雪崩法",计算_雪崩!AH111,计算_雪球!AH111)) | I92: =IF(OR($A92="",I$4=""),"",IF(每月预算!$B$29="雪崩法",计算_雪崩!AM111,计算_雪球!AM111)) | J92: =IF(OR($A92="",J$4=""),"",IF(每月预算!$B$29="雪崩法",计算_雪崩!AR111,计算_雪球!AR111)) | K92: =IF(OR($A92="",K$4=""),"",IF(每月预算!$B$29="雪崩法",计算_雪崩!AW111,计算_雪球!AW111)) | L92: =IF(OR($A92="",L$4=""),"",IF(每月预算!$B$29="雪崩法",计算_雪崩!BB111,计算_雪球!BB111)) | M92: =IF($A92="","",IF(每月预算!$B$29="雪崩法",计算_雪崩!BC111,计算_雪球!BC111)) | N92: =IF($A92="","",IF(每月预算!$B$29="雪崩法",计算_雪崩!BE111,计算_雪球!BE111)) | O92: =IF($A92="","",IF(每月预算!$B$29="雪崩法",计算_雪崩!BD111,计算_雪球!BD111))
A93: =IF(89<=$R$2,89,"") | B93: =IF($A93="","",计算_雪球!B112) | C93: =IF(OR($A93="",C$4=""),"",IF(每月预算!$B$29="雪崩法",计算_雪崩!I112,计算_雪球!I112)) | D93: =IF(OR($A93="",D$4=""),"",IF(每月预算!$B$29="雪崩法",计算_雪崩!N112,计算_雪球!N112)) | E93: =IF(OR($A93="",E$4=""),"",IF(每月预算!$B$29="雪崩法",计算_雪崩!S112,计算_雪球!S112)) | F93: =IF(OR($A93="",F$4=""),"",IF(每月预算!$B$29="雪崩法",计算_雪崩!X112,计算_雪球!X112)) | G93: =IF(OR($A93="",G$4=""),"",IF(每月预算!$B$29="雪崩法",计算_雪崩!AC112,计算_雪球!AC112)) | H93: =IF(OR($A93="",H$4=""),"",IF(每月预算!$B$29="雪崩法",计算_雪崩!AH112,计算_雪球!AH112)) | I93: =IF(OR($A93="",I$4=""),"",IF(每月预算!$B$29="雪崩法",计算_雪崩!AM112,计算_雪球!AM112)) | J93: =IF(OR($A93="",J$4=""),"",IF(每月预算!$B$29="雪崩法",计算_雪崩!AR112,计算_雪球!AR112)) | K93: =IF(OR($A93="",K$4=""),"",IF(每月预算!$B$29="雪崩法",计算_雪崩!AW112,计算_雪球!AW112)) | L93: =IF(OR($A93="",L$4=""),"",IF(每月预算!$B$29="雪崩法",计算_雪崩!BB112,计算_雪球!BB112)) | M93: =IF($A93="","",IF(每月预算!$B$29="雪崩法",计算_雪崩!BC112,计算_雪球!BC112)) | N93: =IF($A93="","",IF(每月预算!$B$29="雪崩法",计算_雪崩!BE112,计算_雪球!BE112)) | O93: =IF($A93="","",IF(每月预算!$B$29="雪崩法",计算_雪崩!BD112,计算_雪球!BD112))
A94: =IF(90<=$R$2,90,"") | B94: =IF($A94="","",计算_雪球!B113) | C94: =IF(OR($A94="",C$4=""),"",IF(每月预算!$B$29="雪崩法",计算_雪崩!I113,计算_雪球!I113)) | D94: =IF(OR($A94="",D$4=""),"",IF(每月预算!$B$29="雪崩法",计算_雪崩!N113,计算_雪球!N113)) | E94: =IF(OR($A94="",E$4=""),"",IF(每月预算!$B$29="雪崩法",计算_雪崩!S113,计算_雪球!S113)) | F94: =IF(OR($A94="",F$4=""),"",IF(每月预算!$B$29="雪崩法",计算_雪崩!X113,计算_雪球!X113)) | G94: =IF(OR($A94="",G$4=""),"",IF(每月预算!$B$29="雪崩法",计算_雪崩!AC113,计算_雪球!AC113)) | H94: =IF(OR($A94="",H$4=""),"",IF(每月预算!$B$29="雪崩法",计算_雪崩!AH113,计算_雪球!AH113)) | I94: =IF(OR($A94="",I$4=""),"",IF(每月预算!$B$29="雪崩法",计算_雪崩!AM113,计算_雪球!AM113)) | J94: =IF(OR($A94="",J$4=""),"",IF(每月预算!$B$29="雪崩法",计算_雪崩!AR113,计算_雪球!AR113)) | K94: =IF(OR($A94="",K$4=""),"",IF(每月预算!$B$29="雪崩法",计算_雪崩!AW113,计算_雪球!AW113)) | L94: =IF(OR($A94="",L$4=""),"",IF(每月预算!$B$29="雪崩法",计算_雪崩!BB113,计算_雪球!BB113)) | M94: =IF($A94="","",IF(每月预算!$B$29="雪崩法",计算_雪崩!BC113,计算_雪球!BC113)) | N94: =IF($A94="","",IF(每月预算!$B$29="雪崩法",计算_雪崩!BE113,计算_雪球!BE113)) | O94: =IF($A94="","",IF(每月预算!$B$29="雪崩法",计算_雪崩!BD113,计算_雪球!BD113))
A95: =IF(91<=$R$2,91,"") | B95: =IF($A95="","",计算_雪球!B114) | C95: =IF(OR($A95="",C$4=""),"",IF(每月预算!$B$29="雪崩法",计算_雪崩!I114,计算_雪球!I114)) | D95: =IF(OR($A95="",D$4=""),"",IF(每月预算!$B$29="雪崩法",计算_雪崩!N114,计算_雪球!N114)) | E95: =IF(OR($A95="",E$4=""),"",IF(每月预算!$B$29="雪崩法",计算_雪崩!S114,计算_雪球!S114)) | F95: =IF(OR($A95="",F$4=""),"",IF(每月预算!$B$29="雪崩法",计算_雪崩!X114,计算_雪球!X114)) | G95: =IF(OR($A95="",G$4=""),"",IF(每月预算!$B$29="雪崩法",计算_雪崩!AC114,计算_雪球!AC114)) | H95: =IF(OR($A95="",H$4=""),"",IF(每月预算!$B$29="雪崩法",计算_雪崩!AH114,计算_雪球!AH114)) | I95: =IF(OR($A95="",I$4=""),"",IF(每月预算!$B$29="雪崩法",计算_雪崩!AM114,计算_雪球!AM114)) | J95: =IF(OR($A95="",J$4=""),"",IF(每月预算!$B$29="雪崩法",计算_雪崩!AR114,计算_雪球!AR114)) | K95: =IF(OR($A95="",K$4=""),"",IF(每月预算!$B$29="雪崩法",计算_雪崩!AW114,计算_雪球!AW114)) | L95: =IF(OR($A95="",L$4=""),"",IF(每月预算!$B$29="雪崩法",计算_雪崩!BB114,计算_雪球!BB114)) | M95: =IF($A95="","",IF(每月预算!$B$29="雪崩法",计算_雪崩!BC114,计算_雪球!BC114)) | N95: =IF($A95="","",IF(每月预算!$B$29="雪崩法",计算_雪崩!BE114,计算_雪球!BE114)) | O95: =IF($A95="","",IF(每月预算!$B$29="雪崩法",计算_雪崩!BD114,计算_雪球!BD114))
A96: =IF(92<=$R$2,92,"") | B96: =IF($A96="","",计算_雪球!B115) | C96: =IF(OR($A96="",C$4=""),"",IF(每月预算!$B$29="雪崩法",计算_雪崩!I115,计算_雪球!I115)) | D96: =IF(OR($A96="",D$4=""),"",IF(每月预算!$B$29="雪崩法",计算_雪崩!N115,计算_雪球!N115)) | E96: =IF(OR($A96="",E$4=""),"",IF(每月预算!$B$29="雪崩法",计算_雪崩!S115,计算_雪球!S115)) | F96: =IF(OR($A96="",F$4=""),"",IF(每月预算!$B$29="雪崩法",计算_雪崩!X115,计算_雪球!X115)) | G96: =IF(OR($A96="",G$4=""),"",IF(每月预算!$B$29="雪崩法",计算_雪崩!AC115,计算_雪球!AC115)) | H96: =IF(OR($A96="",H$4=""),"",IF(每月预算!$B$29="雪崩法",计算_雪崩!AH115,计算_雪球!AH115)) | I96: =IF(OR($A96="",I$4=""),"",IF(每月预算!$B$29="雪崩法",计算_雪崩!AM115,计算_雪球!AM115)) | J96: =IF(OR($A96="",J$4=""),"",IF(每月预算!$B$29="雪崩法",计算_雪崩!AR115,计算_雪球!AR115)) | K96: =IF(OR($A96="",K$4=""),"",IF(每月预算!$B$29="雪崩法",计算_雪崩!AW115,计算_雪球!AW115)) | L96: =IF(OR($A96="",L$4=""),"",IF(每月预算!$B$29="雪崩法",计算_雪崩!BB115,计算_雪球!BB115)) | M96: =IF($A96="","",IF(每月预算!$B$29="雪崩法",计算_雪崩!BC115,计算_雪球!BC115)) | N96: =IF($A96="","",IF(每月预算!$B$29="雪崩法",计算_雪崩!BE115,计算_雪球!BE115)) | O96: =IF($A96="","",IF(每月预算!$B$29="雪崩法",计算_雪崩!BD115,计算_雪球!BD115))
A97: =IF(93<=$R$2,93,"") | B97: =IF($A97="","",计算_雪球!B116) | C97: =IF(OR($A97="",C$4=""),"",IF(每月预算!$B$29="雪崩法",计算_雪崩!I116,计算_雪球!I116)) | D97: =IF(OR($A97="",D$4=""),"",IF(每月预算!$B$29="雪崩法",计算_雪崩!N116,计算_雪球!N116)) | E97: =IF(OR($A97="",E$4=""),"",IF(每月预算!$B$29="雪崩法",计算_雪崩!S116,计算_雪球!S116)) | F97: =IF(OR($A97="",F$4=""),"",IF(每月预算!$B$29="雪崩法",计算_雪崩!X116,计算_雪球!X116)) | G97: =IF(OR($A97="",G$4=""),"",IF(每月预算!$B$29="雪崩法",计算_雪崩!AC116,计算_雪球!AC116)) | H97: =IF(OR($A97="",H$4=""),"",IF(每月预算!$B$29="雪崩法",计算_雪崩!AH116,计算_雪球!AH116)) | I97: =IF(OR($A97="",I$4=""),"",IF(每月预算!$B$29="雪崩法",计算_雪崩!AM116,计算_雪球!AM116)) | J97: =IF(OR($A97="",J$4=""),"",IF(每月预算!$B$29="雪崩法",计算_雪崩!AR116,计算_雪球!AR116)) | K97: =IF(OR($A97="",K$4=""),"",IF(每月预算!$B$29="雪崩法",计算_雪崩!AW116,计算_雪球!AW116)) | L97: =IF(OR($A97="",L$4=""),"",IF(每月预算!$B$29="雪崩法",计算_雪崩!BB116,计算_雪球!BB116)) | M97: =IF($A97="","",IF(每月预算!$B$29="雪崩法",计算_雪崩!BC116,计算_雪球!BC116)) | N97: =IF($A97="","",IF(每月预算!$B$29="雪崩法",计算_雪崩!BE116,计算_雪球!BE116)) | O97: =IF($A97="","",IF(每月预算!$B$29="雪崩法",计算_雪崩!BD116,计算_雪球!BD116))
A98: =IF(94<=$R$2,94,"") | B98: =IF($A98="","",计算_雪球!B117) | C98: =IF(OR($A98="",C$4=""),"",IF(每月预算!$B$29="雪崩法",计算_雪崩!I117,计算_雪球!I117)) | D98: =IF(OR($A98="",D$4=""),"",IF(每月预算!$B$29="雪崩法",计算_雪崩!N117,计算_雪球!N117)) | E98: =IF(OR($A98="",E$4=""),"",IF(每月预算!$B$29="雪崩法",计算_雪崩!S117,计算_雪球!S117)) | F98: =IF(OR($A98="",F$4=""),"",IF(每月预算!$B$29="雪崩法",计算_雪崩!X117,计算_雪球!X117)) | G98: =IF(OR($A98="",G$4=""),"",IF(每月预算!$B$29="雪崩法",计算_雪崩!AC117,计算_雪球!AC117)) | H98: =IF(OR($A98="",H$4=""),"",IF(每月预算!$B$29="雪崩法",计算_雪崩!AH117,计算_雪球!AH117)) | I98: =IF(OR($A98="",I$4=""),"",IF(每月预算!$B$29="雪崩法",计算_雪崩!AM117,计算_雪球!AM117)) | J98: =IF(OR($A98="",J$4=""),"",IF(每月预算!$B$29="雪崩法",计算_雪崩!AR117,计算_雪球!AR117)) | K98: =IF(OR($A98="",K$4=""),"",IF(每月预算!$B$29="雪崩法",计算_雪崩!AW117,计算_雪球!AW117)) | L98: =IF(OR($A98="",L$4=""),"",IF(每月预算!$B$29="雪崩法",计算_雪崩!BB117,计算_雪球!BB117)) | M98: =IF($A98="","",IF(每月预算!$B$29="雪崩法",计算_雪崩!BC117,计算_雪球!BC117)) | N98: =IF($A98="","",IF(每月预算!$B$29="雪崩法",计算_雪崩!BE117,计算_雪球!BE117)) | O98: =IF($A98="","",IF(每月预算!$B$29="雪崩法",计算_雪崩!BD117,计算_雪球!BD117))
A99: =IF(95<=$R$2,95,"") | B99: =IF($A99="","",计算_雪球!B118) | C99: =IF(OR($A99="",C$4=""),"",IF(每月预算!$B$29="雪崩法",计算_雪崩!I118,计算_雪球!I118)) | D99: =IF(OR($A99="",D$4=""),"",IF(每月预算!$B$29="雪崩法",计算_雪崩!N118,计算_雪球!N118)) | E99: =IF(OR($A99="",E$4=""),"",IF(每月预算!$B$29="雪崩法",计算_雪崩!S118,计算_雪球!S118)) | F99: =IF(OR($A99="",F$4=""),"",IF(每月预算!$B$29="雪崩法",计算_雪崩!X118,计算_雪球!X118)) | G99: =IF(OR($A99="",G$4=""),"",IF(每月预算!$B$29="雪崩法",计算_雪崩!AC118,计算_雪球!AC118)) | H99: =IF(OR($A99="",H$4=""),"",IF(每月预算!$B$29="雪崩法",计算_雪崩!AH118,计算_雪球!AH118)) | I99: =IF(OR($A99="",I$4=""),"",IF(每月预算!$B$29="雪崩法",计算_雪崩!AM118,计算_雪球!AM118)) | J99: =IF(OR($A99="",J$4=""),"",IF(每月预算!$B$29="雪崩法",计算_雪崩!AR118,计算_雪球!AR118)) | K99: =IF(OR($A99="",K$4=""),"",IF(每月预算!$B$29="雪崩法",计算_雪崩!AW118,计算_雪球!AW118)) | L99: =IF(OR($A99="",L$4=""),"",IF(每月预算!$B$29="雪崩法",计算_雪崩!BB118,计算_雪球!BB118)) | M99: =IF($A99="","",IF(每月预算!$B$29="雪崩法",计算_雪崩!BC118,计算_雪球!BC118)) | N99: =IF($A99="","",IF(每月预算!$B$29="雪崩法",计算_雪崩!BE118,计算_雪球!BE118)) | O99: =IF($A99="","",IF(每月预算!$B$29="雪崩法",计算_雪崩!BD118,计算_雪球!BD118))
A100: =IF(96<=$R$2,96,"") | B100: =IF($A100="","",计算_雪球!B119) | C100: =IF(OR($A100="",C$4=""),"",IF(每月预算!$B$29="雪崩法",计算_雪崩!I119,计算_雪球!I119)) | D100: =IF(OR($A100="",D$4=""),"",IF(每月预算!$B$29="雪崩法",计算_雪崩!N119,计算_雪球!N119)) | E100: =IF(OR($A100="",E$4=""),"",IF(每月预算!$B$29="雪崩法",计算_雪崩!S119,计算_雪球!S119)) | F100: =IF(OR($A100="",F$4=""),"",IF(每月预算!$B$29="雪崩法",计算_雪崩!X119,计算_雪球!X119)) | G100: =IF(OR($A100="",G$4=""),"",IF(每月预算!$B$29="雪崩法",计算_雪崩!AC119,计算_雪球!AC119)) | H100: =IF(OR($A100="",H$4=""),"",IF(每月预算!$B$29="雪崩法",计算_雪崩!AH119,计算_雪球!AH119)) | I100: =IF(OR($A100="",I$4=""),"",IF(每月预算!$B$29="雪崩法",计算_雪崩!AM119,计算_雪球!AM119)) | J100: =IF(OR($A100="",J$4=""),"",IF(每月预算!$B$29="雪崩法",计算_雪崩!AR119,计算_雪球!AR119)) | K100: =IF(OR($A100="",K$4=""),"",IF(每月预算!$B$29="雪崩法",计算_雪崩!AW119,计算_雪球!AW119)) | L100: =IF(OR($A100="",L$4=""),"",IF(每月预算!$B$29="雪崩法",计算_雪崩!BB119,计算_雪球!BB119)) | M100: =IF($A100="","",IF(每月预算!$B$29="雪崩法",计算_雪崩!BC119,计算_雪球!BC119)) | N100: =IF($A100="","",IF(每月预算!$B$29="雪崩法",计算_雪崩!BE119,计算_雪球!BE119)) | O100: =IF($A100="","",IF(每月预算!$B$29="雪崩法",计算_雪崩!BD119,计算_雪球!BD119))
A101: =IF(97<=$R$2,97,"") | B101: =IF($A101="","",计算_雪球!B120) | C101: =IF(OR($A101="",C$4=""),"",IF(每月预算!$B$29="雪崩法",计算_雪崩!I120,计算_雪球!I120)) | D101: =IF(OR($A101="",D$4=""),"",IF(每月预算!$B$29="雪崩法",计算_雪崩!N120,计算_雪球!N120)) | E101: =IF(OR($A101="",E$4=""),"",IF(每月预算!$B$29="雪崩法",计算_雪崩!S120,计算_雪球!S120)) | F101: =IF(OR($A101="",F$4=""),"",IF(每月预算!$B$29="雪崩法",计算_雪崩!X120,计算_雪球!X120)) | G101: =IF(OR($A101="",G$4=""),"",IF(每月预算!$B$29="雪崩法",计算_雪崩!AC120,计算_雪球!AC120)) | H101: =IF(OR($A101="",H$4=""),"",IF(每月预算!$B$29="雪崩法",计算_雪崩!AH120,计算_雪球!AH120)) | I101: =IF(OR($A101="",I$4=""),"",IF(每月预算!$B$29="雪崩法",计算_雪崩!AM120,计算_雪球!AM120)) | J101: =IF(OR($A101="",J$4=""),"",IF(每月预算!$B$29="雪崩法",计算_雪崩!AR120,计算_雪球!AR120)) | K101: =IF(OR($A101="",K$4=""),"",IF(每月预算!$B$29="雪崩法",计算_雪崩!AW120,计算_雪球!AW120)) | L101: =IF(OR($A101="",L$4=""),"",IF(每月预算!$B$29="雪崩法",计算_雪崩!BB120,计算_雪球!BB120)) | M101: =IF($A101="","",IF(每月预算!$B$29="雪崩法",计算_雪崩!BC120,计算_雪球!BC120)) | N101: =IF($A101="","",IF(每月预算!$B$29="雪崩法",计算_雪崩!BE120,计算_雪球!BE120)) | O101: =IF($A101="","",IF(每月预算!$B$29="雪崩法",计算_雪崩!BD120,计算_雪球!BD120))
...

Sheet 利率换算
A1: 利率换算：把各种说法换成真实年化
A2: 填黄底蓝字的格子，绿底的就是真实年化。算出来的年化填回「债务清单」。
A4: ① 日息（比如“日息万五”）
A5: 日利率 | B5: 0.0005 | C5: 万五 = 0.05%
A6: 年化（单利） | B6: =B5*365 -> 0.1825
A8: ② 月息（比如“月息 1.5%”）
A9: 月利率 | B9: 0.015
A10: 年化 | B10: =B9*12 -> 0.18
A12: ③ 分期手续费（每期按最初总额收手续费）
A13: 分期金额（元） | B13: 12000
A14: 分几期 | B14: 12
A15: 每期手续费率 | B15: 0.006
A16: 每期要还 | B16: =B13/B14+B13*B15 -> 1072
A17: 手续费一共多少 | B17: =B13*B15*B14 -> 864
A18: 表面上的年费率 | B18: =B15*12 -> 0.072 | C18: 很多人以为是这个数
A19: 真实年化 | B19: =RATE(B14,-B16,B13)*12 -> 0.13034224 | C19: 你欠的钱每个月在变少，手续费却按最初总额收，所以真实年化接近表面的两倍
A21: ④ 只知道借到手多少、每期还多少（网贷常见）
A22: 实际到手多少（元） | B22: 10000 | C22: 被提前扣掉的“服务费”“砍头息”不算到手
A23: 分几期（按月） | B23: 12
A24: 每期还多少（元） | B24: 1000
A25: 一共多还了多少 | B25: =B23*B24-B22 -> 2000
A26: 真实年化 | B26: =RATE(B23,-B24,B22)*12 -> 0.35074249 | C26: =IF(B26>0.24,"超过 24%：持牌机构的个人贷款可以打 12378 投诉","") -> 超过 24%：持牌机构的个人贷款可以打 12378 投诉

Sheet 计算_雪球
A1: 自动计算（雪球法）—— 这一页不用改
A2: 每月利息 = 欠款 × 年化 ÷ 12；先还所有最低还款，剩下的钱按顺序砸向排在最前面的债。
A4: 顺序 | B4: 清单第几行 | C4: 名称 | D4: 初始欠款 | E4: 年化 | F4: 每月最低还款 | G4: 第几个月还清 | H4: 总利息
A5: 1 | B5: =IFERROR(MATCH(A5,债务清单!$J$5:$J$14,0),"") -> 2 | C5: =IF(B5="","",INDEX(债务清单!$B$5:$B$14,B5)) -> 信用卡B（分期） | D5: =IF(B5="",0,INDEX(债务清单!$D$5:$D$14,B5)) -> 12000 | E5: =IF(B5="",0,INDEX(债务清单!$O$5:$O$14,B5)) -> 0.13 | F5: =IF(B5="",0,N(INDEX(债务清单!$F$5:$F$14,B5))) -> 1072 | G5: =IF(D5<=0,"",IF(E263+F263-I263>0.01,"超过20年",COUNTIF(E24:E263,">0.005"))) -> 7 | H5: =SUM(F24:F263) -> 460.13
A6: 2 | B6: =IFERROR(MATCH(A6,债务清单!$J$5:$J$14,0),"") -> 4 | C6: =IF(B6="","",INDEX(债务清单!$B$5:$B$14,B6)) -> 亲友借款（老王） | D6: =IF(B6="",0,INDEX(债务清单!$D$5:$D$14,B6)) -> 20000 | E6: =IF(B6="",0,INDEX(债务清单!$O$5:$O$14,B6)) -> 0 | F6: =IF(B6="",0,N(INDEX(债务清单!$F$5:$F$14,B6))) -> 500 | G6: =IF(D6<=0,"",IF(J263+K263-N263>0.01,"超过20年",COUNTIF(J24:J263,">0.005"))) -> 13 | H6: =SUM(K24:K263) -> 0
A7: 3 | B7: =IFERROR(MATCH(A7,债务清单!$J$5:$J$14,0),"") -> 3 | C7: =IF(B7="","",INDEX(债务清单!$B$5:$B$14,B7)) -> 网贷X | D7: =IF(B7="",0,INDEX(债务清单!$D$5:$D$14,B7)) -> 25000 | E7: =IF(B7="",0,INDEX(债务清单!$O$5:$O$14,B7)) -> 0.24 | F7: =IF(B7="",0,N(INDEX(债务清单!$F$5:$F$14,B7))) -> 1350 | G7: =IF(D7<=0,"",IF(O263+P263-S263>0.01,"超过20年",COUNTIF(O24:O263,">0.005"))) -> 17 | H7: =SUM(P24:P263) -> 5546.51
A8: 4 | B8: =IFERROR(MATCH(A8,债务清单!$J$5:$J$14,0),"") -> 1 | C8: =IF(B8="","",INDEX(债务清单!$B$5:$B$14,B8)) -> 信用卡A | D8: =IF(B8="",0,INDEX(债务清单!$D$5:$D$14,B8)) -> 38000 | E8: =IF(B8="",0,INDEX(债务清单!$O$5:$O$14,B8)) -> 0.18 | F8: =IF(B8="",0,N(INDEX(债务清单!$F$5:$F$14,B8))) -> 1900 | G8: =IF(D8<=0,"",IF(T263+U263-X263>0.01,"超过20年",COUNTIF(T24:T263,">0.005"))) -> 19 | H8: =SUM(U24:U263) -> 6940.7
A9: 5 | B9: =IFERROR(MATCH(A9,债务清单!$J$5:$J$14,0),"") | C9: =IF(B9="","",INDEX(债务清单!$B$5:$B$14,B9)) | D9: =IF(B9="",0,INDEX(债务清单!$D$5:$D$14,B9)) -> 0 | E9: =IF(B9="",0,INDEX(债务清单!$O$5:$O$14,B9)) -> 0 | F9: =IF(B9="",0,N(INDEX(债务清单!$F$5:$F$14,B9))) -> 0 | G9: =IF(D9<=0,"",IF(Y263+Z263-AC263>0.01,"超过20年",COUNTIF(Y24:Y263,">0.005"))) | H9: =SUM(Z24:Z263) -> 0
A10: 6 | B10: =IFERROR(MATCH(A10,债务清单!$J$5:$J$14,0),"") | C10: =IF(B10="","",INDEX(债务清单!$B$5:$B$14,B10)) | D10: =IF(B10="",0,INDEX(债务清单!$D$5:$D$14,B10)) -> 0 | E10: =IF(B10="",0,INDEX(债务清单!$O$5:$O$14,B10)) -> 0 | F10: =IF(B10="",0,N(INDEX(债务清单!$F$5:$F$14,B10))) -> 0 | G10: =IF(D10<=0,"",IF(AD263+AE263-AH263>0.01,"超过20年",COUNTIF(AD24:AD263,">0.005"))) | H10: =SUM(AE24:AE263) -> 0
A11: 7 | B11: =IFERROR(MATCH(A11,债务清单!$J$5:$J$14,0),"") | C11: =IF(B11="","",INDEX(债务清单!$B$5:$B$14,B11)) | D11: =IF(B11="",0,INDEX(债务清单!$D$5:$D$14,B11)) -> 0 | E11: =IF(B11="",0,INDEX(债务清单!$O$5:$O$14,B11)) -> 0 | F11: =IF(B11="",0,N(INDEX(债务清单!$F$5:$F$14,B11))) -> 0 | G11: =IF(D11<=0,"",IF(AI263+AJ263-AM263>0.01,"超过20年",COUNTIF(AI24:AI263,">0.005"))) | H11: =SUM(AJ24:AJ263) -> 0
A12: 8 | B12: =IFERROR(MATCH(A12,债务清单!$J$5:$J$14,0),"") | C12: =IF(B12="","",INDEX(债务清单!$B$5:$B$14,B12)) | D12: =IF(B12="",0,INDEX(债务清单!$D$5:$D$14,B12)) -> 0 | E12: =IF(B12="",0,INDEX(债务清单!$O$5:$O$14,B12)) -> 0 | F12: =IF(B12="",0,N(INDEX(债务清单!$F$5:$F$14,B12))) -> 0 | G12: =IF(D12<=0,"",IF(AN263+AO263-AR263>0.01,"超过20年",COUNTIF(AN24:AN263,">0.005"))) | H12: =SUM(AO24:AO263) -> 0
A13: 9 | B13: =IFERROR(MATCH(A13,债务清单!$J$5:$J$14,0),"") | C13: =IF(B13="","",INDEX(债务清单!$B$5:$B$14,B13)) | D13: =IF(B13="",0,INDEX(债务清单!$D$5:$D$14,B13)) -> 0 | E13: =IF(B13="",0,INDEX(债务清单!$O$5:$O$14,B13)) -> 0 | F13: =IF(B13="",0,N(INDEX(债务清单!$F$5:$F$14,B13))) -> 0 | G13: =IF(D13<=0,"",IF(AS263+AT263-AW263>0.01,"超过20年",COUNTIF(AS24:AS263,">0.005"))) | H13: =SUM(AT24:AT263) -> 0
A14: 10 | B14: =IFERROR(MATCH(A14,债务清单!$J$5:$J$14,0),"") | C14: =IF(B14="","",INDEX(债务清单!$B$5:$B$14,B14)) | D14: =IF(B14="",0,INDEX(债务清单!$D$5:$D$14,B14)) -> 0 | E14: =IF(B14="",0,INDEX(债务清单!$O$5:$O$14,B14)) -> 0 | F14: =IF(B14="",0,N(INDEX(债务清单!$F$5:$F$14,B14))) -> 0 | G14: =IF(D14<=0,"",IF(AX263+AY263-BB263>0.01,"超过20年",COUNTIF(AX24:AX263,">0.005"))) | H14: =SUM(AY24:AY263) -> 0
A16: 每月还款总预算 | C16: =每月预算!B27 -> 5822
A17: 开始月份 | C17: =每月预算!B30 -> 46327
A18: 还清需要几个月 | C18: =IF(COUNTIF(G5:G14,"超过20年")>0,"超过20年",IF(COUNT(G5:G14)=0,0,MAX(G5:G14))) -> 19
A19: 总利息 | C19: =SUM(H5:H14) -> 12947.34
A20: 第一笔还清是第几个月 | C20: =IF(COUNT(G5:G14)=0,"",MIN(G5:G14)) -> 7
E22: =IF(C5="","第1笔（空）","第1笔："&C5) -> 第1笔：信用卡B（分期） | J22: =IF(C6="","第2笔（空）","第2笔："&C6) -> 第2笔：亲友借款（老王） | O22: =IF(C7="","第3笔（空）","第3笔："&C7) -> 第3笔：网贷X | T22: =IF(C8="","第4笔（空）","第4笔："&C8) -> 第4笔：信用卡A | Y22: =IF(C9="","第5笔（空）","第5笔："&C9) -> 第5笔（空） | AD22: =IF(C10="","第6笔（空）","第6笔："&C10) -> 第6笔（空） | AI22: =IF(C11="","第7笔（空）","第7笔："&C11) -> 第7笔（空） | AN22: =IF(C12="","第8笔（空）","第8笔："&C12) -> 第8笔（空） | AS22: =IF(C13="","第9笔（空）","第9笔："&C13) -> 第9笔（空） | AX22: =IF(C14="","第10笔（空）","第10笔："&C14) -> 第10笔（空）
A23: 月份 | B23: 日期 | C23: 最低还款部分合计 | D23: 可加速的钱 | E23: 月初欠款 | F23: 利息 | G23: 最低还款部分 | H23: 加速部分 | I23: 本月还款 | J23: 月初欠款 | K23: 利息 | L23: 最低还款部分 | M23: 加速部分 | N23: 本月还款 | O23: 月初欠款 | P23: 利息 | Q23: 最低还款部分 | R23: 加速部分 | S23: 本月还款 | T23: 月初欠款 | U23: 利息 | V23: 最低还款部分 | W23: 加速部分 | X23: 本月还款 | Y23: 月初欠款 | Z23: 利息 | AA23: 最低还款部分 | AB23: 加速部分 | AC23: 本月还款 | AD23: 月初欠款 | AE23: 利息 | AF23: 最低还款部分 | AG23: 加速部分 | AH23: 本月还款 | AI23: 月初欠款 | AJ23: 利息 | AK23: 最低还款部分 | AL23: 加速部分 | AM23: 本月还款 | AN23: 月初欠款 | AO23: 利息 | AP23: 最低还款部分 | AQ23: 加速部分 | AR23: 本月还款 | AS23: 月初欠款 | AT23: 利息 | AU23: 最低还款部分 | AV23: 加速部分 | AW23: 本月还款 | AX23: 月初欠款 | AY23: 利息 | AZ23: 最低还款部分 | BA23: 加速部分 | BB23: 本月还款 | BC23: 本月还款合计 | BD23: 月末还剩合计 | BE23: 加速钱给了
A24: 1 | B24: =EDATE($C$17,A24-1) -> 46327 | C24: =G24+L24+Q24+V24+AA24+AF24+AK24+AP24+AU24+AZ24 -> 4822 | D24: =MAX(0,$C$16-C24) -> 1000 | E24: =$D$5 -> 12000 | F24: =ROUND(E24*$E$5/12,2) -> 130 | G24: =MIN($F$5,E24+F24) -> 1072 | H24: =MAX(0,MIN(E24+F24-G24,$D24)) -> 1000 | I24: =G24+H24 -> 2072 | J24: =$D$6 -> 20000 | K24: =ROUND(J24*$E$6/12,2) -> 0 | L24: =MIN($F$6,J24+K24) -> 500 | M24: =MAX(0,MIN(J24+K24-L24,$D24-(H24))) -> 0 | N24: =L24+M24 -> 500 | O24: =$D$7 -> 25000 | P24: =ROUND(O24*$E$7/12,2) -> 500 | Q24: =MIN($F$7,O24+P24) -> 1350 | R24: =MAX(0,MIN(O24+P24-Q24,$D24-(H24+M24))) -> 0 | S24: =Q24+R24 -> 1350 | T24: =$D$8 -> 38000 | U24: =ROUND(T24*$E$8/12,2) -> 570 | V24: =MIN($F$8,T24+U24) -> 1900 | W24: =MAX(0,MIN(T24+U24-V24,$D24-(H24+M24+R24))) -> 0 | X24: =V24+W24 -> 1900 | Y24: =$D$9 -> 0 | Z24: =ROUND(Y24*$E$9/12,2) -> 0 | AA24: =MIN($F$9,Y24+Z24) -> 0 | AB24: =MAX(0,MIN(Y24+Z24-AA24,$D24-(H24+M24+R24+W24))) -> 0 | AC24: =AA24+AB24 -> 0 | AD24: =$D$10 -> 0 | AE24: =ROUND(AD24*$E$10/12,2) -> 0 | AF24: =MIN($F$10,AD24+AE24) -> 0 | AG24: =MAX(0,MIN(AD24+AE24-AF24,$D24-(H24+M24+R24+W24+AB24))) -> 0 | AH24: =AF24+AG24 -> 0 | AI24: =$D$11 -> 0 | AJ24: =ROUND(AI24*$E$11/12,2) -> 0 | AK24: =MIN($F$11,AI24+AJ24) -> 0 | AL24: =MAX(0,MIN(AI24+AJ24-AK24,$D24-(H24+M24+R24+W24+AB24+AG24))) -> 0 | AM24: =AK24+AL24 -> 0 | AN24: =$D$12 -> 0 | AO24: =ROUND(AN24*$E$12/12,2) -> 0 | AP24: =MIN($F$12,AN24+AO24) -> 0 | AQ24: =MAX(0,MIN(AN24+AO24-AP24,$D24-(H24+M24+R24+W24+AB24+AG24+AL24))) -> 0 | AR24: =AP24+AQ24 -> 0 | AS24: =$D$13 -> 0 | AT24: =ROUND(AS24*$E$13/12,2) -> 0 | AU24: =MIN($F$13,AS24+AT24) -> 0 | AV24: =MAX(0,MIN(AS24+AT24-AU24,$D24-(H24+M24+R24+W24+AB24+AG24+AL24+AQ24))) -> 0 | AW24: =AU24+AV24 -> 0 | AX24: =$D$14 -> 0 | AY24: =ROUND(AX24*$E$14/12,2) -> 0 | AZ24: =MIN($F$14,AX24+AY24) -> 0 | BA24: =MAX(0,MIN(AX24+AY24-AZ24,$D24-(H24+M24+R24+W24+AB24+AG24+AL24+AQ24+AV24))) -> 0 | BB24: =AZ24+BA24 -> 0 | BC24: =I24+N24+S24+X24+AC24+AH24+AM24+AR24+AW24+BB24 -> 5822 | BD24: =ROUND((E24+F24-I24)+(J24+K24-N24)+(O24+P24-S24)+(T24+U24-X24)+(Y24+Z24-AC24)+(AD24+AE24-AH24)+(AI24+AJ24-AM24)+(AN24+AO24-AR24)+(AS24+AT24-AW24)+(AX24+AY24-BB24),2) -> 90378 | BE24: =IF(H24>0.005,$C$5,IF(M24>0.005,$C$6,IF(R24>0.005,$C$7,IF(W24>0.005,$C$8,IF(AB24>0.005,$C$9,IF(AG24>0.005,$C$10,IF(AL24>0.005,$C$11,IF(AQ24>0.005,$C$12,IF(AV24>0.005,$C$13,IF(BA24>0.005,$C$14,"")))))))))) -> 信用卡B（分期）
A25: 2 | B25: =EDATE($C$17,A25-1) -> 46357 | C25: =G25+L25+Q25+V25+AA25+AF25+AK25+AP25+AU25+AZ25 -> 4822 | D25: =MAX(0,$C$16-C25) -> 1000 | E25: =ROUND(MAX(0,E24+F24-I24),2) -> 10058 | F25: =ROUND(E25*$E$5/12,2) -> 108.96 | G25: =MIN($F$5,E25+F25) -> 1072 | H25: =MAX(0,MIN(E25+F25-G25,$D25)) -> 1000 | I25: =G25+H25 -> 2072 | J25: =ROUND(MAX(0,J24+K24-N24),2) -> 19500 | K25: =ROUND(J25*$E$6/12,2) -> 0 | L25: =MIN($F$6,J25+K25) -> 500 | M25: =MAX(0,MIN(J25+K25-L25,$D25-(H25))) -> 0 | N25: =L25+M25 -> 500 | O25: =ROUND(MAX(0,O24+P24-S24),2) -> 24150 | P25: =ROUND(O25*$E$7/12,2) -> 483 | Q25: =MIN($F$7,O25+P25) -> 1350 | R25: =MAX(0,MIN(O25+P25-Q25,$D25-(H25+M25))) -> 0 | S25: =Q25+R25 -> 1350 | T25: =ROUND(MAX(0,T24+U24-X24),2) -> 36670 | U25: =ROUND(T25*$E$8/12,2) -> 550.05 | V25: =MIN($F$8,T25+U25) -> 1900 | W25: =MAX(0,MIN(T25+U25-V25,$D25-(H25+M25+R25))) -> 0 | X25: =V25+W25 -> 1900 | Y25: =ROUND(MAX(0,Y24+Z24-AC24),2) -> 0 | Z25: =ROUND(Y25*$E$9/12,2) -> 0 | AA25: =MIN($F$9,Y25+Z25) -> 0 | AB25: =MAX(0,MIN(Y25+Z25-AA25,$D25-(H25+M25+R25+W25))) -> 0 | AC25: =AA25+AB25 -> 0 | AD25: =ROUND(MAX(0,AD24+AE24-AH24),2) -> 0 | AE25: =ROUND(AD25*$E$10/12,2) -> 0 | AF25: =MIN($F$10,AD25+AE25) -> 0 | AG25: =MAX(0,MIN(AD25+AE25-AF25,$D25-(H25+M25+R25+W25+AB25))) -> 0 | AH25: =AF25+AG25 -> 0 | AI25: =ROUND(MAX(0,AI24+AJ24-AM24),2) -> 0 | AJ25: =ROUND(AI25*$E$11/12,2) -> 0 | AK25: =MIN($F$11,AI25+AJ25) -> 0 | AL25: =MAX(0,MIN(AI25+AJ25-AK25,$D25-(H25+M25+R25+W25+AB25+AG25))) -> 0 | AM25: =AK25+AL25 -> 0 | AN25: =ROUND(MAX(0,AN24+AO24-AR24),2) -> 0 | AO25: =ROUND(AN25*$E$12/12,2) -> 0 | AP25: =MIN($F$12,AN25+AO25) -> 0 | AQ25: =MAX(0,MIN(AN25+AO25-AP25,$D25-(H25+M25+R25+W25+AB25+AG25+AL25))) -> 0 | AR25: =AP25+AQ25 -> 0 | AS25: =ROUND(MAX(0,AS24+AT24-AW24),2) -> 0 | AT25: =ROUND(AS25*$E$13/12,2) -> 0 | AU25: =MIN($F$13,AS25+AT25) -> 0 | AV25: =MAX(0,MIN(AS25+AT25-AU25,$D25-(H25+M25+R25+W25+AB25+AG25+AL25+AQ25))) -> 0 | AW25: =AU25+AV25 -> 0 | AX25: =ROUND(MAX(0,AX24+AY24-BB24),2) -> 0 | AY25: =ROUND(AX25*$E$14/12,2) -> 0 | AZ25: =MIN($F$14,AX25+AY25) -> 0 | BA25: =MAX(0,MIN(AX25+AY25-AZ25,$D25-(H25+M25+R25+W25+AB25+AG25+AL25+AQ25+AV25))) -> 0 | BB25: =AZ25+BA25 -> 0 | BC25: =I25+N25+S25+X25+AC25+AH25+AM25+AR25+AW25+BB25 -> 5822 | BD25: =ROUND((E25+F25-I25)+(J25+K25-N25)+(O25+P25-S25)+(T25+U25-X25)+(Y25+Z25-AC25)+(AD25+AE25-AH25)+(AI25+AJ25-AM25)+(AN25+AO25-AR25)+(AS25+AT25-AW25)+(AX25+AY25-BB25),2) -> 85698.01 | BE25: =IF(H25>0.005,$C$5,IF(M25>0.005,$C$6,IF(R25>0.005,$C$7,IF(W25>0.005,$C$8,IF(AB25>0.005,$C$9,IF(AG25>0.005,$C$10,IF(AL25>0.005,$C$11,IF(AQ25>0.005,$C$12,IF(AV25>0.005,$C$13,IF(BA25>0.005,$C$14,"")))))))))) -> 信用卡B（分期）
A26: 3 | B26: =EDATE($C$17,A26-1) -> 46388 | C26: =G26+L26+Q26+V26+AA26+AF26+AK26+AP26+AU26+AZ26 -> 4822 | D26: =MAX(0,$C$16-C26) -> 1000 | E26: =ROUND(MAX(0,E25+F25-I25),2) -> 8094.96 | F26: =ROUND(E26*$E$5/12,2) -> 87.7 | G26: =MIN($F$5,E26+F26) -> 1072 | H26: =MAX(0,MIN(E26+F26-G26,$D26)) -> 1000 | I26: =G26+H26 -> 2072 | J26: =ROUND(MAX(0,J25+K25-N25),2) -> 19000 | K26: =ROUND(J26*$E$6/12,2) -> 0 | L26: =MIN($F$6,J26+K26) -> 500 | M26: =MAX(0,MIN(J26+K26-L26,$D26-(H26))) -> 0 | N26: =L26+M26 -> 500 | O26: =ROUND(MAX(0,O25+P25-S25),2) -> 23283 | P26: =ROUND(O26*$E$7/12,2) -> 465.66 | Q26: =MIN($F$7,O26+P26) -> 1350 | R26: =MAX(0,MIN(O26+P26-Q26,$D26-(H26+M26))) -> 0 | S26: =Q26+R26 -> 1350 | T26: =ROUND(MAX(0,T25+U25-X25),2) -> 35320.05 | U26: =ROUND(T26*$E$8/12,2) -> 529.8 | V26: =MIN($F$8,T26+U26) -> 1900 | W26: =MAX(0,MIN(T26+U26-V26,$D26-(H26+M26+R26))) -> 0 | X26: =V26+W26 -> 1900 | Y26: =ROUND(MAX(0,Y25+Z25-AC25),2) -> 0 | Z26: =ROUND(Y26*$E$9/12,2) -> 0 | AA26: =MIN($F$9,Y26+Z26) -> 0 | AB26: =MAX(0,MIN(Y26+Z26-AA26,$D26-(H26+M26+R26+W26))) -> 0 | AC26: =AA26+AB26 -> 0 | AD26: =ROUND(MAX(0,AD25+AE25-AH25),2) -> 0 | AE26: =ROUND(AD26*$E$10/12,2) -> 0 | AF26: =MIN($F$10,AD26+AE26) -> 0 | AG26: =MAX(0,MIN(AD26+AE26-AF26,$D26-(H26+M26+R26+W26+AB26))) -> 0 | AH26: =AF26+AG26 -> 0 | AI26: =ROUND(MAX(0,AI25+AJ25-AM25),2) -> 0 | AJ26: =ROUND(AI26*$E$11/12,2) -> 0 | AK26: =MIN($F$11,AI26+AJ26) -> 0 | AL26: =MAX(0,MIN(AI26+AJ26-AK26,$D26-(H26+M26+R26+W26+AB26+AG26))) -> 0 | AM26: =AK26+AL26 -> 0 | AN26: =ROUND(MAX(0,AN25+AO25-AR25),2) -> 0 | AO26: =ROUND(AN26*$E$12/12,2) -> 0 | AP26: =MIN($F$12,AN26+AO26) -> 0 | AQ26: =MAX(0,MIN(AN26+AO26-AP26,$D26-(H26+M26+R26+W26+AB26+AG26+AL26))) -> 0 | AR26: =AP26+AQ26 -> 0 | AS26: =ROUND(MAX(0,AS25+AT25-AW25),2) -> 0 | AT26: =ROUND(AS26*$E$13/12,2) -> 0 | AU26: =MIN($F$13,AS26+AT26) -> 0 | AV26: =MAX(0,MIN(AS26+AT26-AU26,$D26-(H26+M26+R26+W26+AB26+AG26+AL26+AQ26))) -> 0 | AW26: =AU26+AV26 -> 0 | AX26: =ROUND(MAX(0,AX25+AY25-BB25),2) -> 0 | AY26: =ROUND(AX26*$E$14/12,2) -> 0 | AZ26: =MIN($F$14,AX26+AY26) -> 0 | BA26: =MAX(0,MIN(AX26+AY26-AZ26,$D26-(H26+M26+R26+W26+AB26+AG26+AL26+AQ26+AV26))) -> 0 | BB26: =AZ26+BA26 -> 0 | BC26: =I26+N26+S26+X26+AC26+AH26+AM26+AR26+AW26+BB26 -> 5822 | BD26: =ROUND((E26+F26-I26)+(J26+K26-N26)+(O26+P26-S26)+(T26+U26-X26)+(Y26+Z26-AC26)+(AD26+AE26-AH26)+(AI26+AJ26-AM26)+(AN26+AO26-AR26)+(AS26+AT26-AW26)+(AX26+AY26-BB26),2) -> 80959.17 | BE26: =IF(H26>0.005,$C$5,IF(M26>0.005,$C$6,IF(R26>0.005,$C$7,IF(W26>0.005,$C$8,IF(AB26>0.005,$C$9,IF(AG26>0.005,$C$10,IF(AL26>0.005,$C$11,IF(AQ26>0.005,$C$12,IF(AV26>0.005,$C$13,IF(BA26>0.005,$C$14,"")))))))))) -> 信用卡B（分期）
A27: 4 | B27: =EDATE($C$17,A27-1) -> 46419 | C27: =G27+L27+Q27+V27+AA27+AF27+AK27+AP27+AU27+AZ27 -> 4822 | D27: =MAX(0,$C$16-C27) -> 1000 | E27: =ROUND(MAX(0,E26+F26-I26),2) -> 6110.66 | F27: =ROUND(E27*$E$5/12,2) -> 66.2 | G27: =MIN($F$5,E27+F27) -> 1072 | H27: =MAX(0,MIN(E27+F27-G27,$D27)) -> 1000 | I27: =G27+H27 -> 2072 | J27: =ROUND(MAX(0,J26+K26-N26),2) -> 18500 | K27: =ROUND(J27*$E$6/12,2) -> 0 | L27: =MIN($F$6,J27+K27) -> 500 | M27: =MAX(0,MIN(J27+K27-L27,$D27-(H27))) -> 0 | N27: =L27+M27 -> 500 | O27: =ROUND(MAX(0,O26+P26-S26),2) -> 22398.66 | P27: =ROUND(O27*$E$7/12,2) -> 447.97 | Q27: =MIN($F$7,O27+P27) -> 1350 | R27: =MAX(0,MIN(O27+P27-Q27,$D27-(H27+M27))) -> 0 | S27: =Q27+R27 -> 1350 | T27: =ROUND(MAX(0,T26+U26-X26),2) -> 33949.85 | U27: =ROUND(T27*$E$8/12,2) -> 509.25 | V27: =MIN($F$8,T27+U27) -> 1900 | W27: =MAX(0,MIN(T27+U27-V27,$D27-(H27+M27+R27))) -> 0 | X27: =V27+W27 -> 1900 | Y27: =ROUND(MAX(0,Y26+Z26-AC26),2) -> 0 | Z27: =ROUND(Y27*$E$9/12,2) -> 0 | AA27: =MIN($F$9,Y27+Z27) -> 0 | AB27: =MAX(0,MIN(Y27+Z27-AA27,$D27-(H27+M27+R27+W27))) -> 0 | AC27: =AA27+AB27 -> 0 | AD27: =ROUND(MAX(0,AD26+AE26-AH26),2) -> 0 | AE27: =ROUND(AD27*$E$10/12,2) -> 0 | AF27: =MIN($F$10,AD27+AE27) -> 0 | AG27: =MAX(0,MIN(AD27+AE27-AF27,$D27-(H27+M27+R27+W27+AB27))) -> 0 | AH27: =AF27+AG27 -> 0 | AI27: =ROUND(MAX(0,AI26+AJ26-AM26),2) -> 0 | AJ27: =ROUND(AI27*$E$11/12,2) -> 0 | AK27: =MIN($F$11,AI27+AJ27) -> 0 | AL27: =MAX(0,MIN(AI27+AJ27-AK27,$D27-(H27+M27+R27+W27+AB27+AG27))) -> 0 | AM27: =AK27+AL27 -> 0 | AN27: =ROUND(MAX(0,AN26+AO26-AR26),2) -> 0 | AO27: =ROUND(AN27*$E$12/12,2) -> 0 | AP27: =MIN($F$12,AN27+AO27) -> 0 | AQ27: =MAX(0,MIN(AN27+AO27-AP27,$D27-(H27+M27+R27+W27+AB27+AG27+AL27))) -> 0 | AR27: =AP27+AQ27 -> 0 | AS27: =ROUND(MAX(0,AS26+AT26-AW26),2) -> 0 | AT27: =ROUND(AS27*$E$13/12,2) -> 0 | AU27: =MIN($F$13,AS27+AT27) -> 0 | AV27: =MAX(0,MIN(AS27+AT27-AU27,$D27-(H27+M27+R27+W27+AB27+AG27+AL27+AQ27))) -> 0 | AW27: =AU27+AV27 -> 0 | AX27: =ROUND(MAX(0,AX26+AY26-BB26),2) -> 0 | AY27: =ROUND(AX27*$E$14/12,2) -> 0 | AZ27: =MIN($F$14,AX27+AY27) -> 0 | BA27: =MAX(0,MIN(AX27+AY27-AZ27,$D27-(H27+M27+R27+W27+AB27+AG27+AL27+AQ27+AV27))) -> 0 | BB27: =AZ27+BA27 -> 0 | BC27: =I27+N27+S27+X27+AC27+AH27+AM27+AR27+AW27+BB27 -> 5822 | BD27: =ROUND((E27+F27-I27)+(J27+K27-N27)+(O27+P27-S27)+(T27+U27-X27)+(Y27+Z27-AC27)+(AD27+AE27-AH27)+(AI27+AJ27-AM27)+(AN27+AO27-AR27)+(AS27+AT27-AW27)+(AX27+AY27-BB27),2) -> 76160.59 | BE27: =IF(H27>0.005,$C$5,IF(M27>0.005,$C$6,IF(R27>0.005,$C$7,IF(W27>0.005,$C$8,IF(AB27>0.005,$C$9,IF(AG27>0.005,$C$10,IF(AL27>0.005,$C$11,IF(AQ27>0.005,$C$12,IF(AV27>0.005,$C$13,IF(BA27>0.005,$C$14,"")))))))))) -> 信用卡B（分期）
A28: 5 | B28: =EDATE($C$17,A28-1) -> 46447 | C28: =G28+L28+Q28+V28+AA28+AF28+AK28+AP28+AU28+AZ28 -> 4822 | D28: =MAX(0,$C$16-C28) -> 1000 | E28: =ROUND(MAX(0,E27+F27-I27),2) -> 4104.86 | F28: =ROUND(E28*$E$5/12,2) -> 44.47 | G28: =MIN($F$5,E28+F28) -> 1072 | H28: =MAX(0,MIN(E28+F28-G28,$D28)) -> 1000 | I28: =G28+H28 -> 2072 | J28: =ROUND(MAX(0,J27+K27-N27),2) -> 18000 | K28: =ROUND(J28*$E$6/12,2) -> 0 | L28: =MIN($F$6,J28+K28) -> 500 | M28: =MAX(0,MIN(J28+K28-L28,$D28-(H28))) -> 0 | N28: =L28+M28 -> 500 | O28: =ROUND(MAX(0,O27+P27-S27),2) -> 21496.63 | P28: =ROUND(O28*$E$7/12,2) -> 429.93 | Q28: =MIN($F$7,O28+P28) -> 1350 | R28: =MAX(0,MIN(O28+P28-Q28,$D28-(H28+M28))) -> 0 | S28: =Q28+R28 -> 1350 | T28: =ROUND(MAX(0,T27+U27-X27),2) -> 32559.1 | U28: =ROUND(T28*$E$8/12,2) -> 488.39 | V28: =MIN($F$8,T28+U28) -> 1900 | W28: =MAX(0,MIN(T28+U28-V28,$D28-(H28+M28+R28))) -> 0 | X28: =V28+W28 -> 1900 | Y28: =ROUND(MAX(0,Y27+Z27-AC27),2) -> 0 | Z28: =ROUND(Y28*$E$9/12,2) -> 0 | AA28: =MIN($F$9,Y28+Z28) -> 0 | AB28: =MAX(0,MIN(Y28+Z28-AA28,$D28-(H28+M28+R28+W28))) -> 0 | AC28: =AA28+AB28 -> 0 | AD28: =ROUND(MAX(0,AD27+AE27-AH27),2) -> 0 | AE28: =ROUND(AD28*$E$10/12,2) -> 0 | AF28: =MIN($F$10,AD28+AE28) -> 0 | AG28: =MAX(0,MIN(AD28+AE28-AF28,$D28-(H28+M28+R28+W28+AB28))) -> 0 | AH28: =AF28+AG28 -> 0 | AI28: =ROUND(MAX(0,AI27+AJ27-AM27),2) -> 0 | AJ28: =ROUND(AI28*$E$11/12,2) -> 0 | AK28: =MIN($F$11,AI28+AJ28) -> 0 | AL28: =MAX(0,MIN(AI28+AJ28-AK28,$D28-(H28+M28+R28+W28+AB28+AG28))) -> 0 | AM28: =AK28+AL28 -> 0 | AN28: =ROUND(MAX(0,AN27+AO27-AR27),2) -> 0 | AO28: =ROUND(AN28*$E$12/12,2) -> 0 | AP28: =MIN($F$12,AN28+AO28) -> 0 | AQ28: =MAX(0,MIN(AN28+AO28-AP28,$D28-(H28+M28+R28+W28+AB28+AG28+AL28))) -> 0 | AR28: =AP28+AQ28 -> 0 | AS28: =ROUND(MAX(0,AS27+AT27-AW27),2) -> 0 | AT28: =ROUND(AS28*$E$13/12,2) -> 0 | AU28: =MIN($F$13,AS28+AT28) -> 0 | AV28: =MAX(0,MIN(AS28+AT28-AU28,$D28-(H28+M28+R28+W28+AB28+AG28+AL28+AQ28))) -> 0 | AW28: =AU28+AV28 -> 0 | AX28: =ROUND(MAX(0,AX27+AY27-BB27),2) -> 0 | AY28: =ROUND(AX28*$E$14/12,2) -> 0 | AZ28: =MIN($F$14,AX28+AY28) -> 0 | BA28: =MAX(0,MIN(AX28+AY28-AZ28,$D28-(H28+M28+R28+W28+AB28+AG28+AL28+AQ28+AV28))) -> 0 | BB28: =AZ28+BA28 -> 0 | BC28: =I28+N28+S28+X28+AC28+AH28+AM28+AR28+AW28+BB28 -> 5822 | BD28: =ROUND((E28+F28-I28)+(J28+K28-N28)+(O28+P28-S28)+(T28+U28-X28)+(Y28+Z28-AC28)+(AD28+AE28-AH28)+(AI28+AJ28-AM28)+(AN28+AO28-AR28)+(AS28+AT28-AW28)+(AX28+AY28-BB28),2) -> 71301.38 | BE28: =IF(H28>0.005,$C$5,IF(M28>0.005,$C$6,IF(R28>0.005,$C$7,IF(W28>0.005,$C$8,IF(AB28>0.005,$C$9,IF(AG28>0.005,$C$10,IF(AL28>0.005,$C$11,IF(AQ28>0.005,$C$12,IF(AV28>0.005,$C$13,IF(BA28>0.005,$C$14,"")))))))))) -> 信用卡B（分期）
A29: 6 | B29: =EDATE($C$17,A29-1) -> 46478 | C29: =G29+L29+Q29+V29+AA29+AF29+AK29+AP29+AU29+AZ29 -> 4822 | D29: =MAX(0,$C$16-C29) -> 1000 | E29: =ROUND(MAX(0,E28+F28-I28),2) -> 2077.33 | F29: =ROUND(E29*$E$5/12,2) -> 22.5 | G29: =MIN($F$5,E29+F29) -> 1072 | H29: =MAX(0,MIN(E29+F29-G29,$D29)) -> 1000 | I29: =G29+H29 -> 2072 | J29: =ROUND(MAX(0,J28+K28-N28),2) -> 17500 | K29: =ROUND(J29*$E$6/12,2) -> 0 | L29: =MIN($F$6,J29+K29) -> 500 | M29: =MAX(0,MIN(J29+K29-L29,$D29-(H29))) -> 0 | N29: =L29+M29 -> 500 | O29: =ROUND(MAX(0,O28+P28-S28),2) -> 20576.56 | P29: =ROUND(O29*$E$7/12,2) -> 411.53 | Q29: =MIN($F$7,O29+P29) -> 1350 | R29: =MAX(0,MIN(O29+P29-Q29,$D29-(H29+M29))) -> 0 | S29: =Q29+R29 -> 1350 | T29: =ROUND(MAX(0,T28+U28-X28),2) -> 31147.49 | U29: =ROUND(T29*$E$8/12,2) -> 467.21 | V29: =MIN($F$8,T29+U29) -> 1900 | W29: =MAX(0,MIN(T29+U29-V29,$D29-(H29+M29+R29))) -> 0 | X29: =V29+W29 -> 1900 | Y29: =ROUND(MAX(0,Y28+Z28-AC28),2) -> 0 | Z29: =ROUND(Y29*$E$9/12,2) -> 0 | AA29: =MIN($F$9,Y29+Z29) -> 0 | AB29: =MAX(0,MIN(Y29+Z29-AA29,$D29-(H29+M29+R29+W29))) -> 0 | AC29: =AA29+AB29 -> 0 | AD29: =ROUND(MAX(0,AD28+AE28-AH28),2) -> 0 | AE29: =ROUND(AD29*$E$10/12,2) -> 0 | AF29: =MIN($F$10,AD29+AE29) -> 0 | AG29: =MAX(0,MIN(AD29+AE29-AF29,$D29-(H29+M29+R29+W29+AB29))) -> 0 | AH29: =AF29+AG29 -> 0 | AI29: =ROUND(MAX(0,AI28+AJ28-AM28),2) -> 0 | AJ29: =ROUND(AI29*$E$11/12,2) -> 0 | AK29: =MIN($F$11,AI29+AJ29) -> 0 | AL29: =MAX(0,MIN(AI29+AJ29-AK29,$D29-(H29+M29+R29+W29+AB29+AG29))) -> 0 | AM29: =AK29+AL29 -> 0 | AN29: =ROUND(MAX(0,AN28+AO28-AR28),2) -> 0 | AO29: =ROUND(AN29*$E$12/12,2) -> 0 | AP29: =MIN($F$12,AN29+AO29) -> 0 | AQ29: =MAX(0,MIN(AN29+AO29-AP29,$D29-(H29+M29+R29+W29+AB29+AG29+AL29))) -> 0 | AR29: =AP29+AQ29 -> 0 | AS29: =ROUND(MAX(0,AS28+AT28-AW28),2) -> 0 | AT29: =ROUND(AS29*$E$13/12,2) -> 0 | AU29: =MIN($F$13,AS29+AT29) -> 0 | AV29: =MAX(0,MIN(AS29+AT29-AU29,$D29-(H29+M29+R29+W29+AB29+AG29+AL29+AQ29))) -> 0 | AW29: =AU29+AV29 -> 0 | AX29: =ROUND(MAX(0,AX28+AY28-BB28),2) -> 0 | AY29: =ROUND(AX29*$E$14/12,2) -> 0 | AZ29: =MIN($F$14,AX29+AY29) -> 0 | BA29: =MAX(0,MIN(AX29+AY29-AZ29,$D29-(H29+M29+R29+W29+AB29+AG29+AL29+AQ29+AV29))) -> 0 | BB29: =AZ29+BA29 -> 0 | BC29: =I29+N29+S29+X29+AC29+AH29+AM29+AR29+AW29+BB29 -> 5822 | BD29: =ROUND((E29+F29-I29)+(J29+K29-N29)+(O29+P29-S29)+(T29+U29-X29)+(Y29+Z29-AC29)+(AD29+AE29-AH29)+(AI29+AJ29-AM29)+(AN29+AO29-AR29)+(AS29+AT29-AW29)+(AX29+AY29-BB29),2) -> 66380.62 | BE29: =IF(H29>0.005,$C$5,IF(M29>0.005,$C$6,IF(R29>0.005,$C$7,IF(W29>0.005,$C$8,IF(AB29>0.005,$C$9,IF(AG29>0.005,$C$10,IF(AL29>0.005,$C$11,IF(AQ29>0.005,$C$12,IF(AV29>0.005,$C$13,IF(BA29>0.005,$C$14,"")))))))))) -> 信用卡B（分期）
A30: 7 | B30: =EDATE($C$17,A30-1) -> 46508 | C30: =G30+L30+Q30+V30+AA30+AF30+AK30+AP30+AU30+AZ30 -> 3778.13 | D30: =MAX(0,$C$16-C30) -> 2043.87 | E30: =ROUND(MAX(0,E29+F29-I29),2) -> 27.83 | F30: =ROUND(E30*$E$5/12,2) -> 0.3 | G30: =MIN($F$5,E30+F30) -> 28.13 | H30: =MAX(0,MIN(E30+F30-G30,$D30)) -> 0 | I30: =G30+H30 -> 28.13 | J30: =ROUND(MAX(0,J29+K29-N29),2) -> 17000 | K30: =ROUND(J30*$E$6/12,2) -> 0 | L30: =MIN($F$6,J30+K30) -> 500 | M30: =MAX(0,MIN(J30+K30-L30,$D30-(H30))) -> 2043.87 | N30: =L30+M30 -> 2543.87 | O30: =ROUND(MAX(0,O29+P29-S29),2) -> 19638.09 | P30: =ROUND(O30*$E$7/12,2) -> 392.76 | Q30: =MIN($F$7,O30+P30) -> 1350 | R30: =MAX(0,MIN(O30+P30-Q30,$D30-(H30+M30))) -> 0 | S30: =Q30+R30 -> 1350 | T30: =ROUND(MAX(0,T29+U29-X29),2) -> 29714.7 | U30: =ROUND(T30*$E$8/12,2) -> 445.72 | V30: =MIN($F$8,T30+U30) -> 1900 | W30: =MAX(0,MIN(T30+U30-V30,$D30-(H30+M30+R30))) -> 0 | X30: =V30+W30 -> 1900 | Y30: =ROUND(MAX(0,Y29+Z29-AC29),2) -> 0 | Z30: =ROUND(Y30*$E$9/12,2) -> 0 | AA30: =MIN($F$9,Y30+Z30) -> 0 | AB30: =MAX(0,MIN(Y30+Z30-AA30,$D30-(H30+M30+R30+W30))) -> 0 | AC30: =AA30+AB30 -> 0 | AD30: =ROUND(MAX(0,AD29+AE29-AH29),2) -> 0 | AE30: =ROUND(AD30*$E$10/12,2) -> 0 | AF30: =MIN($F$10,AD30+AE30) -> 0 | AG30: =MAX(0,MIN(AD30+AE30-AF30,$D30-(H30+M30+R30+W30+AB30))) -> 0 | AH30: =AF30+AG30 -> 0 | AI30: =ROUND(MAX(0,AI29+AJ29-AM29),2) -> 0 | AJ30: =ROUND(AI30*$E$11/12,2) -> 0 | AK30: =MIN($F$11,AI30+AJ30) -> 0 | AL30: =MAX(0,MIN(AI30+AJ30-AK30,$D30-(H30+M30+R30+W30+AB30+AG30))) -> 0 | AM30: =AK30+AL30 -> 0 | AN30: =ROUND(MAX(0,AN29+AO29-AR29),2) -> 0 | AO30: =ROUND(AN30*$E$12/12,2) -> 0 | AP30: =MIN($F$12,AN30+AO30) -> 0 | AQ30: =MAX(0,MIN(AN30+AO30-AP30,$D30-(H30+M30+R30+W30+AB30+AG30+AL30))) -> 0 | AR30: =AP30+AQ30 -> 0 | AS30: =ROUND(MAX(0,AS29+AT29-AW29),2) -> 0 | AT30: =ROUND(AS30*$E$13/12,2) -> 0 | AU30: =MIN($F$13,AS30+AT30) -> 0 | AV30: =MAX(0,MIN(AS30+AT30-AU30,$D30-(H30+M30+R30+W30+AB30+AG30+AL30+AQ30))) -> 0 | AW30: =AU30+AV30 -> 0 | AX30: =ROUND(MAX(0,AX29+AY29-BB29),2) -> 0 | AY30: =ROUND(AX30*$E$14/12,2) -> 0 | AZ30: =MIN($F$14,AX30+AY30) -> 0 | BA30: =MAX(0,MIN(AX30+AY30-AZ30,$D30-(H30+M30+R30+W30+AB30+AG30+AL30+AQ30+AV30))) -> 0 | BB30: =AZ30+BA30 -> 0 | BC30: =I30+N30+S30+X30+AC30+AH30+AM30+AR30+AW30+BB30 -> 5822 | BD30: =ROUND((E30+F30-I30)+(J30+K30-N30)+(O30+P30-S30)+(T30+U30-X30)+(Y30+Z30-AC30)+(AD30+AE30-AH30)+(AI30+AJ30-AM30)+(AN30+AO30-AR30)+(AS30+AT30-AW30)+(AX30+AY30-BB30),2) -> 61397.4 | BE30: =IF(H30>0.005,$C$5,IF(M30>0.005,$C$6,IF(R30>0.005,$C$7,IF(W30>0.005,$C$8,IF(AB30>0.005,$C$9,IF(AG30>0.005,$C$10,IF(AL30>0.005,$C$11,IF(AQ30>0.005,$C$12,IF(AV30>0.005,$C$13,IF(BA30>0.005,$C$14,"")))))))))) -> 亲友借款（老王）
A31: 8 | B31: =EDATE($C$17,A31-1) -> 46539 | C31: =G31+L31+Q31+V31+AA31+AF31+AK31+AP31+AU31+AZ31 -> 3750 | D31: =MAX(0,$C$16-C31) -> 2072 | E31: =ROUND(MAX(0,E30+F30-I30),2) -> 0 | F31: =ROUND(E31*$E$5/12,2) -> 0 | G31: =MIN($F$5,E31+F31) -> 0 | H31: =MAX(0,MIN(E31+F31-G31,$D31)) -> 0 | I31: =G31+H31 -> 0 | J31: =ROUND(MAX(0,J30+K30-N30),2) -> 14456.13 | K31: =ROUND(J31*$E$6/12,2) -> 0 | L31: =MIN($F$6,J31+K31) -> 500 | M31: =MAX(0,MIN(J31+K31-L31,$D31-(H31))) -> 2072 | N31: =L31+M31 -> 2572 | O31: =ROUND(MAX(0,O30+P30-S30),2) -> 18680.85 | P31: =ROUND(O31*$E$7/12,2) -> 373.62 | Q31: =MIN($F$7,O31+P31) -> 1350 | R31: =MAX(0,MIN(O31+P31-Q31,$D31-(H31+M31))) -> 0 | S31: =Q31+R31 -> 1350 | T31: =ROUND(MAX(0,T30+U30-X30),2) -> 28260.42 | U31: =ROUND(T31*$E$8/12,2) -> 423.91 | V31: =MIN($F$8,T31+U31) -> 1900 | W31: =MAX(0,MIN(T31+U31-V31,$D31-(H31+M31+R31))) -> 0 | X31: =V31+W31 -> 1900 | Y31: =ROUND(MAX(0,Y30+Z30-AC30),2) -> 0 | Z31: =ROUND(Y31*$E$9/12,2) -> 0 | AA31: =MIN($F$9,Y31+Z31) -> 0 | AB31: =MAX(0,MIN(Y31+Z31-AA31,$D31-(H31+M31+R31+W31))) -> 0 | AC31: =AA31+AB31 -> 0 | AD31: =ROUND(MAX(0,AD30+AE30-AH30),2) -> 0 | AE31: =ROUND(AD31*$E$10/12,2) -> 0 | AF31: =MIN($F$10,AD31+AE31) -> 0 | AG31: =MAX(0,MIN(AD31+AE31-AF31,$D31-(H31+M31+R31+W31+AB31))) -> 0 | AH31: =AF31+AG31 -> 0 | AI31: =ROUND(MAX(0,AI30+AJ30-AM30),2) -> 0 | AJ31: =ROUND(AI31*$E$11/12,2) -> 0 | AK31: =MIN($F$11,AI31+AJ31) -> 0 | AL31: =MAX(0,MIN(AI31+AJ31-AK31,$D31-(H31+M31+R31+W31+AB31+AG31))) -> 0 | AM31: =AK31+AL31 -> 0 | AN31: =ROUND(MAX(0,AN30+AO30-AR30),2) -> 0 | AO31: =ROUND(AN31*$E$12/12,2) -> 0 | AP31: =MIN($F$12,AN31+AO31) -> 0 | AQ31: =MAX(0,MIN(AN31+AO31-AP31,$D31-(H31+M31+R31+W31+AB31+AG31+AL31))) -> 0 | AR31: =AP31+AQ31 -> 0 | AS31: =ROUND(MAX(0,AS30+AT30-AW30),2) -> 0 | AT31: =ROUND(AS31*$E$13/12,2) -> 0 | AU31: =MIN($F$13,AS31+AT31) -> 0 | AV31: =MAX(0,MIN(AS31+AT31-AU31,$D31-(H31+M31+R31+W31+AB31+AG31+AL31+AQ31))) -> 0 | AW31: =AU31+AV31 -> 0 | AX31: =ROUND(MAX(0,AX30+AY30-BB30),2) -> 0 | AY31: =ROUND(AX31*$E$14/12,2) -> 0 | AZ31: =MIN($F$14,AX31+AY31) -> 0 | BA31: =MAX(0,MIN(AX31+AY31-AZ31,$D31-(H31+M31+R31+W31+AB31+AG31+AL31+AQ31+AV31))) -> 0 | BB31: =AZ31+BA31 -> 0 | BC31: =I31+N31+S31+X31+AC31+AH31+AM31+AR31+AW31+BB31 -> 5822 | BD31: =ROUND((E31+F31-I31)+(J31+K31-N31)+(O31+P31-S31)+(T31+U31-X31)+(Y31+Z31-AC31)+(AD31+AE31-AH31)+(AI31+AJ31-AM31)+(AN31+AO31-AR31)+(AS31+AT31-AW31)+(AX31+AY31-BB31),2) -> 56372.93 | BE31: =IF(H31>0.005,$C$5,IF(M31>0.005,$C$6,IF(R31>0.005,$C$7,IF(W31>0.005,$C$8,IF(AB31>0.005,$C$9,IF(AG31>0.005,$C$10,IF(AL31>0.005,$C$11,IF(AQ31>0.005,$C$12,IF(AV31>0.005,$C$13,IF(BA31>0.005,$C$14,"")))))))))) -> 亲友借款（老王）
A32: 9 | B32: =EDATE($C$17,A32-1) -> 46569 | C32: =G32+L32+Q32+V32+AA32+AF32+AK32+AP32+AU32+AZ32 -> 3750 | D32: =MAX(0,$C$16-C32) -> 2072 | E32: =ROUND(MAX(0,E31+F31-I31),2) -> 0 | F32: =ROUND(E32*$E$5/12,2) -> 0 | G32: =MIN($F$5,E32+F32) -> 0 | H32: =MAX(0,MIN(E32+F32-G32,$D32)) -> 0 | I32: =G32+H32 -> 0 | J32: =ROUND(MAX(0,J31+K31-N31),2) -> 11884.13 | K32: =ROUND(J32*$E$6/12,2) -> 0 | L32: =MIN($F$6,J32+K32) -> 500 | M32: =MAX(0,MIN(J32+K32-L32,$D32-(H32))) -> 2072 | N32: =L32+M32 -> 2572 | O32: =ROUND(MAX(0,O31+P31-S31),2) -> 17704.47 | P32: =ROUND(O32*$E$7/12,2) -> 354.09 | Q32: =MIN($F$7,O32+P32) -> 1350 | R32: =MAX(0,MIN(O32+P32-Q32,$D32-(H32+M32))) -> 0 | S32: =Q32+R32 -> 1350 | T32: =ROUND(MAX(0,T31+U31-X31),2) -> 26784.33 | U32: =ROUND(T32*$E$8/12,2) -> 401.76 | V32: =MIN($F$8,T32+U32) -> 1900 | W32: =MAX(0,MIN(T32+U32-V32,$D32-(H32+M32+R32))) -> 0 | X32: =V32+W32 -> 1900 | Y32: =ROUND(MAX(0,Y31+Z31-AC31),2) -> 0 | Z32: =ROUND(Y32*$E$9/12,2) -> 0 | AA32: =MIN($F$9,Y32+Z32) -> 0 | AB32: =MAX(0,MIN(Y32+Z32-AA32,$D32-(H32+M32+R32+W32))) -> 0 | AC32: =AA32+AB32 -> 0 | AD32: =ROUND(MAX(0,AD31+AE31-AH31),2) -> 0 | AE32: =ROUND(AD32*$E$10/12,2) -> 0 | AF32: =MIN($F$10,AD32+AE32) -> 0 | AG32: =MAX(0,MIN(AD32+AE32-AF32,$D32-(H32+M32+R32+W32+AB32))) -> 0 | AH32: =AF32+AG32 -> 0 | AI32: =ROUND(MAX(0,AI31+AJ31-AM31),2) -> 0 | AJ32: =ROUND(AI32*$E$11/12,2) -> 0 | AK32: =MIN($F$11,AI32+AJ32) -> 0 | AL32: =MAX(0,MIN(AI32+AJ32-AK32,$D32-(H32+M32+R32+W32+AB32+AG32))) -> 0 | AM32: =AK32+AL32 -> 0 | AN32: =ROUND(MAX(0,AN31+AO31-AR31),2) -> 0 | AO32: =ROUND(AN32*$E$12/12,2) -> 0 | AP32: =MIN($F$12,AN32+AO32) -> 0 | AQ32: =MAX(0,MIN(AN32+AO32-AP32,$D32-(H32+M32+R32+W32+AB32+AG32+AL32))) -> 0 | AR32: =AP32+AQ32 -> 0 | AS32: =ROUND(MAX(0,AS31+AT31-AW31),2) -> 0 | AT32: =ROUND(AS32*$E$13/12,2) -> 0 | AU32: =MIN($F$13,AS32+AT32) -> 0 | AV32: =MAX(0,MIN(AS32+AT32-AU32,$D32-(H32+M32+R32+W32+AB32+AG32+AL32+AQ32))) -> 0 | AW32: =AU32+AV32 -> 0 | AX32: =ROUND(MAX(0,AX31+AY31-BB31),2) -> 0 | AY32: =ROUND(AX32*$E$14/12,2) -> 0 | AZ32: =MIN($F$14,AX32+AY32) -> 0 | BA32: =MAX(0,MIN(AX32+AY32-AZ32,$D32-(H32+M32+R32+W32+AB32+AG32+AL32+AQ32+AV32))) -> 0 | BB32: =AZ32+BA32 -> 0 | BC32: =I32+N32+S32+X32+AC32+AH32+AM32+AR32+AW32+BB32 -> 5822 | BD32: =ROUND((E32+F32-I32)+(J32+K32-N32)+(O32+P32-S32)+(T32+U32-X32)+(Y32+Z32-AC32)+(AD32+AE32-AH32)+(AI32+AJ32-AM32)+(AN32+AO32-AR32)+(AS32+AT32-AW32)+(AX32+AY32-BB32),2) -> 51306.78 | BE32: =IF(H32>0.005,$C$5,IF(M32>0.005,$C$6,IF(R32>0.005,$C$7,IF(W32>0.005,$C$8,IF(AB32>0.005,$C$9,IF(AG32>0.005,$C$10,IF(AL32>0.005,$C$11,IF(AQ32>0.005,$C$12,IF(AV32>0.005,$C$13,IF(BA32>0.005,$C$14,"")))))))))) -> 亲友借款（老王）
A33: 10 | B33: =EDATE($C$17,A33-1) -> 46600 | C33: =G33+L33+Q33+V33+AA33+AF33+AK33+AP33+AU33+AZ33 -> 3750 | D33: =MAX(0,$C$16-C33) -> 2072 | E33: =ROUND(MAX(0,E32+F32-I32),2) -> 0 | F33: =ROUND(E33*$E$5/12,2) -> 0 | G33: =MIN($F$5,E33+F33) -> 0 | H33: =MAX(0,MIN(E33+F33-G33,$D33)) -> 0 | I33: =G33+H33 -> 0 | J33: =ROUND(MAX(0,J32+K32-N32),2) -> 9312.13 | K33: =ROUND(J33*$E$6/12,2) -> 0 | L33: =MIN($F$6,J33+K33) -> 500 | M33: =MAX(0,MIN(J33+K33-L33,$D33-(H33))) -> 2072 | N33: =L33+M33 -> 2572 | O33: =ROUND(MAX(0,O32+P32-S32),2) -> 16708.56 | P33: =ROUND(O33*$E$7/12,2) -> 334.17 | Q33: =MIN($F$7,O33+P33) -> 1350 | R33: =MAX(0,MIN(O33+P33-Q33,$D33-(H33+M33))) -> 0 | S33: =Q33+R33 -> 1350 | T33: =ROUND(MAX(0,T32+U32-X32),2) -> 25286.09 | U33: =ROUND(T33*$E$8/12,2) -> 379.29 | V33: =MIN($F$8,T33+U33) -> 1900 | W33: =MAX(0,MIN(T33+U33-V33,$D33-(H33+M33+R33))) -> 0 | X33: =V33+W33 -> 1900 | Y33: =ROUND(MAX(0,Y32+Z32-AC32),2) -> 0 | Z33: =ROUND(Y33*$E$9/12,2) -> 0 | AA33: =MIN($F$9,Y33+Z33) -> 0 | AB33: =MAX(0,MIN(Y33+Z33-AA33,$D33-(H33+M33+R33+W33))) -> 0 | AC33: =AA33+AB33 -> 0 | AD33: =ROUND(MAX(0,AD32+AE32-AH32),2) -> 0 | AE33: =ROUND(AD33*$E$10/12,2) -> 0 | AF33: =MIN($F$10,AD33+AE33) -> 0 | AG33: =MAX(0,MIN(AD33+AE33-AF33,$D33-(H33+M33+R33+W33+AB33))) -> 0 | AH33: =AF33+AG33 -> 0 | AI33: =ROUND(MAX(0,AI32+AJ32-AM32),2) -> 0 | AJ33: =ROUND(AI33*$E$11/12,2) -> 0 | AK33: =MIN($F$11,AI33+AJ33) -> 0 | AL33: =MAX(0,MIN(AI33+AJ33-AK33,$D33-(H33+M33+R33+W33+AB33+AG33))) -> 0 | AM33: =AK33+AL33 -> 0 | AN33: =ROUND(MAX(0,AN32+AO32-AR32),2) -> 0 | AO33: =ROUND(AN33*$E$12/12,2) -> 0 | AP33: =MIN($F$12,AN33+AO33) -> 0 | AQ33: =MAX(0,MIN(AN33+AO33-AP33,$D33-(H33+M33+R33+W33+AB33+AG33+AL33))) -> 0 | AR33: =AP33+AQ33 -> 0 | AS33: =ROUND(MAX(0,AS32+AT32-AW32),2) -> 0 | AT33: =ROUND(AS33*$E$13/12,2) -> 0 | AU33: =MIN($F$13,AS33+AT33) -> 0 | AV33: =MAX(0,MIN(AS33+AT33-AU33,$D33-(H33+M33+R33+W33+AB33+AG33+AL33+AQ33))) -> 0 | AW33: =AU33+AV33 -> 0 | AX33: =ROUND(MAX(0,AX32+AY32-BB32),2) -> 0 | AY33: =ROUND(AX33*$E$14/12,2) -> 0 | AZ33: =MIN($F$14,AX33+AY33) -> 0 | BA33: =MAX(0,MIN(AX33+AY33-AZ33,$D33-(H33+M33+R33+W33+AB33+AG33+AL33+AQ33+AV33))) -> 0 | BB33: =AZ33+BA33 -> 0 | BC33: =I33+N33+S33+X33+AC33+AH33+AM33+AR33+AW33+BB33 -> 5822 | BD33: =ROUND((E33+F33-I33)+(J33+K33-N33)+(O33+P33-S33)+(T33+U33-X33)+(Y33+Z33-AC33)+(AD33+AE33-AH33)+(AI33+AJ33-AM33)+(AN33+AO33-AR33)+(AS33+AT33-AW33)+(AX33+AY33-BB33),2) -> 46198.24 | BE33: =IF(H33>0.005,$C$5,IF(M33>0.005,$C$6,IF(R33>0.005,$C$7,IF(W33>0.005,$C$8,IF(AB33>0.005,$C$9,IF(AG33>0.005,$C$10,IF(AL33>0.005,$C$11,IF(AQ33>0.005,$C$12,IF(AV33>0.005,$C$13,IF(BA33>0.005,$C$14,"")))))))))) -> 亲友借款（老王）
A34: 11 | B34: =EDATE($C$17,A34-1) -> 46631 | C34: =G34+L34+Q34+V34+AA34+AF34+AK34+AP34+AU34+AZ34 -> 3750 | D34: =MAX(0,$C$16-C34) -> 2072 | E34: =ROUND(MAX(0,E33+F33-I33),2) -> 0 | F34: =ROUND(E34*$E$5/12,2) -> 0 | G34: =MIN($F$5,E34+F34) -> 0 | H34: =MAX(0,MIN(E34+F34-G34,$D34)) -> 0 | I34: =G34+H34 -> 0 | J34: =ROUND(MAX(0,J33+K33-N33),2) -> 6740.13 | K34: =ROUND(J34*$E$6/12,2) -> 0 | L34: =MIN($F$6,J34+K34) -> 500 | M34: =MAX(0,MIN(J34+K34-L34,$D34-(H34))) -> 2072 | N34: =L34+M34 -> 2572 | O34: =ROUND(MAX(0,O33+P33-S33),2) -> 15692.73 | P34: =ROUND(O34*$E$7/12,2) -> 313.85 | Q34: =MIN($F$7,O34+P34) -> 1350 | R34: =MAX(0,MIN(O34+P34-Q34,$D34-(H34+M34))) -> 0 | S34: =Q34+R34 -> 1350 | T34: =ROUND(MAX(0,T33+U33-X33),2) -> 23765.38 | U34: =ROUND(T34*$E$8/12,2) -> 356.48 | V34: =MIN($F$8,T34+U34) -> 1900 | W34: =MAX(0,MIN(T34+U34-V34,$D34-(H34+M34+R34))) -> 0 | X34: =V34+W34 -> 1900 | Y34: =ROUND(MAX(0,Y33+Z33-AC33),2) -> 0 | Z34: =ROUND(Y34*$E$9/12,2) -> 0 | AA34: =MIN($F$9,Y34+Z34) -> 0 | AB34: =MAX(0,MIN(Y34+Z34-AA34,$D34-(H34+M34+R34+W34))) -> 0 | AC34: =AA34+AB34 -> 0 | AD34: =ROUND(MAX(0,AD33+AE33-AH33),2) -> 0 | AE34: =ROUND(AD34*$E$10/12,2) -> 0 | AF34: =MIN($F$10,AD34+AE34) -> 0 | AG34: =MAX(0,MIN(AD34+AE34-AF34,$D34-(H34+M34+R34+W34+AB34))) -> 0 | AH34: =AF34+AG34 -> 0 | AI34: =ROUND(MAX(0,AI33+AJ33-AM33),2) -> 0 | AJ34: =ROUND(AI34*$E$11/12,2) -> 0 | AK34: =MIN($F$11,AI34+AJ34) -> 0 | AL34: =MAX(0,MIN(AI34+AJ34-AK34,$D34-(H34+M34+R34+W34+AB34+AG34))) -> 0 | AM34: =AK34+AL34 -> 0 | AN34: =ROUND(MAX(0,AN33+AO33-AR33),2) -> 0 | AO34: =ROUND(AN34*$E$12/12,2) -> 0 | AP34: =MIN($F$12,AN34+AO34) -> 0 | AQ34: =MAX(0,MIN(AN34+AO34-AP34,$D34-(H34+M34+R34+W34+AB34+AG34+AL34))) -> 0 | AR34: =AP34+AQ34 -> 0 | AS34: =ROUND(MAX(0,AS33+AT33-AW33),2) -> 0 | AT34: =ROUND(AS34*$E$13/12,2) -> 0 | AU34: =MIN($F$13,AS34+AT34) -> 0 | AV34: =MAX(0,MIN(AS34+AT34-AU34,$D34-(H34+M34+R34+W34+AB34+AG34+AL34+AQ34))) -> 0 | AW34: =AU34+AV34 -> 0 | AX34: =ROUND(MAX(0,AX33+AY33-BB33),2) -> 0 | AY34: =ROUND(AX34*$E$14/12,2) -> 0 | AZ34: =MIN($F$14,AX34+AY34) -> 0 | BA34: =MAX(0,MIN(AX34+AY34-AZ34,$D34-(H34+M34+R34+W34+AB34+AG34+AL34+AQ34+AV34))) -> 0 | BB34: =AZ34+BA34 -> 0 | BC34: =I34+N34+S34+X34+AC34+AH34+AM34+AR34+AW34+BB34 -> 5822 | BD34: =ROUND((E34+F34-I34)+(J34+K34-N34)+(O34+P34-S34)+(T34+U34-X34)+(Y34+Z34-AC34)+(AD34+AE34-AH34)+(AI34+AJ34-AM34)+(AN34+AO34-AR34)+(AS34+AT34-AW34)+(AX34+AY34-BB34),2) -> 41046.57 | BE34: =IF(H34>0.005,$C$5,IF(M34>0.005,$C$6,IF(R34>0.005,$C$7,IF(W34>0.005,$C$8,IF(AB34>0.005,$C$9,IF(AG34>0.005,$C$10,IF(AL34>0.005,$C$11,IF(AQ34>0.005,$C$12,IF(AV34>0.005,$C$13,IF(BA34>0.005,$C$14,"")))))))))) -> 亲友借款（老王）
A35: 12 | B35: =EDATE($C$17,A35-1) -> 46661 | C35: =G35+L35+Q35+V35+AA35+AF35+AK35+AP35+AU35+AZ35 -> 3750 | D35: =MAX(0,$C$16-C35) -> 2072 | E35: =ROUND(MAX(0,E34+F34-I34),2) -> 0 | F35: =ROUND(E35*$E$5/12,2) -> 0 | G35: =MIN($F$5,E35+F35) -> 0 | H35: =MAX(0,MIN(E35+F35-G35,$D35)) -> 0 | I35: =G35+H35 -> 0 | J35: =ROUND(MAX(0,J34+K34-N34),2) -> 4168.13 | K35: =ROUND(J35*$E$6/12,2) -> 0 | L35: =MIN($F$6,J35+K35) -> 500 | M35: =MAX(0,MIN(J35+K35-L35,$D35-(H35))) -> 2072 | N35: =L35+M35 -> 2572 | O35: =ROUND(MAX(0,O34+P34-S34),2) -> 14656.58 | P35: =ROUND(O35*$E$7/12,2) -> 293.13 | Q35: =MIN($F$7,O35+P35) -> 1350 | R35: =MAX(0,MIN(O35+P35-Q35,$D35-(H35+M35))) -> 0 | S35: =Q35+R35 -> 1350 | T35: =ROUND(MAX(0,T34+U34-X34),2) -> 22221.86 | U35: =ROUND(T35*$E$8/12,2) -> 333.33 | V35: =MIN($F$8,T35+U35) -> 1900 | W35: =MAX(0,MIN(T35+U35-V35,$D35-(H35+M35+R35))) -> 0 | X35: =V35+W35 -> 1900 | Y35: =ROUND(MAX(0,Y34+Z34-AC34),2) -> 0 | Z35: =ROUND(Y35*$E$9/12,2) -> 0 | AA35: =MIN($F$9,Y35+Z35) -> 0 | AB35: =MAX(0,MIN(Y35+Z35-AA35,$D35-(H35+M35+R35+W35))) -> 0 | AC35: =AA35+AB35 -> 0 | AD35: =ROUND(MAX(0,AD34+AE34-AH34),2) -> 0 | AE35: =ROUND(AD35*$E$10/12,2) -> 0 | AF35: =MIN($F$10,AD35+AE35) -> 0 | AG35: =MAX(0,MIN(AD35+AE35-AF35,$D35-(H35+M35+R35+W35+AB35))) -> 0 | AH35: =AF35+AG35 -> 0 | AI35: =ROUND(MAX(0,AI34+AJ34-AM34),2) -> 0 | AJ35: =ROUND(AI35*$E$11/12,2) -> 0 | AK35: =MIN($F$11,AI35+AJ35) -> 0 | AL35: =MAX(0,MIN(AI35+AJ35-AK35,$D35-(H35+M35+R35+W35+AB35+AG35))) -> 0 | AM35: =AK35+AL35 -> 0 | AN35: =ROUND(MAX(0,AN34+AO34-AR34),2) -> 0 | AO35: =ROUND(AN35*$E$12/12,2) -> 0 | AP35: =MIN($F$12,AN35+AO35) -> 0 | AQ35: =MAX(0,MIN(AN35+AO35-AP35,$D35-(H35+M35+R35+W35+AB35+AG35+AL35))) -> 0 | AR35: =AP35+AQ35 -> 0 | AS35: =ROUND(MAX(0,AS34+AT34-AW34),2) -> 0 | AT35: =ROUND(AS35*$E$13/12,2) -> 0 | AU35: =MIN($F$13,AS35+AT35) -> 0 | AV35: =MAX(0,MIN(AS35+AT35-AU35,$D35-(H35+M35+R35+W35+AB35+AG35+AL35+AQ35))) -> 0 | AW35: =AU35+AV35 -> 0 | AX35: =ROUND(MAX(0,AX34+AY34-BB34),2) -> 0 | AY35: =ROUND(AX35*$E$14/12,2) -> 0 | AZ35: =MIN($F$14,AX35+AY35) -> 0 | BA35: =MAX(0,MIN(AX35+AY35-AZ35,$D35-(H35+M35+R35+W35+AB35+AG35+AL35+AQ35+AV35))) -> 0 | BB35: =AZ35+BA35 -> 0 | BC35: =I35+N35+S35+X35+AC35+AH35+AM35+AR35+AW35+BB35 -> 5822 | BD35: =ROUND((E35+F35-I35)+(J35+K35-N35)+(O35+P35-S35)+(T35+U35-X35)+(Y35+Z35-AC35)+(AD35+AE35-AH35)+(AI35+AJ35-AM35)+(AN35+AO35-AR35)+(AS35+AT35-AW35)+(AX35+AY35-BB35),2) -> 35851.03 | BE35: =IF(H35>0.005,$C$5,IF(M35>0.005,$C$6,IF(R35>0.005,$C$7,IF(W35>0.005,$C$8,IF(AB35>0.005,$C$9,IF(AG35>0.005,$C$10,IF(AL35>0.005,$C$11,IF(AQ35>0.005,$C$12,IF(AV35>0.005,$C$13,IF(BA35>0.005,$C$14,"")))))))))) -> 亲友借款（老王）
A36: 13 | B36: =EDATE($C$17,A36-1) -> 46692 | C36: =G36+L36+Q36+V36+AA36+AF36+AK36+AP36+AU36+AZ36 -> 3750 | D36: =MAX(0,$C$16-C36) -> 2072 | E36: =ROUND(MAX(0,E35+F35-I35),2) -> 0 | F36: =ROUND(E36*$E$5/12,2) -> 0 | G36: =MIN($F$5,E36+F36) -> 0 | H36: =MAX(0,MIN(E36+F36-G36,$D36)) -> 0 | I36: =G36+H36 -> 0 | J36: =ROUND(MAX(0,J35+K35-N35),2) -> 1596.13 | K36: =ROUND(J36*$E$6/12,2) -> 0 | L36: =MIN($F$6,J36+K36) -> 500 | M36: =MAX(0,MIN(J36+K36-L36,$D36-(H36))) -> 1096.13 | N36: =L36+M36 -> 1596.13 | O36: =ROUND(MAX(0,O35+P35-S35),2) -> 13599.71 | P36: =ROUND(O36*$E$7/12,2) -> 271.99 | Q36: =MIN($F$7,O36+P36) -> 1350 | R36: =MAX(0,MIN(O36+P36-Q36,$D36-(H36+M36))) -> 975.87 | S36: =Q36+R36 -> 2325.87 | T36: =ROUND(MAX(0,T35+U35-X35),2) -> 20655.19 | U36: =ROUND(T36*$E$8/12,2) -> 309.83 | V36: =MIN($F$8,T36+U36) -> 1900 | W36: =MAX(0,MIN(T36+U36-V36,$D36-(H36+M36+R36))) -> 0 | X36: =V36+W36 -> 1900 | Y36: =ROUND(MAX(0,Y35+Z35-AC35),2) -> 0 | Z36: =ROUND(Y36*$E$9/12,2) -> 0 | AA36: =MIN($F$9,Y36+Z36) -> 0 | AB36: =MAX(0,MIN(Y36+Z36-AA36,$D36-(H36+M36+R36+W36))) -> 0 | AC36: =AA36+AB36 -> 0 | AD36: =ROUND(MAX(0,AD35+AE35-AH35),2) -> 0 | AE36: =ROUND(AD36*$E$10/12,2) -> 0 | AF36: =MIN($F$10,AD36+AE36) -> 0 | AG36: =MAX(0,MIN(AD36+AE36-AF36,$D36-(H36+M36+R36+W36+AB36))) -> 0 | AH36: =AF36+AG36 -> 0 | AI36: =ROUND(MAX(0,AI35+AJ35-AM35),2) -> 0 | AJ36: =ROUND(AI36*$E$11/12,2) -> 0 | AK36: =MIN($F$11,AI36+AJ36) -> 0 | AL36: =MAX(0,MIN(AI36+AJ36-AK36,$D36-(H36+M36+R36+W36+AB36+AG36))) -> 0 | AM36: =AK36+AL36 -> 0 | AN36: =ROUND(MAX(0,AN35+AO35-AR35),2) -> 0 | AO36: =ROUND(AN36*$E$12/12,2) -> 0 | AP36: =MIN($F$12,AN36+AO36) -> 0 | AQ36: =MAX(0,MIN(AN36+AO36-AP36,$D36-(H36+M36+R36+W36+AB36+AG36+AL36))) -> 0 | AR36: =AP36+AQ36 -> 0 | AS36: =ROUND(MAX(0,AS35+AT35-AW35),2) -> 0 | AT36: =ROUND(AS36*$E$13/12,2) -> 0 | AU36: =MIN($F$13,AS36+AT36) -> 0 | AV36: =MAX(0,MIN(AS36+AT36-AU36,$D36-(H36+M36+R36+W36+AB36+AG36+AL36+AQ36))) -> 0 | AW36: =AU36+AV36 -> 0 | AX36: =ROUND(MAX(0,AX35+AY35-BB35),2) -> 0 | AY36: =ROUND(AX36*$E$14/12,2) -> 0 | AZ36: =MIN($F$14,AX36+AY36) -> 0 | BA36: =MAX(0,MIN(AX36+AY36-AZ36,$D36-(H36+M36+R36+W36+AB36+AG36+AL36+AQ36+AV36))) -> 0 | BB36: =AZ36+BA36 -> 0 | BC36: =I36+N36+S36+X36+AC36+AH36+AM36+AR36+AW36+BB36 -> 5822 | BD36: =ROUND((E36+F36-I36)+(J36+K36-N36)+(O36+P36-S36)+(T36+U36-X36)+(Y36+Z36-AC36)+(AD36+AE36-AH36)+(AI36+AJ36-AM36)+(AN36+AO36-AR36)+(AS36+AT36-AW36)+(AX36+AY36-BB36),2) -> 30610.85 | BE36: =IF(H36>0.005,$C$5,IF(M36>0.005,$C$6,IF(R36>0.005,$C$7,IF(W36>0.005,$C$8,IF(AB36>0.005,$C$9,IF(AG36>0.005,$C$10,IF(AL36>0.005,$C$11,IF(AQ36>0.005,$C$12,IF(AV36>0.005,$C$13,IF(BA36>0.005,$C$14,"")))))))))) -> 亲友借款（老王）
... A263: 240 | B263: =EDATE($C$17,A263-1) -> 53601 | C263: =G263+L263+Q263+V263+AA263+AF263+AK263+AP263+AU263+AZ263 -> 0 | D263: =MAX(0,$C$16-C263) -> 5822 | E263: =ROUND(MAX(0,E262+F262-I262),2) -> 0 | F263: =ROUND(E263*$E$5/12,2) -> 0 | G263: =MIN($F$5,E263+F263) -> 0 | H263: =MAX(0,MIN(E263+F263-G263,$D263)) -> 0 | I263: =G263+H263 -> 0 | J263: =ROUND(MAX(0,J262+K262-N262),2) -> 0 | K263: =ROUND(J263*$E$6/12,2) -> 0 | L263: =MIN($F$6,J263+K263) -> 0 | M263: =MAX(0,MIN(J263+K263-L263,$D263-(H263))) -> 0 | N263: =L263+M263 -> 0 | O263: =ROUND(MAX(0,O262+P262-S262),2) -> 0 | P263: =ROUND(O263*$E$7/12,2) -> 0 | Q263: =MIN($F$7,O263+P263) -> 0 | R263: =MAX(0,MIN(O263+P263-Q263,$D263-(H263+M263))) -> 0 | S263: =Q263+R263 -> 0 | T263: =ROUND(MAX(0,T262+U262-X262),2) -> 0 | U263: =ROUND(T263*$E$8/12,2) -> 0 | V263: =MIN($F$8,T263+U263) -> 0 | W263: =MAX(0,MIN(T263+U263-V263,$D263-(H263+M263+R263))) -> 0 | X263: =V263+W263 -> 0 | Y263: =ROUND(MAX(0,Y262+Z262-AC262),2) -> 0 | Z263: =ROUND(Y263*$E$9/12,2) -> 0 | AA263: =MIN($F$9,Y263+Z263) -> 0 | AB263: =MAX(0,MIN(Y263+Z263-AA263,$D263-(H263+M263+R263+W263))) -> 0 | AC263: =AA263+AB263 -> 0 | AD263: =ROUND(MAX(0,AD262+AE262-AH262),2) -> 0 | AE263: =ROUND(AD263*$E$10/12,2) -> 0 | AF263: =MIN($F$10,AD263+AE263) -> 0 | AG263: =MAX(0,MIN(AD263+AE263-AF263,$D263-(H263+M263+R263+W263+AB263))) -> 0 | AH263: =AF263+AG263 -> 0 | AI263: =ROUND(MAX(0,AI262+AJ262-AM262),2) -> 0 | AJ263: =ROUND(AI263*$E$11/12,2) -> 0 | AK263: =MIN($F$11,AI263+AJ263) -> 0 | AL263: =MAX(0,MIN(AI263+AJ263-AK263,$D263-(H263+M263+R263+W263+AB263+AG263))) -> 0 | AM263: =AK263+AL263 -> 0 | AN263: =ROUND(MAX(0,AN262+AO262-AR262),2) -> 0 | AO263: =ROUND(AN263*$E$12/12,2) -> 0 | AP263: =MIN($F$12,AN263+AO263) -> 0 | AQ263: =MAX(0,MIN(AN263+AO263-AP263,$D263-(H263+M263+R263+W263+AB263+AG263+AL263))) -> 0 | AR263: =AP263+AQ263 -> 0 | AS263: =ROUND(MAX(0,AS262+AT262-AW262),2) -> 0 | AT263: =ROUND(AS263*$E$13/12,2) -> 0 | AU263: =MIN($F$13,AS263+AT263) -> 0 | AV263: =MAX(0,MIN(AS263+AT263-AU263,$D263-(H263+M263+R263+W263+AB263+AG263+AL263+AQ263))) -> 0 | AW263: =AU263+AV263 -> 0 | AX263: =ROUND(MAX(0,AX262+AY262-BB262),2) -> 0 | AY263: =ROUND(AX263*$E$14/12,2) -> 0 | AZ263: =MIN($F$14,AX263+AY263) -> 0 | BA263: =MAX(0,MIN(AX263+AY263-AZ263,$D263-(H263+M263+R263+W263+AB263+AG263+AL263+AQ263+AV263))) -> 0 | BB263: =AZ263+BA263 -> 0 | BC263: =I263+N263+S263+X263+AC263+AH263+AM263+AR263+AW263+BB263 -> 0 | BD263: =ROUND((E263+F263-I263)+(J263+K263-N263)+(O263+P263-S263)+(T263+U263-X263)+(Y263+Z263-AC263)+(AD263+AE263-AH263)+(AI263+AJ263-AM263)+(AN263+AO263-AR263)+(AS263+AT263-AW263)+(AX263+AY263-BB263),2) -> 0 | BE263: =IF(H263>0.005,$C$5,IF(M263>0.005,$C$6,IF(R263>0.005,$C$7,IF(W263>0.005,$C$8,IF(AB263>0.005,$C$9,IF(AG263>0.005,$C$10,IF(AL263>0.005,$C$11,IF(AQ263>0.005,$C$12,IF(AV263>0.005,$C$13,IF(BA263>0.005,$C$14,""))))))))))

Sheet 计算_雪崩
A1: 自动计算（雪崩法）—— 这一页不用改
A2: 每月利息 = 欠款 × 年化 ÷ 12；先还所有最低还款，剩下的钱按顺序砸向排在最前面的债。
A4: 顺序 | B4: 清单第几行 | C4: 名称 | D4: 初始欠款 | E4: 年化 | F4: 每月最低还款 | G4: 第几个月还清 | H4: 总利息
A5: 1 | B5: =IFERROR(MATCH(A5,债务清单!$K$5:$K$14,0),"") -> 3 | C5: =IF(B5="","",INDEX(债务清单!$B$5:$B$14,B5)) -> 网贷X | D5: =IF(B5="",0,INDEX(债务清单!$D$5:$D$14,B5)) -> 25000 | E5: =IF(B5="",0,INDEX(债务清单!$O$5:$O$14,B5)) -> 0.24 | F5: =IF(B5="",0,N(INDEX(债务清单!$F$5:$F$14,B5))) -> 1350 | G5: =IF(D5<=0,"",IF(E263+F263-I263>0.01,"超过20年",COUNTIF(E24:E263,">0.005"))) -> 13 | H5: =SUM(F24:F263) -> 3391.34
A6: 2 | B6: =IFERROR(MATCH(A6,债务清单!$K$5:$K$14,0),"") -> 1 | C6: =IF(B6="","",INDEX(债务清单!$B$5:$B$14,B6)) -> 信用卡A | D6: =IF(B6="",0,INDEX(债务清单!$D$5:$D$14,B6)) -> 38000 | E6: =IF(B6="",0,INDEX(债务清单!$O$5:$O$14,B6)) -> 0.18 | F6: =IF(B6="",0,N(INDEX(债务清单!$F$5:$F$14,B6))) -> 1900 | G6: =IF(D6<=0,"",IF(J263+K263-N263>0.01,"超过20年",COUNTIF(J24:J263,">0.005"))) -> 17 | H6: =SUM(K24:K263) -> 6252.74
A7: 3 | B7: =IFERROR(MATCH(A7,债务清单!$K$5:$K$14,0),"") -> 2 | C7: =IF(B7="","",INDEX(债务清单!$B$5:$B$14,B7)) -> 信用卡B（分期） | D7: =IF(B7="",0,INDEX(债务清单!$D$5:$D$14,B7)) -> 12000 | E7: =IF(B7="",0,INDEX(债务清单!$O$5:$O$14,B7)) -> 0.13 | F7: =IF(B7="",0,N(INDEX(债务清单!$F$5:$F$14,B7))) -> 1072 | G7: =IF(D7<=0,"",IF(O263+P263-S263>0.01,"超过20年",COUNTIF(O24:O263,">0.005"))) -> 12 | H7: =SUM(P24:P263) -> 861.55
A8: 4 | B8: =IFERROR(MATCH(A8,债务清单!$K$5:$K$14,0),"") -> 4 | C8: =IF(B8="","",INDEX(债务清单!$B$5:$B$14,B8)) -> 亲友借款（老王） | D8: =IF(B8="",0,INDEX(债务清单!$D$5:$D$14,B8)) -> 20000 | E8: =IF(B8="",0,INDEX(债务清单!$O$5:$O$14,B8)) -> 0 | F8: =IF(B8="",0,N(INDEX(债务清单!$F$5:$F$14,B8))) -> 500 | G8: =IF(D8<=0,"",IF(T263+U263-X263>0.01,"超过20年",COUNTIF(T24:T263,">0.005"))) -> 19 | H8: =SUM(U24:U263) -> 0
A9: 5 | B9: =IFERROR(MATCH(A9,债务清单!$K$5:$K$14,0),"") | C9: =IF(B9="","",INDEX(债务清单!$B$5:$B$14,B9)) | D9: =IF(B9="",0,INDEX(债务清单!$D$5:$D$14,B9)) -> 0 | E9: =IF(B9="",0,INDEX(债务清单!$O$5:$O$14,B9)) -> 0 | F9: =IF(B9="",0,N(INDEX(债务清单!$F$5:$F$14,B9))) -> 0 | G9: =IF(D9<=0,"",IF(Y263+Z263-AC263>0.01,"超过20年",COUNTIF(Y24:Y263,">0.005"))) | H9: =SUM(Z24:Z263) -> 0
A10: 6 | B10: =IFERROR(MATCH(A10,债务清单!$K$5:$K$14,0),"") | C10: =IF(B10="","",INDEX(债务清单!$B$5:$B$14,B10)) | D10: =IF(B10="",0,INDEX(债务清单!$D$5:$D$14,B10)) -> 0 | E10: =IF(B10="",0,INDEX(债务清单!$O$5:$O$14,B10)) -> 0 | F10: =IF(B10="",0,N(INDEX(债务清单!$F$5:$F$14,B10))) -> 0 | G10: =IF(D10<=0,"",IF(AD263+AE263-AH263>0.01,"超过20年",COUNTIF(AD24:AD263,">0.005"))) | H10: =SUM(AE24:AE263) -> 0
A11: 7 | B11: =IFERROR(MATCH(A11,债务清单!$K$5:$K$14,0),"") | C11: =IF(B11="","",INDEX(债务清单!$B$5:$B$14,B11)) | D11: =IF(B11="",0,INDEX(债务清单!$D$5:$D$14,B11)) -> 0 | E11: =IF(B11="",0,INDEX(债务清单!$O$5:$O$14,B11)) -> 0 | F11: =IF(B11="",0,N(INDEX(债务清单!$F$5:$F$14,B11))) -> 0 | G11: =IF(D11<=0,"",IF(AI263+AJ263-AM263>0.01,"超过20年",COUNTIF(AI24:AI263,">0.005"))) | H11: =SUM(AJ24:AJ263) -> 0
A12: 8 | B12: =IFERROR(MATCH(A12,债务清单!$K$5:$K$14,0),"") | C12: =IF(B12="","",INDEX(债务清单!$B$5:$B$14,B12)) | D12: =IF(B12="",0,INDEX(债务清单!$D$5:$D$14,B12)) -> 0 | E12: =IF(B12="",0,INDEX(债务清单!$O$5:$O$14,B12)) -> 0 | F12: =IF(B12="",0,N(INDEX(债务清单!$F$5:$F$14,B12))) -> 0 | G12: =IF(D12<=0,"",IF(AN263+AO263-AR263>0.01,"超过20年",COUNTIF(AN24:AN263,">0.005"))) | H12: =SUM(AO24:AO263) -> 0
A13: 9 | B13: =IFERROR(MATCH(A13,债务清单!$K$5:$K$14,0),"") | C13: =IF(B13="","",INDEX(债务清单!$B$5:$B$14,B13)) | D13: =IF(B13="",0,INDEX(债务清单!$D$5:$D$14,B13)) -> 0 | E13: =IF(B13="",0,INDEX(债务清单!$O$5:$O$14,B13)) -> 0 | F13: =IF(B13="",0,N(INDEX(债务清单!$F$5:$F$14,B13))) -> 0 | G13: =IF(D13<=0,"",IF(AS263+AT263-AW263>0.01,"超过20年",COUNTIF(AS24:AS263,">0.005"))) | H13: =SUM(AT24:AT263) -> 0
A14: 10 | B14: =IFERROR(MATCH(A14,债务清单!$K$5:$K$14,0),"") | C14: =IF(B14="","",INDEX(债务清单!$B$5:$B$14,B14)) | D14: =IF(B14="",0,INDEX(债务清单!$D$5:$D$14,B14)) -> 0 | E14: =IF(B14="",0,INDEX(债务清单!$O$5:$O$14,B14)) -> 0 | F14: =IF(B14="",0,N(INDEX(债务清单!$F$5:$F$14,B14))) -> 0 | G14: =IF(D14<=0,"",IF(AX263+AY263-BB263>0.01,"超过20年",COUNTIF(AX24:AX263,">0.005"))) | H14: =SUM(AY24:AY263) -> 0
A16: 每月还款总预算 | C16: =每月预算!B27 -> 5822
A17: 开始月份 | C17: =每月预算!B30 -> 46327
A18: 还清需要几个月 | C18: =IF(COUNTIF(G5:G14,"超过20年")>0,"超过20年",IF(COUNT(G5:G14)=0,0,MAX(G5:G14))) -> 19
A19: 总利息 | C19: =SUM(H5:H14) -> 10505.63
A20: 第一笔还清是第几个月 | C20: =IF(COUNT(G5:G14)=0,"",MIN(G5:G14)) -> 12
E22: =IF(C5="","第1笔（空）","第1笔："&C5) -> 第1笔：网贷X | J22: =IF(C6="","第2笔（空）","第2笔："&C6) -> 第2笔：信用卡A | O22: =IF(C7="","第3笔（空）","第3笔："&C7) -> 第3笔：信用卡B（分期） | T22: =IF(C8="","第4笔（空）","第4笔："&C8) -> 第4笔：亲友借款（老王） | Y22: =IF(C9="","第5笔（空）","第5笔："&C9) -> 第5笔（空） | AD22: =IF(C10="","第6笔（空）","第6笔："&C10) -> 第6笔（空） | AI22: =IF(C11="","第7笔（空）","第7笔："&C11) -> 第7笔（空） | AN22: =IF(C12="","第8笔（空）","第8笔："&C12) -> 第8笔（空） | AS22: =IF(C13="","第9笔（空）","第9笔："&C13) -> 第9笔（空） | AX22: =IF(C14="","第10笔（空）","第10笔："&C14) -> 第10笔（空）
A23: 月份 | B23: 日期 | C23: 最低还款部分合计 | D23: 可加速的钱 | E23: 月初欠款 | F23: 利息 | G23: 最低还款部分 | H23: 加速部分 | I23: 本月还款 | J23: 月初欠款 | K23: 利息 | L23: 最低还款部分 | M23: 加速部分 | N23: 本月还款 | O23: 月初欠款 | P23: 利息 | Q23: 最低还款部分 | R23: 加速部分 | S23: 本月还款 | T23: 月初欠款 | U23: 利息 | V23: 最低还款部分 | W23: 加速部分 | X23: 本月还款 | Y23: 月初欠款 | Z23: 利息 | AA23: 最低还款部分 | AB23: 加速部分 | AC23: 本月还款 | AD23: 月初欠款 | AE23: 利息 | AF23: 最低还款部分 | AG23: 加速部分 | AH23: 本月还款 | AI23: 月初欠款 | AJ23: 利息 | AK23: 最低还款部分 | AL23: 加速部分 | AM23: 本月还款 | AN23: 月初欠款 | AO23: 利息 | AP23: 最低还款部分 | AQ23: 加速部分 | AR23: 本月还款 | AS23: 月初欠款 | AT23: 利息 | AU23: 最低还款部分 | AV23: 加速部分 | AW23: 本月还款 | AX23: 月初欠款 | AY23: 利息 | AZ23: 最低还款部分 | BA23: 加速部分 | BB23: 本月还款 | BC23: 本月还款合计 | BD23: 月末还剩合计 | BE23: 加速钱给了
A24: 1 | B24: =EDATE($C$17,A24-1) -> 46327 | C24: =G24+L24+Q24+V24+AA24+AF24+AK24+AP24+AU24+AZ24 -> 4822 | D24: =MAX(0,$C$16-C24) -> 1000 | E24: =$D$5 -> 25000 | F24: =ROUND(E24*$E$5/12,2) -> 500 | G24: =MIN($F$5,E24+F24) -> 1350 | H24: =MAX(0,MIN(E24+F24-G24,$D24)) -> 1000 | I24: =G24+H24 -> 2350 | J24: =$D$6 -> 38000 | K24: =ROUND(J24*$E$6/12,2) -> 570 | L24: =MIN($F$6,J24+K24) -> 1900 | M24: =MAX(0,MIN(J24+K24-L24,$D24-(H24))) -> 0 | N24: =L24+M24 -> 1900 | O24: =$D$7 -> 12000 | P24: =ROUND(O24*$E$7/12,2) -> 130 | Q24: =MIN($F$7,O24+P24) -> 1072 | R24: =MAX(0,MIN(O24+P24-Q24,$D24-(H24+M24))) -> 0 | S24: =Q24+R24 -> 1072 | T24: =$D$8 -> 20000 | U24: =ROUND(T24*$E$8/12,2) -> 0 | V24: =MIN($F$8,T24+U24) -> 500 | W24: =MAX(0,MIN(T24+U24-V24,$D24-(H24+M24+R24))) -> 0 | X24: =V24+W24 -> 500 | Y24: =$D$9 -> 0 | Z24: =ROUND(Y24*$E$9/12,2) -> 0 | AA24: =MIN($F$9,Y24+Z24) -> 0 | AB24: =MAX(0,MIN(Y24+Z24-AA24,$D24-(H24+M24+R24+W24))) -> 0 | AC24: =AA24+AB24 -> 0 | AD24: =$D$10 -> 0 | AE24: =ROUND(AD24*$E$10/12,2) -> 0 | AF24: =MIN($F$10,AD24+AE24) -> 0 | AG24: =MAX(0,MIN(AD24+AE24-AF24,$D24-(H24+M24+R24+W24+AB24))) -> 0 | AH24: =AF24+AG24 -> 0 | AI24: =$D$11 -> 0 | AJ24: =ROUND(AI24*$E$11/12,2) -> 0 | AK24: =MIN($F$11,AI24+AJ24) -> 0 | AL24: =MAX(0,MIN(AI24+AJ24-AK24,$D24-(H24+M24+R24+W24+AB24+AG24))) -> 0 | AM24: =AK24+AL24 -> 0 | AN24: =$D$12 -> 0 | AO24: =ROUND(AN24*$E$12/12,2) -> 0 | AP24: =MIN($F$12,AN24+AO24) -> 0 | AQ24: =MAX(0,MIN(AN24+AO24-AP24,$D24-(H24+M24+R24+W24+AB24+AG24+AL24))) -> 0 | AR24: =AP24+AQ24 -> 0 | AS24: =$D$13 -> 0 | AT24: =ROUND(AS24*$E$13/12,2) -> 0 | AU24: =MIN($F$13,AS24+AT24) -> 0 | AV24: =MAX(0,MIN(AS24+AT24-AU24,$D24-(H24+M24+R24+W24+AB24+AG24+AL24+AQ24))) -> 0 | AW24: =AU24+AV24 -> 0 | AX24: =$D$14 -> 0 | AY24: =ROUND(AX24*$E$14/12,2) -> 0 | AZ24: =MIN($F$14,AX24+AY24) -> 0 | BA24: =MAX(0,MIN(AX24+AY24-AZ24,$D24-(H24+M24+R24+W24+AB24+AG24+AL24+AQ24+AV24))) -> 0 | BB24: =AZ24+BA24 -> 0 | BC24: =I24+N24+S24+X24+AC24+AH24+AM24+AR24+AW24+BB24 -> 5822 | BD24: =ROUND((E24+F24-I24)+(J24+K24-N24)+(O24+P24-S24)+(T24+U24-X24)+(Y24+Z24-AC24)+(AD24+AE24-AH24)+(AI24+AJ24-AM24)+(AN24+AO24-AR24)+(AS24+AT24-AW24)+(AX24+AY24-BB24),2) -> 90378 | BE24: =IF(H24>0.005,$C$5,IF(M24>0.005,$C$6,IF(R24>0.005,$C$7,IF(W24>0.005,$C$8,IF(AB24>0.005,$C$9,IF(AG24>0.005,$C$10,IF(AL24>0.005,$C$11,IF(AQ24>0.005,$C$12,IF(AV24>0.005,$C$13,IF(BA24>0.005,$C$14,"")))))))))) -> 网贷X
A25: 2 | B25: =EDATE($C$17,A25-1) -> 46357 | C25: =G25+L25+Q25+V25+AA25+AF25+AK25+AP25+AU25+AZ25 -> 4822 | D25: =MAX(0,$C$16-C25) -> 1000 | E25: =ROUND(MAX(0,E24+F24-I24),2) -> 23150 | F25: =ROUND(E25*$E$5/12,2) -> 463 | G25: =MIN($F$5,E25+F25) -> 1350 | H25: =MAX(0,MIN(E25+F25-G25,$D25)) -> 1000 | I25: =G25+H25 -> 2350 | J25: =ROUND(MAX(0,J24+K24-N24),2) -> 36670 | K25: =ROUND(J25*$E$6/12,2) -> 550.05 | L25: =MIN($F$6,J25+K25) -> 1900 | M25: =MAX(0,MIN(J25+K25-L25,$D25-(H25))) -> 0 | N25: =L25+M25 -> 1900 | O25: =ROUND(MAX(0,O24+P24-S24),2) -> 11058 | P25: =ROUND(O25*$E$7/12,2) -> 119.8 | Q25: =MIN($F$7,O25+P25) -> 1072 | R25: =MAX(0,MIN(O25+P25-Q25,$D25-(H25+M25))) -> 0 | S25: =Q25+R25 -> 1072 | T25: =ROUND(MAX(0,T24+U24-X24),2) -> 19500 | U25: =ROUND(T25*$E$8/12,2) -> 0 | V25: =MIN($F$8,T25+U25) -> 500 | W25: =MAX(0,MIN(T25+U25-V25,$D25-(H25+M25+R25))) -> 0 | X25: =V25+W25 -> 500 | Y25: =ROUND(MAX(0,Y24+Z24-AC24),2) -> 0 | Z25: =ROUND(Y25*$E$9/12,2) -> 0 | AA25: =MIN($F$9,Y25+Z25) -> 0 | AB25: =MAX(0,MIN(Y25+Z25-AA25,$D25-(H25+M25+R25+W25))) -> 0 | AC25: =AA25+AB25 -> 0 | AD25: =ROUND(MAX(0,AD24+AE24-AH24),2) -> 0 | AE25: =ROUND(AD25*$E$10/12,2) -> 0 | AF25: =MIN($F$10,AD25+AE25) -> 0 | AG25: =MAX(0,MIN(AD25+AE25-AF25,$D25-(H25+M25+R25+W25+AB25))) -> 0 | AH25: =AF25+AG25 -> 0 | AI25: =ROUND(MAX(0,AI24+AJ24-AM24),2) -> 0 | AJ25: =ROUND(AI25*$E$11/12,2) -> 0 | AK25: =MIN($F$11,AI25+AJ25) -> 0 | AL25: =MAX(0,MIN(AI25+AJ25-AK25,$D25-(H25+M25+R25+W25+AB25+AG25))) -> 0 | AM25: =AK25+AL25 -> 0 | AN25: =ROUND(MAX(0,AN24+AO24-AR24),2) -> 0 | AO25: =ROUND(AN25*$E$12/12,2) -> 0 | AP25: =MIN($F$12,AN25+AO25) -> 0 | AQ25: =MAX(0,MIN(AN25+AO25-AP25,$D25-(H25+M25+R25+W25+AB25+AG25+AL25))) -> 0 | AR25: =AP25+AQ25 -> 0 | AS25: =ROUND(MAX(0,AS24+AT24-AW24),2) -> 0 | AT25: =ROUND(AS25*$E$13/12,2) -> 0 | AU25: =MIN($F$13,AS25+AT25) -> 0 | AV25: =MAX(0,MIN(AS25+AT25-AU25,$D25-(H25+M25+R25+W25+AB25+AG25+AL25+AQ25))) -> 0 | AW25: =AU25+AV25 -> 0 | AX25: =ROUND(MAX(0,AX24+AY24-BB24),2) -> 0 | AY25: =ROUND(AX25*$E$14/12,2) -> 0 | AZ25: =MIN($F$14,AX25+AY25) -> 0 | BA25: =MAX(0,MIN(AX25+AY25-AZ25,$D25-(H25+M25+R25+W25+AB25+AG25+AL25+AQ25+AV25))) -> 0 | BB25: =AZ25+BA25 -> 0 | BC25: =I25+N25+S25+X25+AC25+AH25+AM25+AR25+AW25+BB25 -> 5822 | BD25: =ROUND((E25+F25-I25)+(J25+K25-N25)+(O25+P25-S25)+(T25+U25-X25)+(Y25+Z25-AC25)+(AD25+AE25-AH25)+(AI25+AJ25-AM25)+(AN25+AO25-AR25)+(AS25+AT25-AW25)+(AX25+AY25-BB25),2) -> 85688.85 | BE25: =IF(H25>0.005,$C$5,IF(M25>0.005,$C$6,IF(R25>0.005,$C$7,IF(W25>0.005,$C$8,IF(AB25>0.005,$C$9,IF(AG25>0.005,$C$10,IF(AL25>0.005,$C$11,IF(AQ25>0.005,$C$12,IF(AV25>0.005,$C$13,IF(BA25>0.005,$C$14,"")))))))))) -> 网贷X
A26: 3 | B26: =EDATE($C$17,A26-1) -> 46388 | C26: =G26+L26+Q26+V26+AA26+AF26+AK26+AP26+AU26+AZ26 -> 4822 | D26: =MAX(0,$C$16-C26) -> 1000 | E26: =ROUND(MAX(0,E25+F25-I25),2) -> 21263 | F26: =ROUND(E26*$E$5/12,2) -> 425.26 | G26: =MIN($F$5,E26+F26) -> 1350 | H26: =MAX(0,MIN(E26+F26-G26,$D26)) -> 1000 | I26: =G26+H26 -> 2350 | J26: =ROUND(MAX(0,J25+K25-N25),2) -> 35320.05 | K26: =ROUND(J26*$E$6/12,2) -> 529.8 | L26: =MIN($F$6,J26+K26) -> 1900 | M26: =MAX(0,MIN(J26+K26-L26,$D26-(H26))) -> 0 | N26: =L26+M26 -> 1900 | O26: =ROUND(MAX(0,O25+P25-S25),2) -> 10105.8 | P26: =ROUND(O26*$E$7/12,2) -> 109.48 | Q26: =MIN($F$7,O26+P26) -> 1072 | R26: =MAX(0,MIN(O26+P26-Q26,$D26-(H26+M26))) -> 0 | S26: =Q26+R26 -> 1072 | T26: =ROUND(MAX(0,T25+U25-X25),2) -> 19000 | U26: =ROUND(T26*$E$8/12,2) -> 0 | V26: =MIN($F$8,T26+U26) -> 500 | W26: =MAX(0,MIN(T26+U26-V26,$D26-(H26+M26+R26))) -> 0 | X26: =V26+W26 -> 500 | Y26: =ROUND(MAX(0,Y25+Z25-AC25),2) -> 0 | Z26: =ROUND(Y26*$E$9/12,2) -> 0 | AA26: =MIN($F$9,Y26+Z26) -> 0 | AB26: =MAX(0,MIN(Y26+Z26-AA26,$D26-(H26+M26+R26+W26))) -> 0 | AC26: =AA26+AB26 -> 0 | AD26: =ROUND(MAX(0,AD25+AE25-AH25),2) -> 0 | AE26: =ROUND(AD26*$E$10/12,2) -> 0 | AF26: =MIN($F$10,AD26+AE26) -> 0 | AG26: =MAX(0,MIN(AD26+AE26-AF26,$D26-(H26+M26+R26+W26+AB26))) -> 0 | AH26: =AF26+AG26 -> 0 | AI26: =ROUND(MAX(0,AI25+AJ25-AM25),2) -> 0 | AJ26: =ROUND(AI26*$E$11/12,2) -> 0 | AK26: =MIN($F$11,AI26+AJ26) -> 0 | AL26: =MAX(0,MIN(AI26+AJ26-AK26,$D26-(H26+M26+R26+W26+AB26+AG26))) -> 0 | AM26: =AK26+AL26 -> 0 | AN26: =ROUND(MAX(0,AN25+AO25-AR25),2) -> 0 | AO26: =ROUND(AN26*$E$12/12,2) -> 0 | AP26: =MIN($F$12,AN26+AO26) -> 0 | AQ26: =MAX(0,MIN(AN26+AO26-AP26,$D26-(H26+M26+R26+W26+AB26+AG26+AL26))) -> 0 | AR26: =AP26+AQ26 -> 0 | AS26: =ROUND(MAX(0,AS25+AT25-AW25),2) -> 0 | AT26: =ROUND(AS26*$E$13/12,2) -> 0 | AU26: =MIN($F$13,AS26+AT26) -> 0 | AV26: =MAX(0,MIN(AS26+AT26-AU26,$D26-(H26+M26+R26+W26+AB26+AG26+AL26+AQ26))) -> 0 | AW26: =AU26+AV26 -> 0 | AX26: =ROUND(MAX(0,AX25+AY25-BB25),2) -> 0 | AY26: =ROUND(AX26*$E$14/12,2) -> 0 | AZ26: =MIN($F$14,AX26+AY26) -> 0 | BA26: =MAX(0,MIN(AX26+AY26-AZ26,$D26-(H26+M26+R26+W26+AB26+AG26+AL26+AQ26+AV26))) -> 0 | BB26: =AZ26+BA26 -> 0 | BC26: =I26+N26+S26+X26+AC26+AH26+AM26+AR26+AW26+BB26 -> 5822 | BD26: =ROUND((E26+F26-I26)+(J26+K26-N26)+(O26+P26-S26)+(T26+U26-X26)+(Y26+Z26-AC26)+(AD26+AE26-AH26)+(AI26+AJ26-AM26)+(AN26+AO26-AR26)+(AS26+AT26-AW26)+(AX26+AY26-BB26),2) -> 80931.39 | BE26: =IF(H26>0.005,$C$5,IF(M26>0.005,$C$6,IF(R26>0.005,$C$7,IF(W26>0.005,$C$8,IF(AB26>0.005,$C$9,IF(AG26>0.005,$C$10,IF(AL26>0.005,$C$11,IF(AQ26>0.005,$C$12,IF(AV26>0.005,$C$13,IF(BA26>0.005,$C$14,"")))))))))) -> 网贷X
A27: 4 | B27: =EDATE($C$17,A27-1) -> 46419 | C27: =G27+L27+Q27+V27+AA27+AF27+AK27+AP27+AU27+AZ27 -> 4822 | D27: =MAX(0,$C$16-C27) -> 1000 | E27: =ROUND(MAX(0,E26+F26-I26),2) -> 19338.26 | F27: =ROUND(E27*$E$5/12,2) -> 386.77 | G27: =MIN($F$5,E27+F27) -> 1350 | H27: =MAX(0,MIN(E27+F27-G27,$D27)) -> 1000 | I27: =G27+H27 -> 2350 | J27: =ROUND(MAX(0,J26+K26-N26),2) -> 33949.85 | K27: =ROUND(J27*$E$6/12,2) -> 509.25 | L27: =MIN($F$6,J27+K27) -> 1900 | M27: =MAX(0,MIN(J27+K27-L27,$D27-(H27))) -> 0 | N27: =L27+M27 -> 1900 | O27: =ROUND(MAX(0,O26+P26-S26),2) -> 9143.28 | P27: =ROUND(O27*$E$7/12,2) -> 99.05 | Q27: =MIN($F$7,O27+P27) -> 1072 | R27: =MAX(0,MIN(O27+P27-Q27,$D27-(H27+M27))) -> 0 | S27: =Q27+R27 -> 1072 | T27: =ROUND(MAX(0,T26+U26-X26),2) -> 18500 | U27: =ROUND(T27*$E$8/12,2) -> 0 | V27: =MIN($F$8,T27+U27) -> 500 | W27: =MAX(0,MIN(T27+U27-V27,$D27-(H27+M27+R27))) -> 0 | X27: =V27+W27 -> 500 | Y27: =ROUND(MAX(0,Y26+Z26-AC26),2) -> 0 | Z27: =ROUND(Y27*$E$9/12,2) -> 0 | AA27: =MIN($F$9,Y27+Z27) -> 0 | AB27: =MAX(0,MIN(Y27+Z27-AA27,$D27-(H27+M27+R27+W27))) -> 0 | AC27: =AA27+AB27 -> 0 | AD27: =ROUND(MAX(0,AD26+AE26-AH26),2) -> 0 | AE27: =ROUND(AD27*$E$10/12,2) -> 0 | AF27: =MIN($F$10,AD27+AE27) -> 0 | AG27: =MAX(0,MIN(AD27+AE27-AF27,$D27-(H27+M27+R27+W27+AB27))) -> 0 | AH27: =AF27+AG27 -> 0 | AI27: =ROUND(MAX(0,AI26+AJ26-AM26),2) -> 0 | AJ27: =ROUND(AI27*$E$11/12,2) -> 0 | AK27: =MIN($F$11,AI27+AJ27) -> 0 | AL27: =MAX(0,MIN(AI27+AJ27-AK27,$D27-(H27+M27+R27+W27+AB27+AG27))) -> 0 | AM27: =AK27+AL27 -> 0 | AN27: =ROUND(MAX(0,AN26+AO26-AR26),2) -> 0 | AO27: =ROUND(AN27*$E$12/12,2) -> 0 | AP27: =MIN($F$12,AN27+AO27) -> 0 | AQ27: =MAX(0,MIN(AN27+AO27-AP27,$D27-(H27+M27+R27+W27+AB27+AG27+AL27))) -> 0 | AR27: =AP27+AQ27 -> 0 | AS27: =ROUND(MAX(0,AS26+AT26-AW26),2) -> 0 | AT27: =ROUND(AS27*$E$13/12,2) -> 0 | AU27: =MIN($F$13,AS27+AT27) -> 0 | AV27: =MAX(0,MIN(AS27+AT27-AU27,$D27-(H27+M27+R27+W27+AB27+AG27+AL27+AQ27))) -> 0 | AW27: =AU27+AV27 -> 0 | AX27: =ROUND(MAX(0,AX26+AY26-BB26),2) -> 0 | AY27: =ROUND(AX27*$E$14/12,2) -> 0 | AZ27: =MIN($F$14,AX27+AY27) -> 0 | BA27: =MAX(0,MIN(AX27+AY27-AZ27,$D27-(H27+M27+R27+W27+AB27+AG27+AL27+AQ27+AV27))) -> 0 | BB27: =AZ27+BA27 -> 0 | BC27: =I27+N27+S27+X27+AC27+AH27+AM27+AR27+AW27+BB27 -> 5822 | BD27: =ROUND((E27+F27-I27)+(J27+K27-N27)+(O27+P27-S27)+(T27+U27-X27)+(Y27+Z27-AC27)+(AD27+AE27-AH27)+(AI27+AJ27-AM27)+(AN27+AO27-AR27)+(AS27+AT27-AW27)+(AX27+AY27-BB27),2) -> 76104.46 | BE27: =IF(H27>0.005,$C$5,IF(M27>0.005,$C$6,IF(R27>0.005,$C$7,IF(W27>0.005,$C$8,IF(AB27>0.005,$C$9,IF(AG27>0.005,$C$10,IF(AL27>0.005,$C$11,IF(AQ27>0.005,$C$12,IF(AV27>0.005,$C$13,IF(BA27>0.005,$C$14,"")))))))))) -> 网贷X
A28: 5 | B28: =EDATE($C$17,A28-1) -> 46447 | C28: =G28+L28+Q28+V28+AA28+AF28+AK28+AP28+AU28+AZ28 -> 4822 | D28: =MAX(0,$C$16-C28) -> 1000 | E28: =ROUND(MAX(0,E27+F27-I27),2) -> 17375.03 | F28: =ROUND(E28*$E$5/12,2) -> 347.5 | G28: =MIN($F$5,E28+F28) -> 1350 | H28: =MAX(0,MIN(E28+F28-G28,$D28)) -> 1000 | I28: =G28+H28 -> 2350 | J28: =ROUND(MAX(0,J27+K27-N27),2) -> 32559.1 | K28: =ROUND(J28*$E$6/12,2) -> 488.39 | L28: =MIN($F$6,J28+K28) -> 1900 | M28: =MAX(0,MIN(J28+K28-L28,$D28-(H28))) -> 0 | N28: =L28+M28 -> 1900 | O28: =ROUND(MAX(0,O27+P27-S27),2) -> 8170.33 | P28: =ROUND(O28*$E$7/12,2) -> 88.51 | Q28: =MIN($F$7,O28+P28) -> 1072 | R28: =MAX(0,MIN(O28+P28-Q28,$D28-(H28+M28))) -> 0 | S28: =Q28+R28 -> 1072 | T28: =ROUND(MAX(0,T27+U27-X27),2) -> 18000 | U28: =ROUND(T28*$E$8/12,2) -> 0 | V28: =MIN($F$8,T28+U28) -> 500 | W28: =MAX(0,MIN(T28+U28-V28,$D28-(H28+M28+R28))) -> 0 | X28: =V28+W28 -> 500 | Y28: =ROUND(MAX(0,Y27+Z27-AC27),2) -> 0 | Z28: =ROUND(Y28*$E$9/12,2) -> 0 | AA28: =MIN($F$9,Y28+Z28) -> 0 | AB28: =MAX(0,MIN(Y28+Z28-AA28,$D28-(H28+M28+R28+W28))) -> 0 | AC28: =AA28+AB28 -> 0 | AD28: =ROUND(MAX(0,AD27+AE27-AH27),2) -> 0 | AE28: =ROUND(AD28*$E$10/12,2) -> 0 | AF28: =MIN($F$10,AD28+AE28) -> 0 | AG28: =MAX(0,MIN(AD28+AE28-AF28,$D28-(H28+M28+R28+W28+AB28))) -> 0 | AH28: =AF28+AG28 -> 0 | AI28: =ROUND(MAX(0,AI27+AJ27-AM27),2) -> 0 | AJ28: =ROUND(AI28*$E$11/12,2) -> 0 | AK28: =MIN($F$11,AI28+AJ28) -> 0 | AL28: =MAX(0,MIN(AI28+AJ28-AK28,$D28-(H28+M28+R28+W28+AB28+AG28))) -> 0 | AM28: =AK28+AL28 -> 0 | AN28: =ROUND(MAX(0,AN27+AO27-AR27),2) -> 0 | AO28: =ROUND(AN28*$E$12/12,2) -> 0 | AP28: =MIN($F$12,AN28+AO28) -> 0 | AQ28: =MAX(0,MIN(AN28+AO28-AP28,$D28-(H28+M28+R28+W28+AB28+AG28+AL28))) -> 0 | AR28: =AP28+AQ28 -> 0 | AS28: =ROUND(MAX(0,AS27+AT27-AW27),2) -> 0 | AT28: =ROUND(AS28*$E$13/12,2) -> 0 | AU28: =MIN($F$13,AS28+AT28) -> 0 | AV28: =MAX(0,MIN(AS28+AT28-AU28,$D28-(H28+M28+R28+W28+AB28+AG28+AL28+AQ28))) -> 0 | AW28: =AU28+AV28 -> 0 | AX28: =ROUND(MAX(0,AX27+AY27-BB27),2) -> 0 | AY28: =ROUND(AX28*$E$14/12,2) -> 0 | AZ28: =MIN($F$14,AX28+AY28) -> 0 | BA28: =MAX(0,MIN(AX28+AY28-AZ28,$D28-(H28+M28+R28+W28+AB28+AG28+AL28+AQ28+AV28))) -> 0 | BB28: =AZ28+BA28 -> 0 | BC28: =I28+N28+S28+X28+AC28+AH28+AM28+AR28+AW28+BB28 -> 5822 | BD28: =ROUND((E28+F28-I28)+(J28+K28-N28)+(O28+P28-S28)+(T28+U28-X28)+(Y28+Z28-AC28)+(AD28+AE28-AH28)+(AI28+AJ28-AM28)+(AN28+AO28-AR28)+(AS28+AT28-AW28)+(AX28+AY28-BB28),2) -> 71206.86 | BE28: =IF(H28>0.005,$C$5,IF(M28>0.005,$C$6,IF(R28>0.005,$C$7,IF(W28>0.005,$C$8,IF(AB28>0.005,$C$9,IF(AG28>0.005,$C$10,IF(AL28>0.005,$C$11,IF(AQ28>0.005,$C$12,IF(AV28>0.005,$C$13,IF(BA28>0.005,$C$14,"")))))))))) -> 网贷X
A29: 6 | B29: =EDATE($C$17,A29-1) -> 46478 | C29: =G29+L29+Q29+V29+AA29+AF29+AK29+AP29+AU29+AZ29 -> 4822 | D29: =MAX(0,$C$16-C29) -> 1000 | E29: =ROUND(MAX(0,E28+F28-I28),2) -> 15372.53 | F29: =ROUND(E29*$E$5/12,2) -> 307.45 | G29: =MIN($F$5,E29+F29) -> 1350 | H29: =MAX(0,MIN(E29+F29-G29,$D29)) -> 1000 | I29: =G29+H29 -> 2350 | J29: =ROUND(MAX(0,J28+K28-N28),2) -> 31147.49 | K29: =ROUND(J29*$E$6/12,2) -> 467.21 | L29: =MIN($F$6,J29+K29) -> 1900 | M29: =MAX(0,MIN(J29+K29-L29,$D29-(H29))) -> 0 | N29: =L29+M29 -> 1900 | O29: =ROUND(MAX(0,O28+P28-S28),2) -> 7186.84 | P29: =ROUND(O29*$E$7/12,2) -> 77.86 | Q29: =MIN($F$7,O29+P29) -> 1072 | R29: =MAX(0,MIN(O29+P29-Q29,$D29-(H29+M29))) -> 0 | S29: =Q29+R29 -> 1072 | T29: =ROUND(MAX(0,T28+U28-X28),2) -> 17500 | U29: =ROUND(T29*$E$8/12,2) -> 0 | V29: =MIN($F$8,T29+U29) -> 500 | W29: =MAX(0,MIN(T29+U29-V29,$D29-(H29+M29+R29))) -> 0 | X29: =V29+W29 -> 500 | Y29: =ROUND(MAX(0,Y28+Z28-AC28),2) -> 0 | Z29: =ROUND(Y29*$E$9/12,2) -> 0 | AA29: =MIN($F$9,Y29+Z29) -> 0 | AB29: =MAX(0,MIN(Y29+Z29-AA29,$D29-(H29+M29+R29+W29))) -> 0 | AC29: =AA29+AB29 -> 0 | AD29: =ROUND(MAX(0,AD28+AE28-AH28),2) -> 0 | AE29: =ROUND(AD29*$E$10/12,2) -> 0 | AF29: =MIN($F$10,AD29+AE29) -> 0 | AG29: =MAX(0,MIN(AD29+AE29-AF29,$D29-(H29+M29+R29+W29+AB29))) -> 0 | AH29: =AF29+AG29 -> 0 | AI29: =ROUND(MAX(0,AI28+AJ28-AM28),2) -> 0 | AJ29: =ROUND(AI29*$E$11/12,2) -> 0 | AK29: =MIN($F$11,AI29+AJ29) -> 0 | AL29: =MAX(0,MIN(AI29+AJ29-AK29,$D29-(H29+M29+R29+W29+AB29+AG29))) -> 0 | AM29: =AK29+AL29 -> 0 | AN29: =ROUND(MAX(0,AN28+AO28-AR28),2) -> 0 | AO29: =ROUND(AN29*$E$12/12,2) -> 0 | AP29: =MIN($F$12,AN29+AO29) -> 0 | AQ29: =MAX(0,MIN(AN29+AO29-AP29,$D29-(H29+M29+R29+W29+AB29+AG29+AL29))) -> 0 | AR29: =AP29+AQ29 -> 0 | AS29: =ROUND(MAX(0,AS28+AT28-AW28),2) -> 0 | AT29: =ROUND(AS29*$E$13/12,2) -> 0 | AU29: =MIN($F$13,AS29+AT29) -> 0 | AV29: =MAX(0,MIN(AS29+AT29-AU29,$D29-(H29+M29+R29+W29+AB29+AG29+AL29+AQ29))) -> 0 | AW29: =AU29+AV29 -> 0 | AX29: =ROUND(MAX(0,AX28+AY28-BB28),2) -> 0 | AY29: =ROUND(AX29*$E$14/12,2) -> 0 | AZ29: =MIN($F$14,AX29+AY29) -> 0 | BA29: =MAX(0,MIN(AX29+AY29-AZ29,$D29-(H29+M29+R29+W29+AB29+AG29+AL29+AQ29+AV29))) -> 0 | BB29: =AZ29+BA29 -> 0 | BC29: =I29+N29+S29+X29+AC29+AH29+AM29+AR29+AW29+BB29 -> 5822 | BD29: =ROUND((E29+F29-I29)+(J29+K29-N29)+(O29+P29-S29)+(T29+U29-X29)+(Y29+Z29-AC29)+(AD29+AE29-AH29)+(AI29+AJ29-AM29)+(AN29+AO29-AR29)+(AS29+AT29-AW29)+(AX29+AY29-BB29),2) -> 66237.38 | BE29: =IF(H29>0.005,$C$5,IF(M29>0.005,$C$6,IF(R29>0.005,$C$7,IF(W29>0.005,$C$8,IF(AB29>0.005,$C$9,IF(AG29>0.005,$C$10,IF(AL29>0.005,$C$11,IF(AQ29>0.005,$C$12,IF(AV29>0.005,$C$13,IF(BA29>0.005,$C$14,"")))))))))) -> 网贷X
A30: 7 | B30: =EDATE($C$17,A30-1) -> 46508 | C30: =G30+L30+Q30+V30+AA30+AF30+AK30+AP30+AU30+AZ30 -> 4822 | D30: =MAX(0,$C$16-C30) -> 1000 | E30: =ROUND(MAX(0,E29+F29-I29),2) -> 13329.98 | F30: =ROUND(E30*$E$5/12,2) -> 266.6 | G30: =MIN($F$5,E30+F30) -> 1350 | H30: =MAX(0,MIN(E30+F30-G30,$D30)) -> 1000 | I30: =G30+H30 -> 2350 | J30: =ROUND(MAX(0,J29+K29-N29),2) -> 29714.7 | K30: =ROUND(J30*$E$6/12,2) -> 445.72 | L30: =MIN($F$6,J30+K30) -> 1900 | M30: =MAX(0,MIN(J30+K30-L30,$D30-(H30))) -> 0 | N30: =L30+M30 -> 1900 | O30: =ROUND(MAX(0,O29+P29-S29),2) -> 6192.7 | P30: =ROUND(O30*$E$7/12,2) -> 67.09 | Q30: =MIN($F$7,O30+P30) -> 1072 | R30: =MAX(0,MIN(O30+P30-Q30,$D30-(H30+M30))) -> 0 | S30: =Q30+R30 -> 1072 | T30: =ROUND(MAX(0,T29+U29-X29),2) -> 17000 | U30: =ROUND(T30*$E$8/12,2) -> 0 | V30: =MIN($F$8,T30+U30) -> 500 | W30: =MAX(0,MIN(T30+U30-V30,$D30-(H30+M30+R30))) -> 0 | X30: =V30+W30 -> 500 | Y30: =ROUND(MAX(0,Y29+Z29-AC29),2) -> 0 | Z30: =ROUND(Y30*$E$9/12,2) -> 0 | AA30: =MIN($F$9,Y30+Z30) -> 0 | AB30: =MAX(0,MIN(Y30+Z30-AA30,$D30-(H30+M30+R30+W30))) -> 0 | AC30: =AA30+AB30 -> 0 | AD30: =ROUND(MAX(0,AD29+AE29-AH29),2) -> 0 | AE30: =ROUND(AD30*$E$10/12,2) -> 0 | AF30: =MIN($F$10,AD30+AE30) -> 0 | AG30: =MAX(0,MIN(AD30+AE30-AF30,$D30-(H30+M30+R30+W30+AB30))) -> 0 | AH30: =AF30+AG30 -> 0 | AI30: =ROUND(MAX(0,AI29+AJ29-AM29),2) -> 0 | AJ30: =ROUND(AI30*$E$11/12,2) -> 0 | AK30: =MIN($F$11,AI30+AJ30) -> 0 | AL30: =MAX(0,MIN(AI30+AJ30-AK30,$D30-(H30+M30+R30+W30+AB30+AG30))) -> 0 | AM30: =AK30+AL30 -> 0 | AN30: =ROUND(MAX(0,AN29+AO29-AR29),2) -> 0 | AO30: =ROUND(AN30*$E$12/12,2) -> 0 | AP30: =MIN($F$12,AN30+AO30) -> 0 | AQ30: =MAX(0,MIN(AN30+AO30-AP30,$D30-(H30+M30+R30+W30+AB30+AG30+AL30))) -> 0 | AR30: =AP30+AQ30 -> 0 | AS30: =ROUND(MAX(0,AS29+AT29-AW29),2) -> 0 | AT30: =ROUND(AS30*$E$13/12,2) -> 0 | AU30: =MIN($F$13,AS30+AT30) -> 0 | AV30: =MAX(0,MIN(AS30+AT30-AU30,$D30-(H30+M30+R30+W30+AB30+AG30+AL30+AQ30))) -> 0 | AW30: =AU30+AV30 -> 0 | AX30: =ROUND(MAX(0,AX29+AY29-BB29),2) -> 0 | AY30: =ROUND(AX30*$E$14/12,2) -> 0 | AZ30: =MIN($F$14,AX30+AY30) -> 0 | BA30: =MAX(0,MIN(AX30+AY30-AZ30,$D30-(H30+M30+R30+W30+AB30+AG30+AL30+AQ30+AV30))) -> 0 | BB30: =AZ30+BA30 -> 0 | BC30: =I30+N30+S30+X30+AC30+AH30+AM30+AR30+AW30+BB30 -> 5822 | BD30: =ROUND((E30+F30-I30)+(J30+K30-N30)+(O30+P30-S30)+(T30+U30-X30)+(Y30+Z30-AC30)+(AD30+AE30-AH30)+(AI30+AJ30-AM30)+(AN30+AO30-AR30)+(AS30+AT30-AW30)+(AX30+AY30-BB30),2) -> 61194.79 | BE30: =IF(H30>0.005,$C$5,IF(M30>0.005,$C$6,IF(R30>0.005,$C$7,IF(W30>0.005,$C$8,IF(AB30>0.005,$C$9,IF(AG30>0.005,$C$10,IF(AL30>0.005,$C$11,IF(AQ30>0.005,$C$12,IF(AV30>0.005,$C$13,IF(BA30>0.005,$C$14,"")))))))))) -> 网贷X
A31: 8 | B31: =EDATE($C$17,A31-1) -> 46539 | C31: =G31+L31+Q31+V31+AA31+AF31+AK31+AP31+AU31+AZ31 -> 4822 | D31: =MAX(0,$C$16-C31) -> 1000 | E31: =ROUND(MAX(0,E30+F30-I30),2) -> 11246.58 | F31: =ROUND(E31*$E$5/12,2) -> 224.93 | G31: =MIN($F$5,E31+F31) -> 1350 | H31: =MAX(0,MIN(E31+F31-G31,$D31)) -> 1000 | I31: =G31+H31 -> 2350 | J31: =ROUND(MAX(0,J30+K30-N30),2) -> 28260.42 | K31: =ROUND(J31*$E$6/12,2) -> 423.91 | L31: =MIN($F$6,J31+K31) -> 1900 | M31: =MAX(0,MIN(J31+K31-L31,$D31-(H31))) -> 0 | N31: =L31+M31 -> 1900 | O31: =ROUND(MAX(0,O30+P30-S30),2) -> 5187.79 | P31: =ROUND(O31*$E$7/12,2) -> 56.2 | Q31: =MIN($F$7,O31+P31) -> 1072 | R31: =MAX(0,MIN(O31+P31-Q31,$D31-(H31+M31))) -> 0 | S31: =Q31+R31 -> 1072 | T31: =ROUND(MAX(0,T30+U30-X30),2) -> 16500 | U31: =ROUND(T31*$E$8/12,2) -> 0 | V31: =MIN($F$8,T31+U31) -> 500 | W31: =MAX(0,MIN(T31+U31-V31,$D31-(H31+M31+R31))) -> 0 | X31: =V31+W31 -> 500 | Y31: =ROUND(MAX(0,Y30+Z30-AC30),2) -> 0 | Z31: =ROUND(Y31*$E$9/12,2) -> 0 | AA31: =MIN($F$9,Y31+Z31) -> 0 | AB31: =MAX(0,MIN(Y31+Z31-AA31,$D31-(H31+M31+R31+W31))) -> 0 | AC31: =AA31+AB31 -> 0 | AD31: =ROUND(MAX(0,AD30+AE30-AH30),2) -> 0 | AE31: =ROUND(AD31*$E$10/12,2) -> 0 | AF31: =MIN($F$10,AD31+AE31) -> 0 | AG31: =MAX(0,MIN(AD31+AE31-AF31,$D31-(H31+M31+R31+W31+AB31))) -> 0 | AH31: =AF31+AG31 -> 0 | AI31: =ROUND(MAX(0,AI30+AJ30-AM30),2) -> 0 | AJ31: =ROUND(AI31*$E$11/12,2) -> 0 | AK31: =MIN($F$11,AI31+AJ31) -> 0 | AL31: =MAX(0,MIN(AI31+AJ31-AK31,$D31-(H31+M31+R31+W31+AB31+AG31))) -> 0 | AM31: =AK31+AL31 -> 0 | AN31: =ROUND(MAX(0,AN30+AO30-AR30),2) -> 0 | AO31: =ROUND(AN31*$E$12/12,2) -> 0 | AP31: =MIN($F$12,AN31+AO31) -> 0 | AQ31: =MAX(0,MIN(AN31+AO31-AP31,$D31-(H31+M31+R31+W31+AB31+AG31+AL31))) -> 0 | AR31: =AP31+AQ31 -> 0 | AS31: =ROUND(MAX(0,AS30+AT30-AW30),2) -> 0 | AT31: =ROUND(AS31*$E$13/12,2) -> 0 | AU31: =MIN($F$13,AS31+AT31) -> 0 | AV31: =MAX(0,MIN(AS31+AT31-AU31,$D31-(H31+M31+R31+W31+AB31+AG31+AL31+AQ31))) -> 0 | AW31: =AU31+AV31 -> 0 | AX31: =ROUND(MAX(0,AX30+AY30-BB30),2) -> 0 | AY31: =ROUND(AX31*$E$14/12,2) -> 0 | AZ31: =MIN($F$14,AX31+AY31) -> 0 | BA31: =MAX(0,MIN(AX31+AY31-AZ31,$D31-(H31+M31+R31+W31+AB31+AG31+AL31+AQ31+AV31))) -> 0 | BB31: =AZ31+BA31 -> 0 | BC31: =I31+N31+S31+X31+AC31+AH31+AM31+AR31+AW31+BB31 -> 5822 | BD31: =ROUND((E31+F31-I31)+(J31+K31-N31)+(O31+P31-S31)+(T31+U31-X31)+(Y31+Z31-AC31)+(AD31+AE31-AH31)+(AI31+AJ31-AM31)+(AN31+AO31-AR31)+(AS31+AT31-AW31)+(AX31+AY31-BB31),2) -> 56077.83 | BE31: =IF(H31>0.005,$C$5,IF(M31>0.005,$C$6,IF(R31>0.005,$C$7,IF(W31>0.005,$C$8,IF(AB31>0.005,$C$9,IF(AG31>0.005,$C$10,IF(AL31>0.005,$C$11,IF(AQ31>0.005,$C$12,IF(AV31>0.005,$C$13,IF(BA31>0.005,$C$14,"")))))))))) -> 网贷X
A32: 9 | B32: =EDATE($C$17,A32-1) -> 46569 | C32: =G32+L32+Q32+V32+AA32+AF32+AK32+AP32+AU32+AZ32 -> 4822 | D32: =MAX(0,$C$16-C32) -> 1000 | E32: =ROUND(MAX(0,E31+F31-I31),2) -> 9121.51 | F32: =ROUND(E32*$E$5/12,2) -> 182.43 | G32: =MIN($F$5,E32+F32) -> 1350 | H32: =MAX(0,MIN(E32+F32-G32,$D32)) -> 1000 | I32: =G32+H32 -> 2350 | J32: =ROUND(MAX(0,J31+K31-N31),2) -> 26784.33 | K32: =ROUND(J32*$E$6/12,2) -> 401.76 | L32: =MIN($F$6,J32+K32) -> 1900 | M32: =MAX(0,MIN(J32+K32-L32,$D32-(H32))) -> 0 | N32: =L32+M32 -> 1900 | O32: =ROUND(MAX(0,O31+P31-S31),2) -> 4171.99 | P32: =ROUND(O32*$E$7/12,2) -> 45.2 | Q32: =MIN($F$7,O32+P32) -> 1072 | R32: =MAX(0,MIN(O32+P32-Q32,$D32-(H32+M32))) -> 0 | S32: =Q32+R32 -> 1072 | T32: =ROUND(MAX(0,T31+U31-X31),2) -> 16000 | U32: =ROUND(T32*$E$8/12,2) -> 0 | V32: =MIN($F$8,T32+U32) -> 500 | W32: =MAX(0,MIN(T32+U32-V32,$D32-(H32+M32+R32))) -> 0 | X32: =V32+W32 -> 500 | Y32: =ROUND(MAX(0,Y31+Z31-AC31),2) -> 0 | Z32: =ROUND(Y32*$E$9/12,2) -> 0 | AA32: =MIN($F$9,Y32+Z32) -> 0 | AB32: =MAX(0,MIN(Y32+Z32-AA32,$D32-(H32+M32+R32+W32))) -> 0 | AC32: =AA32+AB32 -> 0 | AD32: =ROUND(MAX(0,AD31+AE31-AH31),2) -> 0 | AE32: =ROUND(AD32*$E$10/12,2) -> 0 | AF32: =MIN($F$10,AD32+AE32) -> 0 | AG32: =MAX(0,MIN(AD32+AE32-AF32,$D32-(H32+M32+R32+W32+AB32))) -> 0 | AH32: =AF32+AG32 -> 0 | AI32: =ROUND(MAX(0,AI31+AJ31-AM31),2) -> 0 | AJ32: =ROUND(AI32*$E$11/12,2) -> 0 | AK32: =MIN($F$11,AI32+AJ32) -> 0 | AL32: =MAX(0,MIN(AI32+AJ32-AK32,$D32-(H32+M32+R32+W32+AB32+AG32))) -> 0 | AM32: =AK32+AL32 -> 0 | AN32: =ROUND(MAX(0,AN31+AO31-AR31),2) -> 0 | AO32: =ROUND(AN32*$E$12/12,2) -> 0 | AP32: =MIN($F$12,AN32+AO32) -> 0 | AQ32: =MAX(0,MIN(AN32+AO32-AP32,$D32-(H32+M32+R32+W32+AB32+AG32+AL32))) -> 0 | AR32: =AP32+AQ32 -> 0 | AS32: =ROUND(MAX(0,AS31+AT31-AW31),2) -> 0 | AT32: =ROUND(AS32*$E$13/12,2) -> 0 | AU32: =MIN($F$13,AS32+AT32) -> 0 | AV32: =MAX(0,MIN(AS32+AT32-AU32,$D32-(H32+M32+R32+W32+AB32+AG32+AL32+AQ32))) -> 0 | AW32: =AU32+AV32 -> 0 | AX32: =ROUND(MAX(0,AX31+AY31-BB31),2) -> 0 | AY32: =ROUND(AX32*$E$14/12,2) -> 0 | AZ32: =MIN($F$14,AX32+AY32) -> 0 | BA32: =MAX(0,MIN(AX32+AY32-AZ32,$D32-(H32+M32+R32+W32+AB32+AG32+AL32+AQ32+AV32))) -> 0 | BB32: =AZ32+BA32 -> 0 | BC32: =I32+N32+S32+X32+AC32+AH32+AM32+AR32+AW32+BB32 -> 5822 | BD32: =ROUND((E32+F32-I32)+(J32+K32-N32)+(O32+P32-S32)+(T32+U32-X32)+(Y32+Z32-AC32)+(AD32+AE32-AH32)+(AI32+AJ32-AM32)+(AN32+AO32-AR32)+(AS32+AT32-AW32)+(AX32+AY32-BB32),2) -> 50885.22 | BE32: =IF(H32>0.005,$C$5,IF(M32>0.005,$C$6,IF(R32>0.005,$C$7,IF(W32>0.005,$C$8,IF(AB32>0.005,$C$9,IF(AG32>0.005,$C$10,IF(AL32>0.005,$C$11,IF(AQ32>0.005,$C$12,IF(AV32>0.005,$C$13,IF(BA32>0.005,$C$14,"")))))))))) -> 网贷X
A33: 10 | B33: =EDATE($C$17,A33-1) -> 46600 | C33: =G33+L33+Q33+V33+AA33+AF33+AK33+AP33+AU33+AZ33 -> 4822 | D33: =MAX(0,$C$16-C33) -> 1000 | E33: =ROUND(MAX(0,E32+F32-I32),2) -> 6953.94 | F33: =ROUND(E33*$E$5/12,2) -> 139.08 | G33: =MIN($F$5,E33+F33) -> 1350 | H33: =MAX(0,MIN(E33+F33-G33,$D33)) -> 1000 | I33: =G33+H33 -> 2350 | J33: =ROUND(MAX(0,J32+K32-N32),2) -> 25286.09 | K33: =ROUND(J33*$E$6/12,2) -> 379.29 | L33: =MIN($F$6,J33+K33) -> 1900 | M33: =MAX(0,MIN(J33+K33-L33,$D33-(H33))) -> 0 | N33: =L33+M33 -> 1900 | O33: =ROUND(MAX(0,O32+P32-S32),2) -> 3145.19 | P33: =ROUND(O33*$E$7/12,2) -> 34.07 | Q33: =MIN($F$7,O33+P33) -> 1072 | R33: =MAX(0,MIN(O33+P33-Q33,$D33-(H33+M33))) -> 0 | S33: =Q33+R33 -> 1072 | T33: =ROUND(MAX(0,T32+U32-X32),2) -> 15500 | U33: =ROUND(T33*$E$8/12,2) -> 0 | V33: =MIN($F$8,T33+U33) -> 500 | W33: =MAX(0,MIN(T33+U33-V33,$D33-(H33+M33+R33))) -> 0 | X33: =V33+W33 -> 500 | Y33: =ROUND(MAX(0,Y32+Z32-AC32),2) -> 0 | Z33: =ROUND(Y33*$E$9/12,2) -> 0 | AA33: =MIN($F$9,Y33+Z33) -> 0 | AB33: =MAX(0,MIN(Y33+Z33-AA33,$D33-(H33+M33+R33+W33))) -> 0 | AC33: =AA33+AB33 -> 0 | AD33: =ROUND(MAX(0,AD32+AE32-AH32),2) -> 0 | AE33: =ROUND(AD33*$E$10/12,2) -> 0 | AF33: =MIN($F$10,AD33+AE33) -> 0 | AG33: =MAX(0,MIN(AD33+AE33-AF33,$D33-(H33+M33+R33+W33+AB33))) -> 0 | AH33: =AF33+AG33 -> 0 | AI33: =ROUND(MAX(0,AI32+AJ32-AM32),2) -> 0 | AJ33: =ROUND(AI33*$E$11/12,2) -> 0 | AK33: =MIN($F$11,AI33+AJ33) -> 0 | AL33: =MAX(0,MIN(AI33+AJ33-AK33,$D33-(H33+M33+R33+W33+AB33+AG33))) -> 0 | AM33: =AK33+AL33 -> 0 | AN33: =ROUND(MAX(0,AN32+AO32-AR32),2) -> 0 | AO33: =ROUND(AN33*$E$12/12,2) -> 0 | AP33: =MIN($F$12,AN33+AO33) -> 0 | AQ33: =MAX(0,MIN(AN33+AO33-AP33,$D33-(H33+M33+R33+W33+AB33+AG33+AL33))) -> 0 | AR33: =AP33+AQ33 -> 0 | AS33: =ROUND(MAX(0,AS32+AT32-AW32),2) -> 0 | AT33: =ROUND(AS33*$E$13/12,2) -> 0 | AU33: =MIN($F$13,AS33+AT33) -> 0 | AV33: =MAX(0,MIN(AS33+AT33-AU33,$D33-(H33+M33+R33+W33+AB33+AG33+AL33+AQ33))) -> 0 | AW33: =AU33+AV33 -> 0 | AX33: =ROUND(MAX(0,AX32+AY32-BB32),2) -> 0 | AY33: =ROUND(AX33*$E$14/12,2) -> 0 | AZ33: =MIN($F$14,AX33+AY33) -> 0 | BA33: =MAX(0,MIN(AX33+AY33-AZ33,$D33-(H33+M33+R33+W33+AB33+AG33+AL33+AQ33+AV33))) -> 0 | BB33: =AZ33+BA33 -> 0 | BC33: =I33+N33+S33+X33+AC33+AH33+AM33+AR33+AW33+BB33 -> 5822 | BD33: =ROUND((E33+F33-I33)+(J33+K33-N33)+(O33+P33-S33)+(T33+U33-X33)+(Y33+Z33-AC33)+(AD33+AE33-AH33)+(AI33+AJ33-AM33)+(AN33+AO33-AR33)+(AS33+AT33-AW33)+(AX33+AY33-BB33),2) -> 45615.66 | BE33: =IF(H33>0.005,$C$5,IF(M33>0.005,$C$6,IF(R33>0.005,$C$7,IF(W33>0.005,$C$8,IF(AB33>0.005,$C$9,IF(AG33>0.005,$C$10,IF(AL33>0.005,$C$11,IF(AQ33>0.005,$C$12,IF(AV33>0.005,$C$13,IF(BA33>0.005,$C$14,"")))))))))) -> 网贷X
A34: 11 | B34: =EDATE($C$17,A34-1) -> 46631 | C34: =G34+L34+Q34+V34+AA34+AF34+AK34+AP34+AU34+AZ34 -> 4822 | D34: =MAX(0,$C$16-C34) -> 1000 | E34: =ROUND(MAX(0,E33+F33-I33),2) -> 4743.02 | F34: =ROUND(E34*$E$5/12,2) -> 94.86 | G34: =MIN($F$5,E34+F34) -> 1350 | H34: =MAX(0,MIN(E34+F34-G34,$D34)) -> 1000 | I34: =G34+H34 -> 2350 | J34: =ROUND(MAX(0,J33+K33-N33),2) -> 23765.38 | K34: =ROUND(J34*$E$6/12,2) -> 356.48 | L34: =MIN($F$6,J34+K34) -> 1900 | M34: =MAX(0,MIN(J34+K34-L34,$D34-(H34))) -> 0 | N34: =L34+M34 -> 1900 | O34: =ROUND(MAX(0,O33+P33-S33),2) -> 2107.26 | P34: =ROUND(O34*$E$7/12,2) -> 22.83 | Q34: =MIN($F$7,O34+P34) -> 1072 | R34: =MAX(0,MIN(O34+P34-Q34,$D34-(H34+M34))) -> 0 | S34: =Q34+R34 -> 1072 | T34: =ROUND(MAX(0,T33+U33-X33),2) -> 15000 | U34: =ROUND(T34*$E$8/12,2) -> 0 | V34: =MIN($F$8,T34+U34) -> 500 | W34: =MAX(0,MIN(T34+U34-V34,$D34-(H34+M34+R34))) -> 0 | X34: =V34+W34 -> 500 | Y34: =ROUND(MAX(0,Y33+Z33-AC33),2) -> 0 | Z34: =ROUND(Y34*$E$9/12,2) -> 0 | AA34: =MIN($F$9,Y34+Z34) -> 0 | AB34: =MAX(0,MIN(Y34+Z34-AA34,$D34-(H34+M34+R34+W34))) -> 0 | AC34: =AA34+AB34 -> 0 | AD34: =ROUND(MAX(0,AD33+AE33-AH33),2) -> 0 | AE34: =ROUND(AD34*$E$10/12,2) -> 0 | AF34: =MIN($F$10,AD34+AE34) -> 0 | AG34: =MAX(0,MIN(AD34+AE34-AF34,$D34-(H34+M34+R34+W34+AB34))) -> 0 | AH34: =AF34+AG34 -> 0 | AI34: =ROUND(MAX(0,AI33+AJ33-AM33),2) -> 0 | AJ34: =ROUND(AI34*$E$11/12,2) -> 0 | AK34: =MIN($F$11,AI34+AJ34) -> 0 | AL34: =MAX(0,MIN(AI34+AJ34-AK34,$D34-(H34+M34+R34+W34+AB34+AG34))) -> 0 | AM34: =AK34+AL34 -> 0 | AN34: =ROUND(MAX(0,AN33+AO33-AR33),2) -> 0 | AO34: =ROUND(AN34*$E$12/12,2) -> 0 | AP34: =MIN($F$12,AN34+AO34) -> 0 | AQ34: =MAX(0,MIN(AN34+AO34-AP34,$D34-(H34+M34+R34+W34+AB34+AG34+AL34))) -> 0 | AR34: =AP34+AQ34 -> 0 | AS34: =ROUND(MAX(0,AS33+AT33-AW33),2) -> 0 | AT34: =ROUND(AS34*$E$13/12,2) -> 0 | AU34: =MIN($F$13,AS34+AT34) -> 0 | AV34: =MAX(0,MIN(AS34+AT34-AU34,$D34-(H34+M34+R34+W34+AB34+AG34+AL34+AQ34))) -> 0 | AW34: =AU34+AV34 -> 0 | AX34: =ROUND(MAX(0,AX33+AY33-BB33),2) -> 0 | AY34: =ROUND(AX34*$E$14/12,2) -> 0 | AZ34: =MIN($F$14,AX34+AY34) -> 0 | BA34: =MAX(0,MIN(AX34+AY34-AZ34,$D34-(H34+M34+R34+W34+AB34+AG34+AL34+AQ34+AV34))) -> 0 | BB34: =AZ34+BA34 -> 0 | BC34: =I34+N34+S34+X34+AC34+AH34+AM34+AR34+AW34+BB34 -> 5822 | BD34: =ROUND((E34+F34-I34)+(J34+K34-N34)+(O34+P34-S34)+(T34+U34-X34)+(Y34+Z34-AC34)+(AD34+AE34-AH34)+(AI34+AJ34-AM34)+(AN34+AO34-AR34)+(AS34+AT34-AW34)+(AX34+AY34-BB34),2) -> 40267.83 | BE34: =IF(H34>0.005,$C$5,IF(M34>0.005,$C$6,IF(R34>0.005,$C$7,IF(W34>0.005,$C$8,IF(AB34>0.005,$C$9,IF(AG34>0.005,$C$10,IF(AL34>0.005,$C$11,IF(AQ34>0.005,$C$12,IF(AV34>0.005,$C$13,IF(BA34>0.005,$C$14,"")))))))))) -> 网贷X
A35: 12 | B35: =EDATE($C$17,A35-1) -> 46661 | C35: =G35+L35+Q35+V35+AA35+AF35+AK35+AP35+AU35+AZ35 -> 4819.55 | D35: =MAX(0,$C$16-C35) -> 1002.45 | E35: =ROUND(MAX(0,E34+F34-I34),2) -> 2487.88 | F35: =ROUND(E35*$E$5/12,2) -> 49.76 | G35: =MIN($F$5,E35+F35) -> 1350 | H35: =MAX(0,MIN(E35+F35-G35,$D35)) -> 1002.45 | I35: =G35+H35 -> 2352.45 | J35: =ROUND(MAX(0,J34+K34-N34),2) -> 22221.86 | K35: =ROUND(J35*$E$6/12,2) -> 333.33 | L35: =MIN($F$6,J35+K35) -> 1900 | M35: =MAX(0,MIN(J35+K35-L35,$D35-(H35))) -> 0 | N35: =L35+M35 -> 1900 | O35: =ROUND(MAX(0,O34+P34-S34),2) -> 1058.09 | P35: =ROUND(O35*$E$7/12,2) -> 11.46 | Q35: =MIN($F$7,O35+P35) -> 1069.55 | R35: =MAX(0,MIN(O35+P35-Q35,$D35-(H35+M35))) -> 0 | S35: =Q35+R35 -> 1069.55 | T35: =ROUND(MAX(0,T34+U34-X34),2) -> 14500 | U35: =ROUND(T35*$E$8/12,2) -> 0 | V35: =MIN($F$8,T35+U35) -> 500 | W35: =MAX(0,MIN(T35+U35-V35,$D35-(H35+M35+R35))) -> 0 | X35: =V35+W35 -> 500 | Y35: =ROUND(MAX(0,Y34+Z34-AC34),2) -> 0 | Z35: =ROUND(Y35*$E$9/12,2) -> 0 | AA35: =MIN($F$9,Y35+Z35) -> 0 | AB35: =MAX(0,MIN(Y35+Z35-AA35,$D35-(H35+M35+R35+W35))) -> 0 | AC35: =AA35+AB35 -> 0 | AD35: =ROUND(MAX(0,AD34+AE34-AH34),2) -> 0 | AE35: =ROUND(AD35*$E$10/12,2) -> 0 | AF35: =MIN($F$10,AD35+AE35) -> 0 | AG35: =MAX(0,MIN(AD35+AE35-AF35,$D35-(H35+M35+R35+W35+AB35))) -> 0 | AH35: =AF35+AG35 -> 0 | AI35: =ROUND(MAX(0,AI34+AJ34-AM34),2) -> 0 | AJ35: =ROUND(AI35*$E$11/12,2) -> 0 | AK35: =MIN($F$11,AI35+AJ35) -> 0 | AL35: =MAX(0,MIN(AI35+AJ35-AK35,$D35-(H35+M35+R35+W35+AB35+AG35))) -> 0 | AM35: =AK35+AL35 -> 0 | AN35: =ROUND(MAX(0,AN34+AO34-AR34),2) -> 0 | AO35: =ROUND(AN35*$E$12/12,2) -> 0 | AP35: =MIN($F$12,AN35+AO35) -> 0 | AQ35: =MAX(0,MIN(AN35+AO35-AP35,$D35-(H35+M35+R35+W35+AB35+AG35+AL35))) -> 0 | AR35: =AP35+AQ35 -> 0 | AS35: =ROUND(MAX(0,AS34+AT34-AW34),2) -> 0 | AT35: =ROUND(AS35*$E$13/12,2) -> 0 | AU35: =MIN($F$13,AS35+AT35) -> 0 | AV35: =MAX(0,MIN(AS35+AT35-AU35,$D35-(H35+M35+R35+W35+AB35+AG35+AL35+AQ35))) -> 0 | AW35: =AU35+AV35 -> 0 | AX35: =ROUND(MAX(0,AX34+AY34-BB34),2) -> 0 | AY35: =ROUND(AX35*$E$14/12,2) -> 0 | AZ35: =MIN($F$14,AX35+AY35) -> 0 | BA35: =MAX(0,MIN(AX35+AY35-AZ35,$D35-(H35+M35+R35+W35+AB35+AG35+AL35+AQ35+AV35))) -> 0 | BB35: =AZ35+BA35 -> 0 | BC35: =I35+N35+S35+X35+AC35+AH35+AM35+AR35+AW35+BB35 -> 5822 | BD35: =ROUND((E35+F35-I35)+(J35+K35-N35)+(O35+P35-S35)+(T35+U35-X35)+(Y35+Z35-AC35)+(AD35+AE35-AH35)+(AI35+AJ35-AM35)+(AN35+AO35-AR35)+(AS35+AT35-AW35)+(AX35+AY35-BB35),2) -> 34840.38 | BE35: =IF(H35>0.005,$C$5,IF(M35>0.005,$C$6,IF(R35>0.005,$C$7,IF(W35>0.005,$C$8,IF(AB35>0.005,$C$9,IF(AG35>0.005,$C$10,IF(AL35>0.005,$C$11,IF(AQ35>0.005,$C$12,IF(AV35>0.005,$C$13,IF(BA35>0.005,$C$14,"")))))))))) -> 网贷X
A36: 13 | B36: =EDATE($C$17,A36-1) -> 46692 | C36: =G36+L36+Q36+V36+AA36+AF36+AK36+AP36+AU36+AZ36 -> 2588.89 | D36: =MAX(0,$C$16-C36) -> 3233.11 | E36: =ROUND(MAX(0,E35+F35-I35),2) -> 185.19 | F36: =ROUND(E36*$E$5/12,2) -> 3.7 | G36: =MIN($F$5,E36+F36) -> 188.89 | H36: =MAX(0,MIN(E36+F36-G36,$D36)) -> 0 | I36: =G36+H36 -> 188.89 | J36: =ROUND(MAX(0,J35+K35-N35),2) -> 20655.19 | K36: =ROUND(J36*$E$6/12,2) -> 309.83 | L36: =MIN($F$6,J36+K36) -> 1900 | M36: =MAX(0,MIN(J36+K36-L36,$D36-(H36))) -> 3233.11 | N36: =L36+M36 -> 5133.11 | O36: =ROUND(MAX(0,O35+P35-S35),2) -> 0 | P36: =ROUND(O36*$E$7/12,2) -> 0 | Q36: =MIN($F$7,O36+P36) -> 0 | R36: =MAX(0,MIN(O36+P36-Q36,$D36-(H36+M36))) -> 0 | S36: =Q36+R36 -> 0 | T36: =ROUND(MAX(0,T35+U35-X35),2) -> 14000 | U36: =ROUND(T36*$E$8/12,2) -> 0 | V36: =MIN($F$8,T36+U36) -> 500 | W36: =MAX(0,MIN(T36+U36-V36,$D36-(H36+M36+R36))) -> 0 | X36: =V36+W36 -> 500 | Y36: =ROUND(MAX(0,Y35+Z35-AC35),2) -> 0 | Z36: =ROUND(Y36*$E$9/12,2) -> 0 | AA36: =MIN($F$9,Y36+Z36) -> 0 | AB36: =MAX(0,MIN(Y36+Z36-AA36,$D36-(H36+M36+R36+W36))) -> 0 | AC36: =AA36+AB36 -> 0 | AD36: =ROUND(MAX(0,AD35+AE35-AH35),2) -> 0 | AE36: =ROUND(AD36*$E$10/12,2) -> 0 | AF36: =MIN($F$10,AD36+AE36) -> 0 | AG36: =MAX(0,MIN(AD36+AE36-AF36,$D36-(H36+M36+R36+W36+AB36))) -> 0 | AH36: =AF36+AG36 -> 0 | AI36: =ROUND(MAX(0,AI35+AJ35-AM35),2) -> 0 | AJ36: =ROUND(AI36*$E$11/12,2) -> 0 | AK36: =MIN($F$11,AI36+AJ36) -> 0 | AL36: =MAX(0,MIN(AI36+AJ36-AK36,$D36-(H36+M36+R36+W36+AB36+AG36))) -> 0 | AM36: =AK36+AL36 -> 0 | AN36: =ROUND(MAX(0,AN35+AO35-AR35),2) -> 0 | AO36: =ROUND(AN36*$E$12/12,2) -> 0 | AP36: =MIN($F$12,AN36+AO36) -> 0 | AQ36: =MAX(0,MIN(AN36+AO36-AP36,$D36-(H36+M36+R36+W36+AB36+AG36+AL36))) -> 0 | AR36: =AP36+AQ36 -> 0 | AS36: =ROUND(MAX(0,AS35+AT35-AW35),2) -> 0 | AT36: =ROUND(AS36*$E$13/12,2) -> 0 | AU36: =MIN($F$13,AS36+AT36) -> 0 | AV36: =MAX(0,MIN(AS36+AT36-AU36,$D36-(H36+M36+R36+W36+AB36+AG36+AL36+AQ36))) -> 0 | AW36: =AU36+AV36 -> 0 | AX36: =ROUND(MAX(0,AX35+AY35-BB35),2) -> 0 | AY36: =ROUND(AX36*$E$14/12,2) -> 0 | AZ36: =MIN($F$14,AX36+AY36) -> 0 | BA36: =MAX(0,MIN(AX36+AY36-AZ36,$D36-(H36+M36+R36+W36+AB36+AG36+AL36+AQ36+AV36))) -> 0 | BB36: =AZ36+BA36 -> 0 | BC36: =I36+N36+S36+X36+AC36+AH36+AM36+AR36+AW36+BB36 -> 5822 | BD36: =ROUND((E36+F36-I36)+(J36+K36-N36)+(O36+P36-S36)+(T36+U36-X36)+(Y36+Z36-AC36)+(AD36+AE36-AH36)+(AI36+AJ36-AM36)+(AN36+AO36-AR36)+(AS36+AT36-AW36)+(AX36+AY36-BB36),2) -> 29331.91 | BE36: =IF(H36>0.005,$C$5,IF(M36>0.005,$C$6,IF(R36>0.005,$C$7,IF(W36>0.005,$C$8,IF(AB36>0.005,$C$9,IF(AG36>0.005,$C$10,IF(AL36>0.005,$C$11,IF(AQ36>0.005,$C$12,IF(AV36>0.005,$C$13,IF(BA36>0.005,$C$14,"")))))))))) -> 信用卡A
... A263: 240 | B263: =EDATE($C$17,A263-1) -> 53601 | C263: =G263+L263+Q263+V263+AA263+AF263+AK263+AP263+AU263+AZ263 -> 0 | D263: =MAX(0,$C$16-C263) -> 5822 | E263: =ROUND(MAX(0,E262+F262-I262),2) -> 0 | F263: =ROUND(E263*$E$5/12,2) -> 0 | G263: =MIN($F$5,E263+F263) -> 0 | H263: =MAX(0,MIN(E263+F263-G263,$D263)) -> 0 | I263: =G263+H263 -> 0 | J263: =ROUND(MAX(0,J262+K262-N262),2) -> 0 | K263: =ROUND(J263*$E$6/12,2) -> 0 | L263: =MIN($F$6,J263+K263) -> 0 | M263: =MAX(0,MIN(J263+K263-L263,$D263-(H263))) -> 0 | N263: =L263+M263 -> 0 | O263: =ROUND(MAX(0,O262+P262-S262),2) -> 0 | P263: =ROUND(O263*$E$7/12,2) -> 0 | Q263: =MIN($F$7,O263+P263) -> 0 | R263: =MAX(0,MIN(O263+P263-Q263,$D263-(H263+M263))) -> 0 | S263: =Q263+R263 -> 0 | T263: =ROUND(MAX(0,T262+U262-X262),2) -> 0 | U263: =ROUND(T263*$E$8/12,2) -> 0 | V263: =MIN($F$8,T263+U263) -> 0 | W263: =MAX(0,MIN(T263+U263-V263,$D263-(H263+M263+R263))) -> 0 | X263: =V263+W263 -> 0 | Y263: =ROUND(MAX(0,Y262+Z262-AC262),2) -> 0 | Z263: =ROUND(Y263*$E$9/12,2) -> 0 | AA263: =MIN($F$9,Y263+Z263) -> 0 | AB263: =MAX(0,MIN(Y263+Z263-AA263,$D263-(H263+M263+R263+W263))) -> 0 | AC263: =AA263+AB263 -> 0 | AD263: =ROUND(MAX(0,AD262+AE262-AH262),2) -> 0 | AE263: =ROUND(AD263*$E$10/12,2) -> 0 | AF263: =MIN($F$10,AD263+AE263) -> 0 | AG263: =MAX(0,MIN(AD263+AE263-AF263,$D263-(H263+M263+R263+W263+AB263))) -> 0 | AH263: =AF263+AG263 -> 0 | AI263: =ROUND(MAX(0,AI262+AJ262-AM262),2) -> 0 | AJ263: =ROUND(AI263*$E$11/12,2) -> 0 | AK263: =MIN($F$11,AI263+AJ263) -> 0 | AL263: =MAX(0,MIN(AI263+AJ263-AK263,$D263-(H263+M263+R263+W263+AB263+AG263))) -> 0 | AM263: =AK263+AL263 -> 0 | AN263: =ROUND(MAX(0,AN262+AO262-AR262),2) -> 0 | AO263: =ROUND(AN263*$E$12/12,2) -> 0 | AP263: =MIN($F$12,AN263+AO263) -> 0 | AQ263: =MAX(0,MIN(AN263+AO263-AP263,$D263-(H263+M263+R263+W263+AB263+AG263+AL263))) -> 0 | AR263: =AP263+AQ263 -> 0 | AS263: =ROUND(MAX(0,AS262+AT262-AW262),2) -> 0 | AT263: =ROUND(AS263*$E$13/12,2) -> 0 | AU263: =MIN($F$13,AS263+AT263) -> 0 | AV263: =MAX(0,MIN(AS263+AT263-AU263,$D263-(H263+M263+R263+W263+AB263+AG263+AL263+AQ263))) -> 0 | AW263: =AU263+AV263 -> 0 | AX263: =ROUND(MAX(0,AX262+AY262-BB262),2) -> 0 | AY263: =ROUND(AX263*$E$14/12,2) -> 0 | AZ263: =MIN($F$14,AX263+AY263) -> 0 | BA263: =MAX(0,MIN(AX263+AY263-AZ263,$D263-(H263+M263+R263+W263+AB263+AG263+AL263+AQ263+AV263))) -> 0 | BB263: =AZ263+BA263 -> 0 | BC263: =I263+N263+S263+X263+AC263+AH263+AM263+AR263+AW263+BB263 -> 0 | BD263: =ROUND((E263+F263-I263)+(J263+K263-N263)+(O263+P263-S263)+(T263+U263-X263)+(Y263+Z263-AC263)+(AD263+AE263-AH263)+(AI263+AJ263-AM263)+(AN263+AO263-AR263)+(AS263+AT263-AW263)+(AX263+AY263-BB263),2) -> 0 | BE263: =IF(H263>0.005,$C$5,IF(M263>0.005,$C$6,IF(R263>0.005,$C$7,IF(W263>0.005,$C$8,IF(AB263>0.005,$C$9,IF(AG263>0.005,$C$10,IF(AL263>0.005,$C$11,IF(AQ263>0.005,$C$12,IF(AV263>0.005,$C$13,IF(BA263>0.005,$C$14,""))))))))))
